{
  "1306.T": {
    "ticker": "1306.T",
    "bullish_prob": 0.7185,
    "bearish_prob": 0.2815,
    "prediction": "bullish",
    "confidence": 0.437,
    "model_accuracy": 0.5780898876404494,
    "model_trained_at": "2026-06-30T14:41:38.110655",
    "feature_importance": {
      "vol_ratio_5": 346.0,
      "ret_5": 286.0,
      "rsi_9": 271.0,
      "vol_ratio_20": 266.0,
      "ma_ratio_10": 254.0,
      "ret_3": 252.0,
      "minute": 248.0,
      "ret_10": 247.0,
      "vwap_ratio": 237.0,
      "high_low_ratio": 234.0,
      "atr_ratio": 229.0,
      "ret_1": 227.0,
      "bb_width": 226.0,
      "rsi_14": 211.0,
      "ma_ratio_5": 198.0,
      "macd_signal": 198.0,
      "macd_hist": 195.0,
      "time_in_session": 183.0,
      "body_ratio": 176.0,
      "ma_ratio_25": 173.0
    },
    "name": "ＮＥＸＴ　ＦＵＮＤＳ　ＴＯＰＩＸ連動型上場投信",
    "price": 423.0,
    "avg_volume": 22088304
  },
  "1579.T": {
    "ticker": "1579.T",
    "bullish_prob": 0.4244,
    "bearish_prob": 0.5756,
    "prediction": "bearish",
    "confidence": 0.1511,
    "model_accuracy": 0.4770949720670391,
    "model_trained_at": "2026-06-30T14:41:42.561007",
    "feature_importance": {
      "vwap_ratio": 289.0,
      "vol_ratio_20": 282.0,
      "vol_ratio_5": 278.0,
      "rsi_9": 267.0,
      "minute": 256.0,
      "ret_3": 246.0,
      "ret_5": 242.0,
      "rsi_14": 242.0,
      "high_low_ratio": 229.0,
      "ret_1": 226.0,
      "bb_width": 226.0,
      "bb_position": 206.0,
      "time_in_session": 200.0,
      "body_ratio": 199.0,
      "ma_ratio_10": 191.0,
      "ma_ratio_5": 190.0,
      "upper_shadow": 178.0,
      "atr_ratio": 175.0,
      "body": 163.0,
      "macd_hist": 163.0
    },
    "name": "日経平均ブル２倍上場投信",
    "price": 861.0,
    "avg_volume": 21558696
  },
  "1357.T": {
    "ticker": "1357.T",
    "bullish_prob": 0.4701,
    "bearish_prob": 0.5299,
    "prediction": "bearish",
    "confidence": 0.0599,
    "model_accuracy": 0.4921787709497207,
    "model_trained_at": "2026-06-30T14:41:47.156109",
    "feature_importance": {
      "ret_1": 302.0,
      "high_low_ratio": 288.0,
      "minute": 283.0,
      "vol_ratio_5": 282.0,
      "vol_ratio_20": 281.0,
      "ret_5": 259.0,
      "bb_width": 252.0,
      "time_in_session": 251.0,
      "rsi_9": 247.0,
      "ret_3": 239.0,
      "rsi_14": 235.0,
      "vwap_ratio": 234.0,
      "macd_hist": 234.0,
      "atr_ratio": 234.0,
      "macd_signal": 208.0,
      "body_ratio": 197.0,
      "bb_position": 194.0,
      "ret_10": 191.0,
      "ma_ratio_5": 183.0,
      "ma_ratio_10": 181.0
    },
    "name": "ＮＥＸＴ　ＦＵＮＤＳ　日経平均ダブルインバース・インデックス連動型上場投信",
    "price": 2560.0,
    "avg_volume": 18213511
  },
  "3110.T": {
    "ticker": "3110.T",
    "bullish_prob": 0.3219,
    "bearish_prob": 0.6781,
    "prediction": "bearish",
    "confidence": 0.3562,
    "model_accuracy": 0.507563025210084,
    "model_trained_at": "2026-06-30T14:41:51.668208",
    "feature_importance": {
      "time_in_session": 279.0,
      "atr_ratio": 272.0,
      "vol_ratio_5": 272.0,
      "rsi_9": 270.0,
      "ret_3": 269.0,
      "vwap_ratio": 267.0,
      "vol_ratio_20": 264.0,
      "minute": 246.0,
      "ret_5": 242.0,
      "bb_width": 222.0,
      "high_low_ratio": 222.0,
      "rsi_14": 205.0,
      "ret_1": 201.0,
      "macd": 199.0,
      "body_ratio": 197.0,
      "ma_ratio_50": 188.0,
      "macd_hist": 176.0,
      "bb_position": 174.0,
      "ma_ratio_5": 173.0,
      "ma_ratio_10": 170.0
    },
    "name": "日東紡績",
    "price": 4185.0,
    "avg_volume": 7612940
  },
  "1475.T": {
    "ticker": "1475.T",
    "bullish_prob": 0.1019,
    "bearish_prob": 0.8981,
    "prediction": "bearish",
    "confidence": 0.7963,
    "model_accuracy": 0.6555555555555556,
    "model_trained_at": "2026-06-30T14:41:56.206250",
    "feature_importance": {
      "vol_ratio_5": 362.0,
      "atr_ratio": 314.0,
      "vol_ratio_20": 312.0,
      "bb_width": 308.0,
      "ret_1": 275.0,
      "macd_signal": 248.0,
      "minute": 245.0,
      "ret_3": 244.0,
      "macd_hist": 232.0,
      "vwap_ratio": 225.0,
      "ma_ratio_5": 222.0,
      "time_in_session": 222.0,
      "high_low_ratio": 219.0,
      "rsi_9": 214.0,
      "ret_5": 203.0,
      "ma_ratio_10": 201.0,
      "ret_10": 199.0,
      "rsi_14": 196.0,
      "bb_position": 193.0,
      "body_ratio": 135.0
    },
    "name": "ｉシェアーズ・コア　ＴＯＰＩＸ　ＥＴＦ",
    "price": 413.0,
    "avg_volume": 6439874
  },
  "2914.T": {
    "ticker": "2914.T",
    "bullish_prob": 0.2665,
    "bearish_prob": 0.7335,
    "prediction": "bearish",
    "confidence": 0.467,
    "model_accuracy": 0.5530726256983242,
    "model_trained_at": "2026-06-30T14:42:00.722666",
    "feature_importance": {
      "vol_ratio_5": 333.0,
      "atr_ratio": 282.0,
      "rsi_9": 278.0,
      "ret_3": 264.0,
      "high_low_ratio": 262.0,
      "bb_position": 258.0,
      "ret_5": 255.0,
      "rsi_14": 252.0,
      "vol_ratio_20": 248.0,
      "time_in_session": 244.0,
      "bb_width": 235.0,
      "minute": 235.0,
      "vwap_ratio": 226.0,
      "ret_10": 225.0,
      "ret_1": 220.0,
      "macd_hist": 214.0,
      "ma_ratio_5": 182.0,
      "ma_ratio_10": 177.0,
      "macd_signal": 170.0,
      "ma_ratio_25": 162.0
    },
    "name": "日本たばこ産業",
    "price": 5926.0,
    "avg_volume": 5567780
  },
  "2502.T": {
    "ticker": "2502.T",
    "bullish_prob": 0.1502,
    "bearish_prob": 0.8498,
    "prediction": "bearish",
    "confidence": 0.6996,
    "model_accuracy": 0.6224089635854342,
    "model_trained_at": "2026-06-30T14:42:05.158889",
    "feature_importance": {
      "vol_ratio_5": 354.0,
      "vol_ratio_20": 298.0,
      "ret_5": 287.0,
      "rsi_9": 284.0,
      "vwap_ratio": 281.0,
      "ma_ratio_5": 276.0,
      "macd_hist": 268.0,
      "minute": 264.0,
      "ret_3": 257.0,
      "atr_ratio": 257.0,
      "time_in_session": 252.0,
      "macd_signal": 243.0,
      "ret_10": 240.0,
      "bb_width": 227.0,
      "high_low_ratio": 223.0,
      "bb_position": 222.0,
      "rsi_14": 219.0,
      "ret_1": 192.0,
      "ma_ratio_10": 175.0,
      "ma_ratio_20": 160.0
    },
    "name": "アサヒグループホールディングス",
    "price": 1550.0,
    "avg_volume": 5418340
  },
  "3382.T": {
    "ticker": "3382.T",
    "bullish_prob": 0.4136,
    "bearish_prob": 0.5864,
    "prediction": "bearish",
    "confidence": 0.1728,
    "model_accuracy": 0.5541899441340782,
    "model_trained_at": "2026-06-30T14:42:09.463467",
    "feature_importance": {
      "vol_ratio_20": 283.0,
      "vol_ratio_5": 282.0,
      "bb_width": 275.0,
      "ret_10": 266.0,
      "vwap_ratio": 266.0,
      "minute": 257.0,
      "rsi_14": 256.0,
      "macd_signal": 256.0,
      "atr_ratio": 255.0,
      "time_in_session": 255.0,
      "ret_5": 239.0,
      "macd_hist": 234.0,
      "rsi_9": 222.0,
      "ma_ratio_5": 219.0,
      "high_low_ratio": 206.0,
      "ma_ratio_10": 195.0,
      "ret_1": 194.0,
      "ma_ratio_20": 193.0,
      "ma_ratio_50": 183.0,
      "ret_3": 181.0
    },
    "name": "セブン＆アイ・ホールディングス",
    "price": 1926.0,
    "avg_volume": 5250100
  },
  "3092.T": {
    "ticker": "3092.T",
    "bullish_prob": 0.1091,
    "bearish_prob": 0.8909,
    "prediction": "bearish",
    "confidence": 0.7819,
    "model_accuracy": 0.6,
    "model_trained_at": "2026-06-30T14:42:13.959558",
    "feature_importance": {
      "vol_ratio_20": 410.0,
      "minute": 318.0,
      "vwap_ratio": 299.0,
      "bb_width": 297.0,
      "rsi_9": 284.0,
      "vol_ratio_5": 282.0,
      "ret_5": 277.0,
      "atr_ratio": 274.0,
      "ret_3": 273.0,
      "time_in_session": 273.0,
      "rsi_14": 272.0,
      "macd_hist": 256.0,
      "high_low_ratio": 251.0,
      "ret_1": 238.0,
      "ret_10": 224.0,
      "ma_ratio_25": 207.0,
      "ma_ratio_5": 200.0,
      "macd": 194.0,
      "ma_ratio_10": 193.0,
      "bb_position": 193.0
    },
    "name": "ＺＯＺＯ",
    "price": 1129.0,
    "avg_volume": 5194880
  },
  "1605.T": {
    "ticker": "1605.T",
    "bullish_prob": 0.2152,
    "bearish_prob": 0.7848,
    "prediction": "bearish",
    "confidence": 0.5696,
    "model_accuracy": 0.5591036414565826,
    "model_trained_at": "2026-06-30T14:42:18.462719",
    "feature_importance": {
      "ret_3": 347.0,
      "vol_ratio_5": 324.0,
      "vol_ratio_20": 300.0,
      "bb_width": 291.0,
      "atr_ratio": 279.0,
      "vwap_ratio": 273.0,
      "minute": 272.0,
      "rsi_14": 259.0,
      "ma_ratio_10": 257.0,
      "rsi_9": 254.0,
      "macd_hist": 242.0,
      "ma_ratio_5": 213.0,
      "ret_5": 209.0,
      "time_in_session": 206.0,
      "high_low_ratio": 191.0,
      "ret_10": 179.0,
      "bb_position": 173.0,
      "macd_signal": 164.0,
      "ret_1": 163.0,
      "ma_ratio_25": 153.0
    },
    "name": "ＩＮＰＥＸ",
    "price": 3283.0,
    "avg_volume": 4808160
  },
  "1568.T": {
    "ticker": "1568.T",
    "bullish_prob": 0.0723,
    "bearish_prob": 0.9277,
    "prediction": "bearish",
    "confidence": 0.8554,
    "model_accuracy": 0.5702786377708978,
    "model_trained_at": "2026-06-30T14:42:23.032933",
    "feature_importance": {
      "vol_ratio_20": 341.0,
      "vwap_ratio": 296.0,
      "ret_5": 271.0,
      "macd_signal": 254.0,
      "ret_10": 250.0,
      "rsi_9": 247.0,
      "ret_3": 242.0,
      "vol_ratio_5": 239.0,
      "bb_width": 238.0,
      "ret_1": 236.0,
      "macd_hist": 220.0,
      "ma_ratio_10": 213.0,
      "time_in_session": 211.0,
      "atr_ratio": 210.0,
      "rsi_14": 206.0,
      "ma_ratio_5": 197.0,
      "minute": 186.0,
      "high_low_ratio": 183.0,
      "bb_position": 175.0,
      "body_ratio": 156.0
    },
    "name": "ＴＯＰＩＸブル２倍上場投信",
    "price": 958.0,
    "avg_volume": 4469426
  },
  "1911.T": {
    "ticker": "1911.T",
    "bullish_prob": 0.1798,
    "bearish_prob": 0.8202,
    "prediction": "bearish",
    "confidence": 0.6404,
    "model_accuracy": 0.6308988764044944,
    "model_trained_at": "2026-06-30T14:42:27.540566",
    "feature_importance": {
      "rsi_14": 328.0,
      "vol_ratio_5": 290.0,
      "vwap_ratio": 287.0,
      "atr_ratio": 282.0,
      "bb_width": 279.0,
      "vol_ratio_20": 272.0,
      "high_low_ratio": 263.0,
      "ret_10": 259.0,
      "ret_3": 258.0,
      "ma_ratio_5": 255.0,
      "minute": 254.0,
      "rsi_9": 235.0,
      "bb_position": 225.0,
      "ma_ratio_10": 218.0,
      "time_in_session": 218.0,
      "ret_5": 217.0,
      "ma_ratio_25": 213.0,
      "ma_ratio_50": 197.0,
      "ret_1": 170.0,
      "macd_hist": 161.0
    },
    "name": "住友林業",
    "price": 1333.0,
    "avg_volume": 4417700
  },
  "1615.T": {
    "ticker": "1615.T",
    "bullish_prob": 0.5839,
    "bearish_prob": 0.4161,
    "prediction": "bullish",
    "confidence": 0.1679,
    "model_accuracy": 0.5414772727272728,
    "model_trained_at": "2026-06-30T14:42:32.043963",
    "feature_importance": {
      "vwap_ratio": 298.0,
      "rsi_14": 288.0,
      "vol_ratio_5": 286.0,
      "macd_hist": 264.0,
      "ret_5": 261.0,
      "ret_1": 252.0,
      "ret_3": 252.0,
      "atr_ratio": 250.0,
      "minute": 248.0,
      "rsi_9": 240.0,
      "ma_ratio_10": 238.0,
      "high_low_ratio": 237.0,
      "ret_10": 236.0,
      "vol_ratio_20": 233.0,
      "body_ratio": 221.0,
      "macd_signal": 220.0,
      "bb_width": 217.0,
      "ma_ratio_5": 201.0,
      "ma_ratio_25": 192.0,
      "time_in_session": 191.0
    },
    "name": "ＮＥＸＴ　ＦＵＮＤＳ　東証銀行業株価指数連動型上場投信",
    "price": 702.0,
    "avg_volume": 4311456
  },
  "3197.T": {
    "ticker": "3197.T",
    "bullish_prob": 0.5734,
    "bearish_prob": 0.4266,
    "prediction": "bullish",
    "confidence": 0.1467,
    "model_accuracy": 0.5473389355742297,
    "model_trained_at": "2026-06-30T14:42:36.555195",
    "feature_importance": {
      "vol_ratio_5": 368.0,
      "rsi_9": 336.0,
      "vol_ratio_20": 301.0,
      "ret_3": 292.0,
      "vwap_ratio": 286.0,
      "macd_hist": 284.0,
      "high_low_ratio": 260.0,
      "minute": 252.0,
      "ret_5": 251.0,
      "ret_10": 241.0,
      "rsi_14": 234.0,
      "bb_width": 221.0,
      "atr_ratio": 218.0,
      "ma_ratio_50": 216.0,
      "ma_ratio_20": 212.0,
      "ma_ratio_5": 211.0,
      "ret_1": 198.0,
      "macd_signal": 192.0,
      "ma_ratio_10": 188.0,
      "ma_ratio_25": 187.0
    },
    "name": "すかいらーくホールディングス",
    "price": 2793.0,
    "avg_volume": 3907440
  },
  "2802.T": {
    "ticker": "2802.T",
    "bullish_prob": 0.5134,
    "bearish_prob": 0.4866,
    "prediction": "bullish",
    "confidence": 0.0269,
    "model_accuracy": 0.4927374301675977,
    "model_trained_at": "2026-06-30T14:42:41.080773",
    "feature_importance": {
      "vwap_ratio": 331.0,
      "vol_ratio_20": 304.0,
      "rsi_9": 298.0,
      "ret_3": 281.0,
      "vol_ratio_5": 278.0,
      "ret_1": 259.0,
      "ret_5": 242.0,
      "minute": 242.0,
      "high_low_ratio": 237.0,
      "time_in_session": 235.0,
      "bb_width": 228.0,
      "ma_ratio_5": 220.0,
      "bb_position": 220.0,
      "body_ratio": 216.0,
      "ma_ratio_10": 215.0,
      "ma_ratio_25": 201.0,
      "macd_hist": 192.0,
      "atr_ratio": 177.0,
      "rsi_14": 174.0,
      "ret_10": 168.0
    },
    "name": "味の素",
    "price": 5725.0,
    "avg_volume": 3867200
  },
  "1570.T": {
    "ticker": "1570.T",
    "bullish_prob": 0.3998,
    "bearish_prob": 0.6002,
    "prediction": "bearish",
    "confidence": 0.2003,
    "model_accuracy": 0.5022346368715084,
    "model_trained_at": "2026-06-30T14:42:45.524183",
    "feature_importance": {
      "vol_ratio_5": 321.0,
      "ret_5": 302.0,
      "vol_ratio_20": 296.0,
      "minute": 276.0,
      "vwap_ratio": 261.0,
      "time_in_session": 243.0,
      "ret_3": 234.0,
      "rsi_9": 226.0,
      "rsi_14": 221.0,
      "body_ratio": 219.0,
      "high_low_ratio": 211.0,
      "ma_ratio_50": 205.0,
      "macd_hist": 203.0,
      "ret_1": 202.0,
      "ma_ratio_10": 198.0,
      "bb_width": 185.0,
      "atr_ratio": 181.0,
      "ret_10": 176.0,
      "ma_ratio_5": 176.0,
      "bb_position": 169.0
    },
    "name": "ＮＥＸＴ　ＦＵＮＤＳ　日経平均レバレッジ・インデックス連動型上場投信",
    "price": 79652.0,
    "avg_volume": 3860996
  },
  "3407.T": {
    "ticker": "3407.T",
    "bullish_prob": 0.4227,
    "bearish_prob": 0.5773,
    "prediction": "bearish",
    "confidence": 0.1547,
    "model_accuracy": 0.5546218487394958,
    "model_trained_at": "2026-06-30T14:42:49.808775",
    "feature_importance": {
      "vol_ratio_5": 296.0,
      "vwap_ratio": 284.0,
      "atr_ratio": 284.0,
      "ret_5": 281.0,
      "rsi_14": 272.0,
      "minute": 262.0,
      "ma_ratio_5": 261.0,
      "vol_ratio_20": 258.0,
      "ret_1": 242.0,
      "bb_width": 230.0,
      "rsi_9": 229.0,
      "high_low_ratio": 226.0,
      "time_in_session": 209.0,
      "ret_10": 200.0,
      "ma_ratio_10": 196.0,
      "ret_3": 189.0,
      "ma_ratio_20": 187.0,
      "macd_hist": 186.0,
      "bb_position": 174.0,
      "ma_ratio_25": 173.0
    },
    "name": "旭化成",
    "price": 1796.0,
    "avg_volume": 3666960
  },
  "2801.T": {
    "ticker": "2801.T",
    "bullish_prob": 0.1747,
    "bearish_prob": 0.8253,
    "prediction": "bearish",
    "confidence": 0.6506,
    "model_accuracy": 0.5596638655462185,
    "model_trained_at": "2026-06-30T14:42:58.911389",
    "feature_importance": {
      "ret_3": 353.0,
      "atr_ratio": 318.0,
      "vol_ratio_20": 305.0,
      "ret_5": 303.0,
      "rsi_14": 300.0,
      "high_low_ratio": 294.0,
      "vwap_ratio": 289.0,
      "bb_position": 281.0,
      "rsi_9": 267.0,
      "ret_1": 263.0,
      "vol_ratio_5": 253.0,
      "time_in_session": 247.0,
      "bb_width": 218.0,
      "ret_10": 214.0,
      "minute": 209.0,
      "macd_hist": 201.0,
      "ma_ratio_5": 199.0,
      "macd": 199.0,
      "macd_signal": 175.0,
      "ma_ratio_25": 172.0
    },
    "name": "キッコーマン",
    "price": 1636.0,
    "avg_volume": 3628160
  },
  "2413.T": {
    "ticker": "2413.T",
    "bullish_prob": 0.2764,
    "bearish_prob": 0.7236,
    "prediction": "bearish",
    "confidence": 0.4472,
    "model_accuracy": 0.529608938547486,
    "model_trained_at": "2026-06-30T14:42:54.342509",
    "feature_importance": {
      "vol_ratio_20": 339.0,
      "vol_ratio_5": 328.0,
      "vwap_ratio": 304.0,
      "macd_hist": 303.0,
      "high_low_ratio": 270.0,
      "rsi_14": 267.0,
      "time_in_session": 253.0,
      "macd_signal": 234.0,
      "ret_5": 231.0,
      "atr_ratio": 229.0,
      "ret_3": 224.0,
      "minute": 224.0,
      "bb_width": 222.0,
      "ret_1": 206.0,
      "bb_position": 204.0,
      "ma_ratio_50": 192.0,
      "ret_10": 188.0,
      "rsi_9": 188.0,
      "ma_ratio_5": 187.0,
      "ma_ratio_25": 172.0
    },
    "name": "エムスリー",
    "price": 1771.0,
    "avg_volume": 3625760
  },
  "3289.T": {
    "ticker": "3289.T",
    "bullish_prob": 0.3157,
    "bearish_prob": 0.6843,
    "prediction": "bearish",
    "confidence": 0.3686,
    "model_accuracy": 0.6463276836158192,
    "model_trained_at": "2026-06-30T14:43:03.478659",
    "feature_importance": {
      "atr_ratio": 356.0,
      "ret_10": 334.0,
      "vol_ratio_5": 333.0,
      "vwap_ratio": 300.0,
      "vol_ratio_20": 299.0,
      "minute": 285.0,
      "bb_width": 270.0,
      "high_low_ratio": 263.0,
      "macd_hist": 260.0,
      "ret_3": 243.0,
      "time_in_session": 242.0,
      "ma_ratio_25": 238.0,
      "rsi_9": 236.0,
      "ret_5": 234.0,
      "ma_ratio_10": 229.0,
      "ma_ratio_50": 212.0,
      "macd_signal": 201.0,
      "ma_ratio_20": 193.0,
      "bb_position": 192.0,
      "ma_ratio_5": 188.0
    },
    "name": "東急不動産ホールディングス",
    "price": 1279.0,
    "avg_volume": 3551060
  },
  "3402.T": {
    "ticker": "3402.T",
    "bullish_prob": 0.2874,
    "bearish_prob": 0.7126,
    "prediction": "bearish",
    "confidence": 0.4252,
    "model_accuracy": 0.5871148459383754,
    "model_trained_at": "2026-06-30T14:43:07.849031",
    "feature_importance": {
      "vol_ratio_5": 345.0,
      "ret_5": 321.0,
      "vol_ratio_20": 313.0,
      "high_low_ratio": 288.0,
      "bb_width": 279.0,
      "vwap_ratio": 272.0,
      "rsi_14": 269.0,
      "atr_ratio": 268.0,
      "minute": 245.0,
      "ret_1": 238.0,
      "ret_3": 237.0,
      "time_in_session": 233.0,
      "rsi_9": 227.0,
      "ma_ratio_5": 208.0,
      "macd_signal": 208.0,
      "ma_ratio_10": 204.0,
      "macd_hist": 200.0,
      "ret_10": 197.0,
      "ma_ratio_50": 175.0,
      "ma_ratio_20": 174.0
    },
    "name": "東レ",
    "price": 1143.0,
    "avg_volume": 3413700
  },
  "3231.T": {
    "ticker": "3231.T",
    "bullish_prob": 0.5616,
    "bearish_prob": 0.4384,
    "prediction": "bullish",
    "confidence": 0.1232,
    "model_accuracy": 0.5491620111731843,
    "model_trained_at": "2026-06-30T14:43:12.283088",
    "feature_importance": {
      "vol_ratio_5": 327.0,
      "vwap_ratio": 302.0,
      "bb_width": 291.0,
      "vol_ratio_20": 284.0,
      "ret_3": 283.0,
      "ret_1": 267.0,
      "time_in_session": 264.0,
      "high_low_ratio": 258.0,
      "rsi_14": 257.0,
      "ma_ratio_5": 246.0,
      "minute": 243.0,
      "macd_hist": 233.0,
      "ma_ratio_50": 227.0,
      "body_ratio": 226.0,
      "atr_ratio": 218.0,
      "ret_10": 215.0,
      "ret_5": 204.0,
      "rsi_9": 198.0,
      "macd_signal": 196.0,
      "bb_position": 163.0
    },
    "name": "野村不動産ホールディングス",
    "price": 924.0,
    "avg_volume": 3320600
  },
  "2644.T": {
    "ticker": "2644.T",
    "bullish_prob": 0.2009,
    "bearish_prob": 0.7991,
    "prediction": "bearish",
    "confidence": 0.5981,
    "model_accuracy": 0.4778711484593837,
    "model_trained_at": "2026-06-30T14:43:16.798988",
    "feature_importance": {
      "vol_ratio_5": 328.0,
      "bb_width": 283.0,
      "vwap_ratio": 281.0,
      "vol_ratio_20": 279.0,
      "time_in_session": 269.0,
      "rsi_14": 267.0,
      "ret_1": 262.0,
      "high_low_ratio": 261.0,
      "ret_3": 258.0,
      "rsi_9": 258.0,
      "ret_5": 246.0,
      "minute": 241.0,
      "atr_ratio": 232.0,
      "macd_hist": 216.0,
      "ma_ratio_5": 209.0,
      "macd": 209.0,
      "ret_10": 202.0,
      "macd_signal": 202.0,
      "body_ratio": 185.0,
      "ma_ratio_10": 166.0
    },
    "name": "グローバルＸ　半導体関連－日本株式　ＥＴＦ",
    "price": 4857.0,
    "avg_volume": 3289224
  },
  "3086.T": {
    "ticker": "3086.T",
    "bullish_prob": 0.483,
    "bearish_prob": 0.517,
    "prediction": "bearish",
    "confidence": 0.034,
    "model_accuracy": 0.523943661971831,
    "model_trained_at": "2026-06-30T14:43:21.420000",
    "feature_importance": {
      "high_low_ratio": 327.0,
      "rsi_9": 296.0,
      "bb_width": 267.0,
      "vol_ratio_20": 264.0,
      "atr_ratio": 250.0,
      "ma_ratio_5": 242.0,
      "vwap_ratio": 238.0,
      "ret_5": 234.0,
      "vol_ratio_5": 229.0,
      "time_in_session": 229.0,
      "macd_signal": 225.0,
      "ret_1": 216.0,
      "rsi_14": 216.0,
      "body_ratio": 205.0,
      "minute": 201.0,
      "bb_position": 190.0,
      "ret_3": 183.0,
      "ma_ratio_10": 180.0,
      "ret_10": 174.0,
      "macd_hist": 168.0
    },
    "name": "Ｊ．フロント　リテイリング",
    "price": 3298.0,
    "avg_volume": 3114620
  },
  "2503.T": {
    "ticker": "2503.T",
    "bullish_prob": 0.446,
    "bearish_prob": 0.554,
    "prediction": "bearish",
    "confidence": 0.108,
    "model_accuracy": 0.5022346368715084,
    "model_trained_at": "2026-06-30T14:43:25.941465",
    "feature_importance": {
      "rsi_14": 321.0,
      "vol_ratio_20": 310.0,
      "vwap_ratio": 273.0,
      "ma_ratio_10": 257.0,
      "high_low_ratio": 257.0,
      "ret_1": 250.0,
      "ret_5": 248.0,
      "vol_ratio_5": 243.0,
      "macd_hist": 235.0,
      "time_in_session": 235.0,
      "macd_signal": 227.0,
      "atr_ratio": 224.0,
      "bb_width": 222.0,
      "ret_10": 220.0,
      "minute": 210.0,
      "ret_3": 205.0,
      "ma_ratio_5": 198.0,
      "rsi_9": 183.0,
      "ma_ratio_50": 165.0,
      "ma_ratio_25": 150.0
    },
    "name": "キリンホールディングス",
    "price": 2796.0,
    "avg_volume": 3103040
  },
  "1802.T": {
    "ticker": "1802.T",
    "bullish_prob": 0.8827,
    "bearish_prob": 0.1173,
    "prediction": "bullish",
    "confidence": 0.7654,
    "model_accuracy": 0.526610644257703,
    "model_trained_at": "2026-06-30T14:43:30.380387",
    "feature_importance": {
      "vol_ratio_20": 342.0,
      "vwap_ratio": 296.0,
      "ret_3": 269.0,
      "bb_width": 268.0,
      "rsi_14": 265.0,
      "vol_ratio_5": 261.0,
      "rsi_9": 256.0,
      "time_in_session": 244.0,
      "minute": 234.0,
      "ret_1": 232.0,
      "ret_5": 223.0,
      "high_low_ratio": 215.0,
      "bb_position": 208.0,
      "atr_ratio": 199.0,
      "ma_ratio_10": 196.0,
      "macd_signal": 192.0,
      "macd_hist": 188.0,
      "ma_ratio_5": 186.0,
      "body_ratio": 163.0,
      "ret_10": 144.0
    },
    "name": "大林組",
    "price": 3206.0,
    "avg_volume": 2742680
  },
  "1928.T": {
    "ticker": "1928.T",
    "bullish_prob": 0.2404,
    "bearish_prob": 0.7596,
    "prediction": "bearish",
    "confidence": 0.5193,
    "model_accuracy": 0.6322033898305085,
    "model_trained_at": "2026-06-30T14:43:34.767733",
    "feature_importance": {
      "vol_ratio_5": 374.0,
      "vwap_ratio": 353.0,
      "vol_ratio_20": 306.0,
      "ma_ratio_5": 296.0,
      "ret_5": 292.0,
      "macd_hist": 292.0,
      "atr_ratio": 292.0,
      "bb_width": 279.0,
      "minute": 271.0,
      "bb_position": 267.0,
      "time_in_session": 255.0,
      "ret_10": 249.0,
      "ret_3": 234.0,
      "rsi_14": 226.0,
      "ma_ratio_10": 224.0,
      "ma_ratio_25": 192.0,
      "rsi_9": 184.0,
      "macd_signal": 172.0,
      "high_low_ratio": 170.0,
      "ret_1": 168.0
    },
    "name": "積水ハウス",
    "price": 3317.0,
    "avg_volume": 2613580
  },
  "3405.T": {
    "ticker": "3405.T",
    "bullish_prob": 0.2493,
    "bearish_prob": 0.7507,
    "prediction": "bearish",
    "confidence": 0.5013,
    "model_accuracy": 0.5824858757062147,
    "model_trained_at": "2026-06-30T14:43:39.174859",
    "feature_importance": {
      "vol_ratio_20": 373.0,
      "vol_ratio_5": 346.0,
      "macd_hist": 303.0,
      "time_in_session": 285.0,
      "atr_ratio": 282.0,
      "ret_10": 268.0,
      "high_low_ratio": 265.0,
      "rsi_14": 263.0,
      "vwap_ratio": 260.0,
      "ret_1": 255.0,
      "ma_ratio_10": 245.0,
      "bb_width": 245.0,
      "ret_3": 235.0,
      "ret_5": 231.0,
      "macd": 220.0,
      "rsi_9": 219.0,
      "minute": 212.0,
      "ma_ratio_5": 211.0,
      "bb_position": 193.0,
      "ma_ratio_50": 183.0
    },
    "name": "クラレ",
    "price": 1659.0,
    "avg_volume": 2608460
  },
  "1803.T": {
    "ticker": "1803.T",
    "bullish_prob": 0.5573,
    "bearish_prob": 0.4427,
    "prediction": "bullish",
    "confidence": 0.1147,
    "model_accuracy": 0.5223463687150838,
    "model_trained_at": "2026-06-30T14:43:43.693464",
    "feature_importance": {
      "vol_ratio_20": 286.0,
      "ret_1": 285.0,
      "ret_5": 266.0,
      "minute": 262.0,
      "vol_ratio_5": 261.0,
      "high_low_ratio": 258.0,
      "bb_width": 256.0,
      "atr_ratio": 242.0,
      "rsi_14": 231.0,
      "vwap_ratio": 214.0,
      "ma_ratio_10": 202.0,
      "macd_signal": 200.0,
      "ret_10": 197.0,
      "time_in_session": 191.0,
      "macd_hist": 189.0,
      "ma_ratio_50": 186.0,
      "ret_3": 181.0,
      "rsi_9": 181.0,
      "bb_position": 179.0,
      "ma_ratio_5": 171.0
    },
    "name": "清水建設",
    "price": 2534.0,
    "avg_volume": 2572320
  },
  "3003.T": {
    "ticker": "3003.T",
    "bullish_prob": 0.4601,
    "bearish_prob": 0.5399,
    "prediction": "bearish",
    "confidence": 0.0798,
    "model_accuracy": 0.660281690140845,
    "model_trained_at": "2026-06-30T14:43:48.170099",
    "feature_importance": {
      "vol_ratio_20": 347.0,
      "ma_ratio_5": 312.0,
      "ret_5": 287.0,
      "vol_ratio_5": 281.0,
      "ret_3": 277.0,
      "rsi_14": 272.0,
      "macd_hist": 262.0,
      "atr_ratio": 257.0,
      "minute": 254.0,
      "bb_position": 253.0,
      "time_in_session": 251.0,
      "ma_ratio_10": 239.0,
      "vwap_ratio": 239.0,
      "rsi_9": 235.0,
      "ret_1": 208.0,
      "macd_signal": 207.0,
      "high_low_ratio": 199.0,
      "macd": 189.0,
      "bb_width": 189.0,
      "ma_ratio_50": 175.0
    },
    "name": "ヒューリック",
    "price": 1684.0,
    "avg_volume": 2558640
  },
  "3103.T": {
    "ticker": "3103.T",
    "bullish_prob": 0.1322,
    "bearish_prob": 0.8678,
    "prediction": "bearish",
    "confidence": 0.7357,
    "model_accuracy": 0.5759103641456582,
    "model_trained_at": "2026-06-30T14:43:52.643459",
    "feature_importance": {
      "vol_ratio_20": 391.0,
      "high_low_ratio": 304.0,
      "minute": 302.0,
      "time_in_session": 302.0,
      "vol_ratio_5": 289.0,
      "macd_signal": 278.0,
      "rsi_14": 273.0,
      "vwap_ratio": 268.0,
      "ret_5": 262.0,
      "atr_ratio": 259.0,
      "ret_1": 251.0,
      "ret_10": 251.0,
      "bb_width": 231.0,
      "ma_ratio_10": 217.0,
      "ma_ratio_5": 215.0,
      "ret_3": 212.0,
      "rsi_9": 206.0,
      "macd_hist": 197.0,
      "bb_position": 189.0,
      "ma_ratio_25": 170.0
    },
    "name": "ユニチカ",
    "price": 1046.0,
    "avg_volume": 2502820
  },
  "1925.T": {
    "ticker": "1925.T",
    "bullish_prob": 0.2416,
    "bearish_prob": 0.7584,
    "prediction": "bearish",
    "confidence": 0.5168,
    "model_accuracy": 0.6050420168067226,
    "model_trained_at": "2026-06-30T14:43:57.212770",
    "feature_importance": {
      "vol_ratio_5": 356.0,
      "vol_ratio_20": 341.0,
      "ret_3": 319.0,
      "vwap_ratio": 301.0,
      "ret_10": 291.0,
      "ret_5": 281.0,
      "atr_ratio": 278.0,
      "rsi_9": 262.0,
      "ma_ratio_5": 249.0,
      "ret_1": 240.0,
      "minute": 237.0,
      "high_low_ratio": 236.0,
      "macd_hist": 226.0,
      "rsi_14": 224.0,
      "bb_width": 224.0,
      "time_in_session": 207.0,
      "macd_signal": 198.0,
      "ma_ratio_20": 195.0,
      "bb_position": 192.0,
      "ma_ratio_25": 180.0
    },
    "name": "大和ハウス工業",
    "price": 4395.0,
    "avg_volume": 2400820
  },
  "2264.T": {
    "ticker": "2264.T",
    "bullish_prob": 0.3716,
    "bearish_prob": 0.6284,
    "prediction": "bearish",
    "confidence": 0.2569,
    "model_accuracy": 0.5778443113772456,
    "model_trained_at": "2026-06-30T14:44:01.767053",
    "feature_importance": {
      "vol_ratio_20": 315.0,
      "vwap_ratio": 308.0,
      "vol_ratio_5": 298.0,
      "atr_ratio": 289.0,
      "ret_1": 255.0,
      "macd_hist": 248.0,
      "minute": 248.0,
      "ret_10": 245.0,
      "rsi_9": 239.0,
      "macd_signal": 235.0,
      "ret_3": 230.0,
      "ret_5": 227.0,
      "high_low_ratio": 224.0,
      "bb_width": 210.0,
      "macd": 189.0,
      "ma_ratio_5": 184.0,
      "rsi_14": 184.0,
      "body_ratio": 178.0,
      "time_in_session": 175.0,
      "bb_position": 174.0
    },
    "name": "森永乳業",
    "price": 1249.0,
    "avg_volume": 2002040
  },
  "2492.T": {
    "ticker": "2492.T",
    "bullish_prob": 0.0051,
    "bearish_prob": 0.9949,
    "prediction": "bearish",
    "confidence": 0.9899,
    "model_accuracy": 0.8464912280701755,
    "model_trained_at": "2026-06-30T14:44:05.958070",
    "feature_importance": {
      "vol_ratio_20": 350.0,
      "vol_ratio_5": 347.0,
      "bb_width": 341.0,
      "atr_ratio": 290.0,
      "ma_ratio_10": 246.0,
      "minute": 244.0,
      "time_in_session": 230.0,
      "macd_hist": 226.0,
      "vwap_ratio": 225.0,
      "ma_ratio_5": 224.0,
      "macd_signal": 210.0,
      "bb_position": 191.0,
      "macd": 188.0,
      "ret_1": 177.0,
      "ma_ratio_25": 165.0,
      "ret_10": 159.0,
      "ma_ratio_50": 159.0,
      "rsi_14": 152.0,
      "ret_3": 138.0,
      "ret_5": 137.0
    },
    "name": "インフォマート",
    "price": 372.0,
    "avg_volume": 1963020
  },
  "3099.T": {
    "ticker": "3099.T",
    "bullish_prob": 0.1104,
    "bearish_prob": 0.8896,
    "prediction": "bearish",
    "confidence": 0.7791,
    "model_accuracy": 0.5642458100558659,
    "model_trained_at": "2026-06-30T14:44:10.393542",
    "feature_importance": {
      "vol_ratio_20": 322.0,
      "vwap_ratio": 308.0,
      "ret_3": 285.0,
      "time_in_session": 278.0,
      "rsi_14": 266.0,
      "ret_5": 262.0,
      "ret_10": 258.0,
      "ma_ratio_5": 257.0,
      "vol_ratio_5": 253.0,
      "high_low_ratio": 253.0,
      "ret_1": 251.0,
      "rsi_9": 237.0,
      "atr_ratio": 228.0,
      "macd_hist": 222.0,
      "minute": 219.0,
      "ma_ratio_10": 217.0,
      "bb_width": 212.0,
      "ma_ratio_50": 194.0,
      "ma_ratio_25": 186.0,
      "body_ratio": 170.0
    },
    "name": "三越伊勢丹ホールディングス",
    "price": 4108.0,
    "avg_volume": 1954780
  },
  "3064.T": {
    "ticker": "3064.T",
    "bullish_prob": 0.095,
    "bearish_prob": 0.905,
    "prediction": "bearish",
    "confidence": 0.8099,
    "model_accuracy": 0.5757746478873239,
    "model_trained_at": "2026-06-30T14:44:14.921554",
    "feature_importance": {
      "atr_ratio": 322.0,
      "minute": 314.0,
      "rsi_14": 309.0,
      "vwap_ratio": 299.0,
      "ret_3": 292.0,
      "vol_ratio_20": 292.0,
      "ret_5": 285.0,
      "rsi_9": 272.0,
      "vol_ratio_5": 269.0,
      "time_in_session": 267.0,
      "ma_ratio_5": 244.0,
      "ret_10": 231.0,
      "bb_width": 228.0,
      "high_low_ratio": 220.0,
      "ret_1": 215.0,
      "ma_ratio_50": 213.0,
      "macd": 212.0,
      "macd_hist": 206.0,
      "bb_position": 198.0,
      "ma_ratio_10": 193.0
    },
    "name": "ＭｏｎｏｔａＲＯ",
    "price": 1781.0,
    "avg_volume": 1952940
  },
  "3387.T": {
    "ticker": "3387.T",
    "bullish_prob": 0.0145,
    "bearish_prob": 0.9855,
    "prediction": "bearish",
    "confidence": 0.971,
    "model_accuracy": 0.8578073089700997,
    "model_trained_at": "2026-06-30T14:44:19.339120",
    "feature_importance": {
      "vol_ratio_5": 452.0,
      "atr_ratio": 375.0,
      "vol_ratio_20": 373.0,
      "minute": 326.0,
      "bb_width": 321.0,
      "ma_ratio_5": 319.0,
      "macd_hist": 317.0,
      "ma_ratio_10": 285.0,
      "macd_signal": 264.0,
      "time_in_session": 250.0,
      "bb_position": 228.0,
      "vwap_ratio": 215.0,
      "macd": 209.0,
      "ret_5": 184.0,
      "ma_ratio_25": 178.0,
      "rsi_14": 174.0,
      "ret_10": 165.0,
      "ma_ratio_50": 163.0,
      "ma_ratio_20": 160.0,
      "ret_1": 155.0
    },
    "name": "クリエイト・レストランツ・ホールディングス",
    "price": 720.0,
    "avg_volume": 1859300
  },
  "2127.T": {
    "ticker": "2127.T",
    "bullish_prob": 0.0756,
    "bearish_prob": 0.9244,
    "prediction": "bearish",
    "confidence": 0.8488,
    "model_accuracy": 0.5715909090909091,
    "model_trained_at": "2026-06-30T14:44:23.922420",
    "feature_importance": {
      "vol_ratio_5": 361.0,
      "ret_1": 313.0,
      "vwap_ratio": 297.0,
      "vol_ratio_20": 297.0,
      "ret_5": 288.0,
      "rsi_9": 279.0,
      "macd_hist": 277.0,
      "ma_ratio_5": 268.0,
      "ret_10": 267.0,
      "minute": 255.0,
      "rsi_14": 243.0,
      "body_ratio": 237.0,
      "bb_width": 235.0,
      "atr_ratio": 233.0,
      "time_in_session": 222.0,
      "ret_3": 214.0,
      "macd_signal": 188.0,
      "high_low_ratio": 183.0,
      "ma_ratio_10": 180.0,
      "ma_ratio_25": 165.0
    },
    "name": "日本Ｍ＆Ａセンターホールディングス",
    "price": 630.0,
    "avg_volume": 1806060
  },
  "2334.T": {
    "ticker": "2334.T",
    "bullish_prob": 0.1267,
    "bearish_prob": 0.8733,
    "prediction": "bearish",
    "confidence": 0.7466,
    "model_accuracy": 0.6498461538461539,
    "model_trained_at": "2026-06-30T14:44:28.325814",
    "feature_importance": {
      "vol_ratio_5": 330.0,
      "atr_ratio": 310.0,
      "rsi_9": 276.0,
      "minute": 276.0,
      "bb_width": 274.0,
      "rsi_14": 260.0,
      "ret_10": 251.0,
      "time_in_session": 251.0,
      "ret_5": 249.0,
      "vwap_ratio": 244.0,
      "macd_signal": 242.0,
      "vol_ratio_20": 237.0,
      "ret_3": 232.0,
      "ma_ratio_10": 221.0,
      "ret_1": 214.0,
      "ma_ratio_50": 198.0,
      "ma_ratio_20": 193.0,
      "bb_position": 189.0,
      "ma_ratio_5": 187.0,
      "high_low_ratio": 186.0
    },
    "name": "イオレ",
    "price": 604.0,
    "avg_volume": 1632300
  },
  "3088.T": {
    "ticker": "3088.T",
    "bullish_prob": 0.6485,
    "bearish_prob": 0.3515,
    "prediction": "bullish",
    "confidence": 0.2971,
    "model_accuracy": 0.5498591549295775,
    "model_trained_at": "2026-06-30T14:44:32.757677",
    "feature_importance": {
      "vol_ratio_20": 370.0,
      "vwap_ratio": 336.0,
      "high_low_ratio": 314.0,
      "atr_ratio": 291.0,
      "vol_ratio_5": 291.0,
      "rsi_14": 287.0,
      "bb_width": 285.0,
      "ret_5": 260.0,
      "rsi_9": 245.0,
      "minute": 245.0,
      "ma_ratio_5": 232.0,
      "ret_3": 210.0,
      "ret_1": 209.0,
      "macd_signal": 202.0,
      "ma_ratio_10": 200.0,
      "time_in_session": 199.0,
      "ma_ratio_50": 183.0,
      "ma_ratio_25": 168.0,
      "macd": 167.0,
      "bb_position": 162.0
    },
    "name": "マツキヨココカラ＆カンパニー",
    "price": 2394.0,
    "avg_volume": 1602460
  },
  "2962.T": {
    "ticker": "2962.T",
    "bullish_prob": 0.4563,
    "bearish_prob": 0.5437,
    "prediction": "bearish",
    "confidence": 0.0874,
    "model_accuracy": 0.5355704697986577,
    "model_trained_at": "2026-06-30T14:44:37.136093",
    "feature_importance": {
      "vol_ratio_5": 284.0,
      "vwap_ratio": 270.0,
      "macd_signal": 261.0,
      "vol_ratio_20": 260.0,
      "rsi_9": 253.0,
      "atr_ratio": 250.0,
      "minute": 244.0,
      "ret_3": 230.0,
      "body_ratio": 226.0,
      "ma_ratio_25": 216.0,
      "high_low_ratio": 201.0,
      "rsi_14": 200.0,
      "time_in_session": 199.0,
      "bb_width": 192.0,
      "macd_hist": 186.0,
      "ma_ratio_10": 175.0,
      "ret_5": 172.0,
      "ma_ratio_50": 170.0,
      "ma_ratio_5": 159.0,
      "body": 155.0
    },
    "name": "テクニスコ",
    "price": 1732.0,
    "avg_volume": 1578500
  },
  "2702.T": {
    "ticker": "2702.T",
    "bullish_prob": 0.0492,
    "bearish_prob": 0.9508,
    "prediction": "bearish",
    "confidence": 0.9017,
    "model_accuracy": 0.8164285714285715,
    "model_trained_at": "2026-06-30T14:44:41.526706",
    "feature_importance": {
      "vol_ratio_20": 387.0,
      "vol_ratio_5": 374.0,
      "time_in_session": 329.0,
      "atr_ratio": 312.0,
      "macd_hist": 286.0,
      "vwap_ratio": 274.0,
      "ma_ratio_10": 264.0,
      "bb_width": 258.0,
      "minute": 245.0,
      "ma_ratio_5": 239.0,
      "rsi_14": 233.0,
      "macd_signal": 227.0,
      "ma_ratio_50": 217.0,
      "ret_10": 206.0,
      "ret_5": 199.0,
      "macd": 187.0,
      "bb_position": 182.0,
      "ma_ratio_25": 172.0,
      "ret_3": 161.0,
      "rsi_9": 161.0
    },
    "name": "日本マクドナルドホールディングス",
    "price": 7432.0,
    "avg_volume": 1566620
  },
  "3391.T": {
    "ticker": "3391.T",
    "bullish_prob": 0.2465,
    "bearish_prob": 0.7535,
    "prediction": "bearish",
    "confidence": 0.507,
    "model_accuracy": 0.5477528089887641,
    "model_trained_at": "2026-06-30T14:44:46.060848",
    "feature_importance": {
      "vol_ratio_5": 324.0,
      "ret_1": 306.0,
      "vwap_ratio": 303.0,
      "rsi_9": 294.0,
      "vol_ratio_20": 289.0,
      "atr_ratio": 284.0,
      "rsi_14": 266.0,
      "high_low_ratio": 262.0,
      "minute": 262.0,
      "macd_hist": 259.0,
      "ret_10": 250.0,
      "ret_5": 242.0,
      "bb_width": 238.0,
      "ma_ratio_5": 236.0,
      "ret_3": 232.0,
      "ma_ratio_50": 232.0,
      "time_in_session": 219.0,
      "ma_ratio_10": 182.0,
      "ma_ratio_25": 181.0,
      "macd": 178.0
    },
    "name": "ツルハホールディングス",
    "price": 2031.0,
    "avg_volume": 1526840
  },
  "1963.T": {
    "ticker": "1963.T",
    "bullish_prob": 0.5664,
    "bearish_prob": 0.4336,
    "prediction": "bullish",
    "confidence": 0.1329,
    "model_accuracy": 0.507563025210084,
    "model_trained_at": "2026-06-30T14:44:50.795919",
    "feature_importance": {
      "vol_ratio_5": 369.0,
      "atr_ratio": 301.0,
      "vol_ratio_20": 278.0,
      "vwap_ratio": 266.0,
      "macd_hist": 262.0,
      "high_low_ratio": 258.0,
      "ret_5": 253.0,
      "time_in_session": 240.0,
      "bb_width": 237.0,
      "rsi_14": 236.0,
      "rsi_9": 225.0,
      "ret_3": 216.0,
      "ma_ratio_10": 216.0,
      "body_ratio": 210.0,
      "ret_10": 210.0,
      "ma_ratio_25": 199.0,
      "minute": 199.0,
      "ma_ratio_5": 188.0,
      "ret_1": 184.0,
      "macd_signal": 175.0
    },
    "name": "日揮ホールディングス",
    "price": 2543.0,
    "avg_volume": 1457420
  },
  "1812.T": {
    "ticker": "1812.T",
    "bullish_prob": 0.2585,
    "bearish_prob": 0.7415,
    "prediction": "bearish",
    "confidence": 0.4829,
    "model_accuracy": 0.5,
    "model_trained_at": "2026-06-30T14:44:55.239302",
    "feature_importance": {
      "vol_ratio_5": 301.0,
      "vol_ratio_20": 287.0,
      "high_low_ratio": 265.0,
      "macd_signal": 253.0,
      "bb_width": 248.0,
      "rsi_9": 247.0,
      "body_ratio": 244.0,
      "vwap_ratio": 232.0,
      "rsi_14": 229.0,
      "minute": 229.0,
      "ma_ratio_50": 215.0,
      "ret_1": 213.0,
      "ret_5": 211.0,
      "atr_ratio": 202.0,
      "macd_hist": 199.0,
      "macd": 185.0,
      "ret_3": 177.0,
      "ma_ratio_5": 171.0,
      "ret_10": 170.0,
      "time_in_session": 167.0
    },
    "name": "鹿島建設",
    "price": 5770.0,
    "avg_volume": 1410600
  },
  "3038.T": {
    "ticker": "3038.T",
    "bullish_prob": 0.1221,
    "bearish_prob": 0.8779,
    "prediction": "bearish",
    "confidence": 0.7558,
    "model_accuracy": 0.53954802259887,
    "model_trained_at": "2026-06-30T14:44:59.927945",
    "feature_importance": {
      "vol_ratio_5": 346.0,
      "bb_width": 339.0,
      "ret_5": 324.0,
      "ma_ratio_5": 316.0,
      "rsi_14": 315.0,
      "atr_ratio": 306.0,
      "vwap_ratio": 304.0,
      "vol_ratio_20": 302.0,
      "minute": 267.0,
      "ret_1": 265.0,
      "macd_hist": 264.0,
      "macd_signal": 261.0,
      "rsi_9": 255.0,
      "high_low_ratio": 249.0,
      "time_in_session": 228.0,
      "ret_3": 223.0,
      "bb_position": 200.0,
      "ma_ratio_10": 184.0,
      "ret_10": 176.0,
      "ma_ratio_25": 176.0
    },
    "name": "神戸物産",
    "price": 2613.0,
    "avg_volume": 1383880
  },
  "2501.T": {
    "ticker": "2501.T",
    "bullish_prob": 0.8326,
    "bearish_prob": 0.1674,
    "prediction": "bullish",
    "confidence": 0.6651,
    "model_accuracy": 0.5432584269662921,
    "model_trained_at": "2026-06-30T14:45:04.599702",
    "feature_importance": {
      "vol_ratio_20": 328.0,
      "ret_5": 316.0,
      "high_low_ratio": 312.0,
      "vwap_ratio": 290.0,
      "ret_3": 283.0,
      "vol_ratio_5": 271.0,
      "rsi_9": 263.0,
      "ret_10": 246.0,
      "atr_ratio": 240.0,
      "macd_signal": 237.0,
      "minute": 234.0,
      "bb_width": 225.0,
      "rsi_14": 220.0,
      "ret_1": 212.0,
      "bb_position": 210.0,
      "macd_hist": 195.0,
      "ma_ratio_5": 192.0,
      "body_ratio": 180.0,
      "time_in_session": 180.0,
      "ma_ratio_50": 168.0
    },
    "name": "サッポロホールディングス",
    "price": 2014.0,
    "avg_volume": 1373940
  },
  "1893.T": {
    "ticker": "1893.T",
    "bullish_prob": 0.4317,
    "bearish_prob": 0.5683,
    "prediction": "bearish",
    "confidence": 0.1366,
    "model_accuracy": 0.5288515406162464,
    "model_trained_at": "2026-06-30T14:45:09.088138",
    "feature_importance": {
      "rsi_14": 304.0,
      "vwap_ratio": 289.0,
      "ret_10": 267.0,
      "atr_ratio": 262.0,
      "ma_ratio_5": 260.0,
      "vol_ratio_20": 255.0,
      "high_low_ratio": 255.0,
      "ret_1": 249.0,
      "rsi_9": 248.0,
      "ret_5": 247.0,
      "bb_width": 242.0,
      "minute": 235.0,
      "vol_ratio_5": 234.0,
      "ret_3": 209.0,
      "ma_ratio_10": 207.0,
      "macd_signal": 192.0,
      "macd_hist": 180.0,
      "macd": 174.0,
      "ma_ratio_50": 168.0,
      "time_in_session": 168.0
    },
    "name": "五洋建設",
    "price": 1704.0,
    "avg_volume": 1320740
  },
  "1878.T": {
    "ticker": "1878.T",
    "bullish_prob": 0.0565,
    "bearish_prob": 0.9435,
    "prediction": "bearish",
    "confidence": 0.887,
    "model_accuracy": 0.6534883720930232,
    "model_trained_at": "2026-06-30T14:45:13.577984",
    "feature_importance": {
      "vol_ratio_20": 417.0,
      "vwap_ratio": 272.0,
      "vol_ratio_5": 272.0,
      "ret_5": 266.0,
      "ret_3": 265.0,
      "ret_10": 260.0,
      "atr_ratio": 259.0,
      "bb_width": 255.0,
      "rsi_9": 242.0,
      "ma_ratio_5": 239.0,
      "time_in_session": 237.0,
      "macd": 226.0,
      "rsi_14": 212.0,
      "minute": 211.0,
      "macd_hist": 210.0,
      "high_low_ratio": 208.0,
      "bb_position": 203.0,
      "ma_ratio_10": 201.0,
      "ma_ratio_50": 192.0,
      "ret_1": 188.0
    },
    "name": "大東建託",
    "price": 3049.0,
    "avg_volume": 1240580
  },
  "3105.T": {
    "ticker": "3105.T",
    "bullish_prob": 0.4154,
    "bearish_prob": 0.5846,
    "prediction": "bearish",
    "confidence": 0.1691,
    "model_accuracy": 0.5014005602240896,
    "model_trained_at": "2026-06-30T14:45:18.169610",
    "feature_importance": {
      "vol_ratio_5": 300.0,
      "rsi_14": 296.0,
      "vwap_ratio": 294.0,
      "vol_ratio_20": 277.0,
      "ret_1": 248.0,
      "ma_ratio_5": 242.0,
      "high_low_ratio": 237.0,
      "ret_3": 233.0,
      "ma_ratio_25": 231.0,
      "time_in_session": 228.0,
      "body_ratio": 222.0,
      "ret_5": 216.0,
      "ma_ratio_10": 215.0,
      "minute": 215.0,
      "atr_ratio": 214.0,
      "macd_signal": 205.0,
      "bb_width": 199.0,
      "rsi_9": 191.0,
      "bb_position": 189.0,
      "ma_ratio_50": 182.0
    },
    "name": "日清紡ホールディングス",
    "price": 2448.0,
    "avg_volume": 1227560
  },
  "2317.T": {
    "ticker": "2317.T",
    "bullish_prob": 0.0346,
    "bearish_prob": 0.9654,
    "prediction": "bearish",
    "confidence": 0.9308,
    "model_accuracy": 0.922340425531915,
    "model_trained_at": "2026-06-30T14:45:22.426351",
    "feature_importance": {
      "vol_ratio_20": 399.0,
      "vol_ratio_5": 397.0,
      "minute": 334.0,
      "macd_hist": 293.0,
      "macd_signal": 285.0,
      "time_in_session": 278.0,
      "ma_ratio_5": 277.0,
      "bb_width": 265.0,
      "ma_ratio_10": 251.0,
      "bb_position": 224.0,
      "vwap_ratio": 212.0,
      "ma_ratio_20": 199.0,
      "atr_ratio": 197.0,
      "ma_ratio_50": 188.0,
      "ma_ratio_25": 183.0,
      "macd": 181.0,
      "ret_10": 156.0,
      "rsi_14": 127.0,
      "rsi_9": 105.0,
      "ret_1": 88.0
    },
    "name": "システナ",
    "price": 392.0,
    "avg_volume": 1200020
  },
  "1662.T": {
    "ticker": "1662.T",
    "bullish_prob": 0.1516,
    "bearish_prob": 0.8484,
    "prediction": "bearish",
    "confidence": 0.6968,
    "model_accuracy": 0.6817337461300309,
    "model_trained_at": "2026-06-30T14:45:26.857540",
    "feature_importance": {
      "vol_ratio_5": 328.0,
      "bb_width": 299.0,
      "vwap_ratio": 284.0,
      "ret_1": 271.0,
      "atr_ratio": 270.0,
      "vol_ratio_20": 268.0,
      "ret_5": 254.0,
      "macd_hist": 237.0,
      "minute": 223.0,
      "ma_ratio_10": 220.0,
      "ret_10": 216.0,
      "ma_ratio_5": 213.0,
      "ret_3": 193.0,
      "rsi_14": 193.0,
      "time_in_session": 191.0,
      "rsi_9": 180.0,
      "high_low_ratio": 179.0,
      "ma_ratio_25": 169.0,
      "macd": 165.0,
      "ma_ratio_20": 154.0
    },
    "name": "石油資源開発",
    "price": 1600.0,
    "avg_volume": 1172680
  },
  "2331.T": {
    "ticker": "2331.T",
    "bullish_prob": 0.3912,
    "bearish_prob": 0.6088,
    "prediction": "bearish",
    "confidence": 0.2175,
    "model_accuracy": 0.71,
    "model_trained_at": "2026-06-30T14:45:31.280059",
    "feature_importance": {
      "vol_ratio_5": 357.0,
      "time_in_session": 327.0,
      "vol_ratio_20": 322.0,
      "bb_width": 293.0,
      "atr_ratio": 276.0,
      "minute": 276.0,
      "rsi_14": 266.0,
      "ret_3": 239.0,
      "ret_5": 236.0,
      "macd_hist": 234.0,
      "ma_ratio_10": 223.0,
      "ma_ratio_50": 220.0,
      "macd_signal": 220.0,
      "rsi_9": 210.0,
      "ma_ratio_5": 209.0,
      "ret_10": 205.0,
      "vwap_ratio": 203.0,
      "bb_position": 189.0,
      "ret_1": 178.0,
      "high_low_ratio": 176.0
    },
    "name": "ＡＬＳＯＫ",
    "price": 1069.0,
    "avg_volume": 1145040
  },
  "2897.T": {
    "ticker": "2897.T",
    "bullish_prob": 0.1091,
    "bearish_prob": 0.8909,
    "prediction": "bearish",
    "confidence": 0.7817,
    "model_accuracy": 0.5524079320113315,
    "model_trained_at": "2026-06-30T14:45:35.883538",
    "feature_importance": {
      "bb_width": 300.0,
      "vol_ratio_5": 292.0,
      "vwap_ratio": 283.0,
      "ma_ratio_10": 270.0,
      "atr_ratio": 267.0,
      "macd_hist": 266.0,
      "ret_5": 263.0,
      "vol_ratio_20": 261.0,
      "ma_ratio_5": 258.0,
      "ret_1": 253.0,
      "minute": 248.0,
      "rsi_9": 246.0,
      "high_low_ratio": 237.0,
      "ret_3": 233.0,
      "bb_position": 220.0,
      "time_in_session": 219.0,
      "rsi_14": 217.0,
      "ret_10": 205.0,
      "macd_signal": 201.0,
      "body_ratio": 189.0
    },
    "name": "日清食品ホールディングス",
    "price": 2755.0,
    "avg_volume": 1121740
  },
  "2579.T": {
    "ticker": "2579.T",
    "bullish_prob": 0.5517,
    "bearish_prob": 0.4483,
    "prediction": "bullish",
    "confidence": 0.1034,
    "model_accuracy": 0.5375358166189111,
    "model_trained_at": "2026-06-30T14:45:40.405021",
    "feature_importance": {
      "ret_3": 320.0,
      "vwap_ratio": 310.0,
      "atr_ratio": 287.0,
      "ret_1": 273.0,
      "rsi_14": 264.0,
      "vol_ratio_5": 264.0,
      "macd_signal": 256.0,
      "bb_width": 247.0,
      "vol_ratio_20": 247.0,
      "rsi_9": 243.0,
      "ret_5": 242.0,
      "ret_10": 240.0,
      "minute": 236.0,
      "high_low_ratio": 229.0,
      "ma_ratio_10": 221.0,
      "ma_ratio_5": 218.0,
      "time_in_session": 213.0,
      "macd_hist": 201.0,
      "bb_position": 170.0,
      "ma_ratio_50": 169.0
    },
    "name": "コカ・コーラ　ボトラーズジャパンホールディングス",
    "price": 4263.0,
    "avg_volume": 1117840
  },
  "1332.T": {
    "ticker": "1332.T",
    "bullish_prob": 0.2521,
    "bearish_prob": 0.7479,
    "prediction": "bearish",
    "confidence": 0.4958,
    "model_accuracy": 0.6040345821325648,
    "model_trained_at": "2026-06-30T14:45:44.922757",
    "feature_importance": {
      "vol_ratio_5": 378.0,
      "vwap_ratio": 335.0,
      "vol_ratio_20": 305.0,
      "minute": 301.0,
      "ret_1": 298.0,
      "rsi_9": 290.0,
      "high_low_ratio": 281.0,
      "time_in_session": 262.0,
      "bb_width": 248.0,
      "atr_ratio": 248.0,
      "ret_10": 246.0,
      "ma_ratio_10": 243.0,
      "macd_hist": 238.0,
      "ma_ratio_50": 230.0,
      "rsi_14": 226.0,
      "bb_position": 226.0,
      "ret_3": 224.0,
      "ret_5": 223.0,
      "ma_ratio_5": 223.0,
      "macd_signal": 188.0
    },
    "name": "ニッスイ",
    "price": 1282.0,
    "avg_volume": 1102360
  },
  "2871.T": {
    "ticker": "2871.T",
    "bullish_prob": 0.4021,
    "bearish_prob": 0.5979,
    "prediction": "bearish",
    "confidence": 0.1958,
    "model_accuracy": 0.5670454545454545,
    "model_trained_at": "2026-06-30T14:45:49.409053",
    "feature_importance": {
      "vol_ratio_5": 339.0,
      "vol_ratio_20": 313.0,
      "rsi_9": 289.0,
      "vwap_ratio": 280.0,
      "rsi_14": 273.0,
      "ret_5": 264.0,
      "bb_width": 260.0,
      "macd_hist": 248.0,
      "atr_ratio": 244.0,
      "time_in_session": 243.0,
      "ret_1": 232.0,
      "minute": 216.0,
      "bb_position": 211.0,
      "ret_3": 206.0,
      "ret_10": 183.0,
      "ma_ratio_25": 182.0,
      "ma_ratio_5": 179.0,
      "macd_signal": 178.0,
      "high_low_ratio": 176.0,
      "ma_ratio_10": 174.0
    },
    "name": "ニチレイ",
    "price": 2156.0,
    "avg_volume": 1075420
  },
  "2432.T": {
    "ticker": "2432.T",
    "bullish_prob": 0.2918,
    "bearish_prob": 0.7082,
    "prediction": "bearish",
    "confidence": 0.4165,
    "model_accuracy": 0.5455072463768115,
    "model_trained_at": "2026-06-30T14:45:54.040112",
    "feature_importance": {
      "vol_ratio_20": 311.0,
      "ret_1": 288.0,
      "rsi_9": 286.0,
      "vwap_ratio": 275.0,
      "bb_width": 268.0,
      "vol_ratio_5": 265.0,
      "rsi_14": 257.0,
      "ret_5": 250.0,
      "ret_3": 247.0,
      "ma_ratio_5": 247.0,
      "time_in_session": 241.0,
      "macd_hist": 239.0,
      "high_low_ratio": 238.0,
      "minute": 229.0,
      "ret_10": 228.0,
      "macd_signal": 224.0,
      "atr_ratio": 212.0,
      "bb_position": 199.0,
      "ma_ratio_25": 194.0,
      "ma_ratio_10": 188.0
    },
    "name": "ディー・エヌ・エー",
    "price": 2403.0,
    "avg_volume": 1074940
  },
  "1655.T": {
    "ticker": "1655.T",
    "bullish_prob": 0.0987,
    "bearish_prob": 0.9013,
    "prediction": "bearish",
    "confidence": 0.8026,
    "model_accuracy": 0.7627450980392156,
    "model_trained_at": "2026-06-30T14:45:58.427944",
    "feature_importance": {
      "vol_ratio_5": 369.0,
      "vwap_ratio": 334.0,
      "vol_ratio_20": 307.0,
      "minute": 305.0,
      "bb_width": 295.0,
      "ret_3": 291.0,
      "time_in_session": 289.0,
      "atr_ratio": 266.0,
      "rsi_14": 245.0,
      "ret_5": 237.0,
      "macd_signal": 235.0,
      "ret_1": 230.0,
      "macd_hist": 229.0,
      "ma_ratio_5": 228.0,
      "rsi_9": 221.0,
      "ret_10": 206.0,
      "bb_position": 190.0,
      "high_low_ratio": 183.0,
      "ma_ratio_10": 181.0,
      "ma_ratio_20": 166.0
    },
    "name": "ｉシェアーズ　Ｓ＆Ｐ　５００　米国株　ＥＴＦ",
    "price": 864.0,
    "avg_volume": 1043530
  },
  "1329.T": {
    "ticker": "1329.T",
    "bullish_prob": 0.2564,
    "bearish_prob": 0.7436,
    "prediction": "bearish",
    "confidence": 0.4872,
    "model_accuracy": 0.5235955056179774,
    "model_trained_at": "2026-06-30T14:46:02.818529",
    "feature_importance": {
      "vol_ratio_5": 337.0,
      "rsi_9": 304.0,
      "vol_ratio_20": 291.0,
      "ret_3": 268.0,
      "ma_ratio_5": 253.0,
      "high_low_ratio": 245.0,
      "vwap_ratio": 237.0,
      "ret_1": 236.0,
      "body_ratio": 226.0,
      "minute": 219.0,
      "time_in_session": 217.0,
      "macd_signal": 209.0,
      "bb_width": 208.0,
      "ret_5": 201.0,
      "bb_position": 200.0,
      "rsi_14": 196.0,
      "macd_hist": 194.0,
      "ret_10": 187.0,
      "atr_ratio": 184.0,
      "ma_ratio_10": 159.0
    },
    "name": "ｉシェアーズ・コア　日経２２５　ＥＴＦ",
    "price": 7310.0,
    "avg_volume": 1015864
  },
  "2243.T": {
    "ticker": "2243.T",
    "bullish_prob": 0.3012,
    "bearish_prob": 0.6988,
    "prediction": "bearish",
    "confidence": 0.3976,
    "model_accuracy": 0.5430167597765363,
    "model_trained_at": "2026-06-30T14:46:07.460427",
    "feature_importance": {
      "vol_ratio_20": 330.0,
      "vol_ratio_5": 324.0,
      "atr_ratio": 313.0,
      "rsi_9": 299.0,
      "bb_position": 291.0,
      "high_low_ratio": 284.0,
      "ret_1": 267.0,
      "ret_5": 261.0,
      "bb_width": 259.0,
      "minute": 252.0,
      "rsi_14": 248.0,
      "macd_hist": 246.0,
      "vwap_ratio": 243.0,
      "ma_ratio_5": 228.0,
      "ret_3": 222.0,
      "body_ratio": 218.0,
      "ret_10": 192.0,
      "time_in_session": 190.0,
      "ma_ratio_25": 162.0,
      "macd_signal": 161.0
    },
    "name": "グローバルＸ　半導体　ＥＴＦ",
    "price": 5256.0,
    "avg_volume": 990397
  },
  "2587.T": {
    "ticker": "2587.T",
    "bullish_prob": 0.4926,
    "bearish_prob": 0.5074,
    "prediction": "bearish",
    "confidence": 0.0149,
    "model_accuracy": 0.5942028985507247,
    "model_trained_at": "2026-06-30T14:46:11.864568",
    "feature_importance": {
      "bb_width": 303.0,
      "vol_ratio_5": 299.0,
      "atr_ratio": 285.0,
      "vwap_ratio": 277.0,
      "ret_5": 267.0,
      "ret_1": 262.0,
      "vol_ratio_20": 252.0,
      "macd": 251.0,
      "minute": 241.0,
      "macd_signal": 234.0,
      "rsi_9": 232.0,
      "time_in_session": 231.0,
      "ma_ratio_50": 215.0,
      "ret_3": 213.0,
      "rsi_14": 211.0,
      "macd_hist": 208.0,
      "ret_10": 207.0,
      "ma_ratio_25": 195.0,
      "ma_ratio_10": 193.0,
      "high_low_ratio": 187.0
    },
    "name": "サントリービバレッジ＆フード",
    "price": 4445.0,
    "avg_volume": 977100
  },
  "2768.T": {
    "ticker": "2768.T",
    "bullish_prob": 0.1344,
    "bearish_prob": 0.8656,
    "prediction": "bearish",
    "confidence": 0.7312,
    "model_accuracy": 0.5131652661064425,
    "model_trained_at": "2026-06-30T14:46:16.345333",
    "feature_importance": {
      "vol_ratio_5": 318.0,
      "vol_ratio_20": 306.0,
      "atr_ratio": 302.0,
      "ma_ratio_5": 285.0,
      "vwap_ratio": 277.0,
      "ret_3": 265.0,
      "rsi_14": 257.0,
      "ret_10": 253.0,
      "minute": 247.0,
      "macd_signal": 230.0,
      "ret_5": 227.0,
      "macd_hist": 220.0,
      "bb_position": 220.0,
      "ret_1": 218.0,
      "high_low_ratio": 212.0,
      "time_in_session": 211.0,
      "bb_width": 196.0,
      "rsi_9": 191.0,
      "ma_ratio_25": 176.0,
      "ma_ratio_10": 162.0
    },
    "name": "双日",
    "price": 5225.0,
    "avg_volume": 975900
  },
  "1808.T": {
    "ticker": "1808.T",
    "bullish_prob": 0.2925,
    "bearish_prob": 0.7075,
    "prediction": "bearish",
    "confidence": 0.415,
    "model_accuracy": 0.5384180790960451,
    "model_trained_at": "2026-06-30T14:46:20.859117",
    "feature_importance": {
      "rsi_14": 335.0,
      "vol_ratio_5": 301.0,
      "ret_1": 300.0,
      "vwap_ratio": 297.0,
      "atr_ratio": 296.0,
      "vol_ratio_20": 291.0,
      "rsi_9": 277.0,
      "minute": 269.0,
      "time_in_session": 241.0,
      "ret_5": 235.0,
      "high_low_ratio": 228.0,
      "macd_hist": 225.0,
      "macd_signal": 219.0,
      "ma_ratio_10": 215.0,
      "bb_width": 214.0,
      "ret_10": 213.0,
      "ret_3": 212.0,
      "bb_position": 197.0,
      "ma_ratio_5": 192.0,
      "ma_ratio_20": 166.0
    },
    "name": "長谷工コーポレーション",
    "price": 2805.0,
    "avg_volume": 962100
  },
  "2170.T": {
    "ticker": "2170.T",
    "bullish_prob": 0.0117,
    "bearish_prob": 0.9883,
    "prediction": "bearish",
    "confidence": 0.9765,
    "model_accuracy": 0.8745762711864407,
    "model_trained_at": "2026-06-30T14:46:25.011636",
    "feature_importance": {
      "vol_ratio_20": 326.0,
      "vol_ratio_5": 321.0,
      "minute": 297.0,
      "time_in_session": 287.0,
      "vwap_ratio": 279.0,
      "macd_signal": 259.0,
      "bb_width": 253.0,
      "macd_hist": 241.0,
      "atr_ratio": 224.0,
      "ma_ratio_25": 220.0,
      "ma_ratio_5": 214.0,
      "ret_5": 205.0,
      "ma_ratio_10": 191.0,
      "ma_ratio_50": 166.0,
      "bb_position": 159.0,
      "rsi_14": 155.0,
      "macd": 154.0,
      "ret_10": 149.0,
      "ret_3": 135.0,
      "rsi_9": 123.0
    },
    "name": "リンクアンドモチベーション",
    "price": 533.0,
    "avg_volume": 924680
  },
  "2269.T": {
    "ticker": "2269.T",
    "bullish_prob": 0.2106,
    "bearish_prob": 0.7894,
    "prediction": "bearish",
    "confidence": 0.5788,
    "model_accuracy": 0.5854651162790698,
    "model_trained_at": "2026-06-30T14:46:29.431434",
    "feature_importance": {
      "ret_3": 331.0,
      "vol_ratio_20": 296.0,
      "vol_ratio_5": 282.0,
      "ret_5": 262.0,
      "rsi_14": 262.0,
      "minute": 261.0,
      "bb_width": 259.0,
      "ret_1": 255.0,
      "rsi_9": 251.0,
      "atr_ratio": 251.0,
      "time_in_session": 238.0,
      "vwap_ratio": 235.0,
      "ma_ratio_10": 223.0,
      "ret_10": 206.0,
      "ma_ratio_20": 204.0,
      "bb_position": 204.0,
      "macd_hist": 198.0,
      "ma_ratio_5": 181.0,
      "ma_ratio_25": 159.0,
      "ma_ratio_50": 152.0
    },
    "name": "明治ホールディングス",
    "price": 3772.0,
    "avg_volume": 916640
  },
  "1343.T": {
    "ticker": "1343.T",
    "bullish_prob": 0.1523,
    "bearish_prob": 0.8477,
    "prediction": "bearish",
    "confidence": 0.6955,
    "model_accuracy": 0.7638225255972697,
    "model_trained_at": "2026-06-30T14:46:33.725567",
    "feature_importance": {
      "vol_ratio_5": 344.0,
      "vwap_ratio": 342.0,
      "rsi_9": 294.0,
      "minute": 286.0,
      "ma_ratio_5": 263.0,
      "atr_ratio": 254.0,
      "ret_1": 253.0,
      "time_in_session": 249.0,
      "vol_ratio_20": 244.0,
      "ma_ratio_10": 240.0,
      "rsi_14": 239.0,
      "ret_3": 235.0,
      "macd_hist": 224.0,
      "ret_5": 223.0,
      "macd": 219.0,
      "macd_signal": 214.0,
      "ret_10": 198.0,
      "bb_width": 192.0,
      "bb_position": 172.0,
      "ma_ratio_50": 158.0
    },
    "name": "ＮＥＸＴ　ＦＵＮＤＳ　東証ＲＥＩＴ　指数連動型上場投信",
    "price": 1950.0,
    "avg_volume": 857842
  },
  "2931.T": {
    "ticker": "2931.T",
    "bullish_prob": 0.0096,
    "bearish_prob": 0.9904,
    "prediction": "bearish",
    "confidence": 0.9808,
    "model_accuracy": 0.8857142857142856,
    "model_trained_at": "2026-06-30T14:46:37.927048",
    "feature_importance": {
      "atr_ratio": 312.0,
      "time_in_session": 307.0,
      "vol_ratio_5": 287.0,
      "vol_ratio_20": 272.0,
      "minute": 258.0,
      "ma_ratio_10": 245.0,
      "macd_hist": 230.0,
      "bb_width": 213.0,
      "ma_ratio_5": 205.0,
      "bb_position": 201.0,
      "vwap_ratio": 194.0,
      "macd_signal": 191.0,
      "ma_ratio_50": 174.0,
      "ret_5": 146.0,
      "ma_ratio_25": 140.0,
      "ret_10": 137.0,
      "rsi_14": 129.0,
      "macd": 120.0,
      "ma_ratio_20": 119.0,
      "ret_1": 115.0
    },
    "name": "ユーグレナ",
    "price": 325.0,
    "avg_volume": 856520
  },
  "1860.T": {
    "ticker": "1860.T",
    "bullish_prob": 0.1901,
    "bearish_prob": 0.8099,
    "prediction": "bearish",
    "confidence": 0.6199,
    "model_accuracy": 0.5922848664688427,
    "model_trained_at": "2026-06-30T14:46:42.441685",
    "feature_importance": {
      "vwap_ratio": 326.0,
      "vol_ratio_5": 312.0,
      "ret_10": 285.0,
      "time_in_session": 271.0,
      "rsi_14": 270.0,
      "bb_width": 268.0,
      "vol_ratio_20": 267.0,
      "macd_hist": 263.0,
      "ret_5": 261.0,
      "ret_3": 256.0,
      "ret_1": 244.0,
      "ma_ratio_5": 243.0,
      "minute": 241.0,
      "high_low_ratio": 232.0,
      "rsi_9": 229.0,
      "macd_signal": 227.0,
      "ma_ratio_10": 212.0,
      "atr_ratio": 208.0,
      "ma_ratio_50": 195.0,
      "bb_position": 182.0
    },
    "name": "戸田建設",
    "price": 1619.0,
    "avg_volume": 811680
  },
  "2337.T": {
    "ticker": "2337.T",
    "bullish_prob": 0.0064,
    "bearish_prob": 0.9936,
    "prediction": "bearish",
    "confidence": 0.9871,
    "model_accuracy": 0.9263598326359833,
    "model_trained_at": "2026-06-30T14:46:51.210649",
    "feature_importance": {
      "vol_ratio_20": 365.0,
      "macd_hist": 341.0,
      "atr_ratio": 333.0,
      "minute": 328.0,
      "vol_ratio_5": 294.0,
      "macd_signal": 279.0,
      "bb_width": 272.0,
      "time_in_session": 271.0,
      "vwap_ratio": 258.0,
      "ma_ratio_5": 242.0,
      "ma_ratio_50": 235.0,
      "bb_position": 224.0,
      "macd": 197.0,
      "ma_ratio_10": 195.0,
      "ma_ratio_20": 134.0,
      "ma_ratio_25": 133.0,
      "rsi_9": 115.0,
      "ret_1": 107.0,
      "ret_10": 95.0,
      "ret_5": 87.0
    },
    "name": "いちご",
    "price": 433.0,
    "avg_volume": 809340
  },
  "2371.T": {
    "ticker": "2371.T",
    "bullish_prob": 0.0501,
    "bearish_prob": 0.9499,
    "prediction": "bearish",
    "confidence": 0.8998,
    "model_accuracy": 0.7021671826625386,
    "model_trained_at": "2026-06-30T14:46:46.857899",
    "feature_importance": {
      "vol_ratio_20": 341.0,
      "time_in_session": 320.0,
      "vol_ratio_5": 308.0,
      "bb_width": 301.0,
      "ret_5": 264.0,
      "minute": 264.0,
      "ma_ratio_5": 261.0,
      "rsi_14": 258.0,
      "vwap_ratio": 245.0,
      "atr_ratio": 239.0,
      "ret_3": 236.0,
      "ret_10": 223.0,
      "ret_1": 212.0,
      "macd_hist": 212.0,
      "macd_signal": 186.0,
      "ma_ratio_10": 174.0,
      "high_low_ratio": 173.0,
      "ma_ratio_50": 169.0,
      "bb_position": 165.0,
      "macd": 162.0
    },
    "name": "カカクコム",
    "price": 3338.0,
    "avg_volume": 804860
  },
  "1580.T": {
    "ticker": "1580.T",
    "bullish_prob": 0.1113,
    "bearish_prob": 0.8887,
    "prediction": "bearish",
    "confidence": 0.7774,
    "model_accuracy": 0.7511111111111112,
    "model_trained_at": "2026-06-30T14:46:55.440404",
    "feature_importance": {
      "rsi_9": 313.0,
      "ret_3": 312.0,
      "ret_1": 304.0,
      "vol_ratio_5": 304.0,
      "vol_ratio_20": 297.0,
      "vwap_ratio": 254.0,
      "ret_5": 249.0,
      "macd_hist": 239.0,
      "bb_width": 238.0,
      "ma_ratio_5": 231.0,
      "atr_ratio": 219.0,
      "minute": 214.0,
      "macd_signal": 212.0,
      "ret_10": 201.0,
      "ma_ratio_10": 191.0,
      "time_in_session": 185.0,
      "ma_ratio_50": 179.0,
      "rsi_14": 175.0,
      "high_low_ratio": 163.0,
      "macd": 131.0
    },
    "name": "日経平均ベア上場投信",
    "price": 751.0,
    "avg_volume": 795474
  },
  "2002.T": {
    "ticker": "2002.T",
    "bullish_prob": 0.5147,
    "bearish_prob": 0.4853,
    "prediction": "bullish",
    "confidence": 0.0294,
    "model_accuracy": 0.6257309941520468,
    "model_trained_at": "2026-06-30T14:46:59.919030",
    "feature_importance": {
      "vol_ratio_5": 354.0,
      "vol_ratio_20": 320.0,
      "vwap_ratio": 299.0,
      "rsi_9": 297.0,
      "rsi_14": 270.0,
      "bb_width": 267.0,
      "atr_ratio": 262.0,
      "ma_ratio_5": 257.0,
      "time_in_session": 248.0,
      "ret_10": 246.0,
      "minute": 240.0,
      "ma_ratio_10": 239.0,
      "ret_1": 238.0,
      "high_low_ratio": 231.0,
      "ma_ratio_25": 215.0,
      "macd_hist": 215.0,
      "ret_5": 203.0,
      "ma_ratio_50": 199.0,
      "ret_3": 181.0,
      "macd_signal": 181.0
    },
    "name": "日清製粉グループ本社",
    "price": 1980.0,
    "avg_volume": 774340
  },
  "1414.T": {
    "ticker": "1414.T",
    "bullish_prob": 0.448,
    "bearish_prob": 0.552,
    "prediction": "bearish",
    "confidence": 0.104,
    "model_accuracy": 0.7741100323624595,
    "model_trained_at": "2026-06-30T14:47:04.454697",
    "feature_importance": {
      "vol_ratio_5": 408.0,
      "bb_width": 361.0,
      "time_in_session": 343.0,
      "atr_ratio": 310.0,
      "vol_ratio_20": 289.0,
      "minute": 264.0,
      "macd_signal": 260.0,
      "ma_ratio_5": 256.0,
      "rsi_14": 252.0,
      "ret_5": 251.0,
      "ret_10": 245.0,
      "ma_ratio_10": 241.0,
      "vwap_ratio": 240.0,
      "bb_position": 239.0,
      "macd": 223.0,
      "rsi_9": 216.0,
      "ma_ratio_50": 214.0,
      "ma_ratio_25": 213.0,
      "macd_hist": 211.0,
      "ret_3": 188.0
    },
    "name": "ショーボンドホールディングス",
    "price": 1238.0,
    "avg_volume": 770740
  },
  "2160.T": {
    "ticker": "2160.T",
    "bullish_prob": 0.4408,
    "bearish_prob": 0.5592,
    "prediction": "bearish",
    "confidence": 0.1183,
    "model_accuracy": 0.5904761904761905,
    "model_trained_at": "2026-06-30T14:47:09.039152",
    "feature_importance": {
      "vol_ratio_20": 354.0,
      "vwap_ratio": 295.0,
      "atr_ratio": 273.0,
      "rsi_14": 264.0,
      "ret_1": 258.0,
      "bb_width": 256.0,
      "time_in_session": 243.0,
      "ret_3": 235.0,
      "ret_10": 231.0,
      "rsi_9": 226.0,
      "macd_hist": 224.0,
      "ret_5": 220.0,
      "ma_ratio_5": 216.0,
      "vol_ratio_5": 214.0,
      "minute": 213.0,
      "high_low_ratio": 212.0,
      "ma_ratio_10": 197.0,
      "macd_signal": 188.0,
      "bb_position": 176.0,
      "ma_ratio_25": 161.0
    },
    "name": "ジーエヌアイグループ",
    "price": 2645.0,
    "avg_volume": 755940
  },
  "1942.T": {
    "ticker": "1942.T",
    "bullish_prob": 0.6065,
    "bearish_prob": 0.3935,
    "prediction": "bullish",
    "confidence": 0.2129,
    "model_accuracy": 0.5162921348314606,
    "model_trained_at": "2026-06-30T14:47:13.558117",
    "feature_importance": {
      "vol_ratio_5": 306.0,
      "rsi_9": 302.0,
      "vwap_ratio": 296.0,
      "vol_ratio_20": 284.0,
      "ma_ratio_5": 274.0,
      "minute": 267.0,
      "body_ratio": 261.0,
      "time_in_session": 260.0,
      "ret_5": 252.0,
      "atr_ratio": 251.0,
      "high_low_ratio": 247.0,
      "ret_3": 230.0,
      "bb_width": 218.0,
      "macd_signal": 213.0,
      "macd_hist": 201.0,
      "bb_position": 193.0,
      "ret_1": 189.0,
      "ret_10": 182.0,
      "rsi_14": 180.0,
      "ma_ratio_10": 172.0
    },
    "name": "関電工",
    "price": 6732.0,
    "avg_volume": 747820
  },
  "1801.T": {
    "ticker": "1801.T",
    "bullish_prob": 0.2533,
    "bearish_prob": 0.7467,
    "prediction": "bearish",
    "confidence": 0.4933,
    "model_accuracy": 0.5609065155807367,
    "model_trained_at": "2026-06-30T14:47:18.279915",
    "feature_importance": {
      "vol_ratio_20": 347.0,
      "vwap_ratio": 303.0,
      "bb_width": 287.0,
      "vol_ratio_5": 280.0,
      "rsi_14": 262.0,
      "ma_ratio_5": 261.0,
      "ret_3": 251.0,
      "rsi_9": 246.0,
      "ret_5": 242.0,
      "high_low_ratio": 232.0,
      "time_in_session": 231.0,
      "bb_position": 222.0,
      "macd_signal": 204.0,
      "macd_hist": 204.0,
      "ret_10": 200.0,
      "ma_ratio_10": 200.0,
      "ret_1": 196.0,
      "atr_ratio": 195.0,
      "ma_ratio_50": 179.0,
      "ma_ratio_25": 174.0
    },
    "name": "大成建設",
    "price": 14057.0,
    "avg_volume": 721680
  },
  "2267.T": {
    "ticker": "2267.T",
    "bullish_prob": 0.3752,
    "bearish_prob": 0.6248,
    "prediction": "bearish",
    "confidence": 0.2496,
    "model_accuracy": 0.5784256559766764,
    "model_trained_at": "2026-06-30T14:47:22.890790",
    "feature_importance": {
      "vol_ratio_20": 394.0,
      "atr_ratio": 304.0,
      "time_in_session": 291.0,
      "ret_3": 287.0,
      "high_low_ratio": 286.0,
      "vwap_ratio": 275.0,
      "ret_1": 272.0,
      "ma_ratio_10": 272.0,
      "ret_5": 268.0,
      "vol_ratio_5": 266.0,
      "ret_10": 256.0,
      "rsi_9": 254.0,
      "bb_width": 245.0,
      "minute": 240.0,
      "rsi_14": 239.0,
      "ma_ratio_5": 211.0,
      "bb_position": 208.0,
      "ma_ratio_50": 195.0,
      "macd": 195.0,
      "macd_signal": 195.0
    },
    "name": "ヤクルト本社",
    "price": 2740.0,
    "avg_volume": 710940
  },
  "2726.T": {
    "ticker": "2726.T",
    "bullish_prob": 0.1333,
    "bearish_prob": 0.8667,
    "prediction": "bearish",
    "confidence": 0.7333,
    "model_accuracy": 0.690625,
    "model_trained_at": "2026-06-30T14:47:27.370071",
    "feature_importance": {
      "vol_ratio_20": 401.0,
      "vol_ratio_5": 394.0,
      "atr_ratio": 347.0,
      "vwap_ratio": 339.0,
      "ma_ratio_5": 310.0,
      "minute": 284.0,
      "ret_5": 270.0,
      "ret_10": 266.0,
      "time_in_session": 261.0,
      "bb_width": 251.0,
      "rsi_14": 242.0,
      "ret_3": 239.0,
      "macd_signal": 238.0,
      "ret_1": 225.0,
      "macd_hist": 222.0,
      "macd": 220.0,
      "ma_ratio_25": 218.0,
      "rsi_9": 213.0,
      "bb_position": 213.0,
      "high_low_ratio": 209.0
    },
    "name": "パルグループホールディングス",
    "price": 1454.0,
    "avg_volume": 693800
  },
  "1951.T": {
    "ticker": "1951.T",
    "bullish_prob": 0.1755,
    "bearish_prob": 0.8245,
    "prediction": "bearish",
    "confidence": 0.6489,
    "model_accuracy": 0.5497142857142857,
    "model_trained_at": "2026-06-30T14:47:32.006296",
    "feature_importance": {
      "vol_ratio_5": 411.0,
      "high_low_ratio": 313.0,
      "vwap_ratio": 292.0,
      "ret_3": 270.0,
      "rsi_9": 269.0,
      "ret_5": 263.0,
      "ret_1": 260.0,
      "vol_ratio_20": 260.0,
      "minute": 260.0,
      "ret_10": 258.0,
      "bb_position": 257.0,
      "ma_ratio_5": 250.0,
      "bb_width": 236.0,
      "time_in_session": 235.0,
      "ma_ratio_50": 234.0,
      "macd_hist": 233.0,
      "atr_ratio": 229.0,
      "rsi_14": 228.0,
      "ma_ratio_10": 213.0,
      "macd_signal": 210.0
    },
    "name": "エクシオグループ",
    "price": 2772.0,
    "avg_volume": 681980
  },
  "3401.T": {
    "ticker": "3401.T",
    "bullish_prob": 0.6115,
    "bearish_prob": 0.3885,
    "prediction": "bullish",
    "confidence": 0.223,
    "model_accuracy": 0.5900000000000001,
    "model_trained_at": "2026-06-30T14:47:36.644117",
    "feature_importance": {
      "atr_ratio": 328.0,
      "minute": 288.0,
      "vol_ratio_5": 285.0,
      "macd_hist": 284.0,
      "rsi_14": 276.0,
      "vol_ratio_20": 263.0,
      "ma_ratio_5": 253.0,
      "rsi_9": 253.0,
      "vwap_ratio": 240.0,
      "ret_3": 239.0,
      "high_low_ratio": 239.0,
      "bb_width": 225.0,
      "ret_10": 223.0,
      "ret_5": 217.0,
      "time_in_session": 206.0,
      "ret_1": 196.0,
      "ma_ratio_50": 193.0,
      "bb_position": 190.0,
      "macd": 184.0,
      "ma_ratio_20": 183.0
    },
    "name": "帝人",
    "price": 1624.0,
    "avg_volume": 677760
  },
  "2433.T": {
    "ticker": "2433.T",
    "bullish_prob": 0.1554,
    "bearish_prob": 0.8446,
    "prediction": "bearish",
    "confidence": 0.6893,
    "model_accuracy": 0.719620253164557,
    "model_trained_at": "2026-06-30T14:47:41.207216",
    "feature_importance": {
      "vol_ratio_5": 289.0,
      "atr_ratio": 274.0,
      "vol_ratio_20": 270.0,
      "ret_10": 268.0,
      "vwap_ratio": 257.0,
      "ret_5": 256.0,
      "rsi_14": 256.0,
      "ret_1": 244.0,
      "bb_width": 239.0,
      "ret_3": 238.0,
      "ma_ratio_5": 217.0,
      "macd_hist": 217.0,
      "macd": 209.0,
      "time_in_session": 200.0,
      "macd_signal": 199.0,
      "minute": 198.0,
      "ma_ratio_10": 194.0,
      "rsi_9": 188.0,
      "bb_position": 185.0,
      "ma_ratio_50": 165.0
    },
    "name": "博報堂ＤＹホールディングス",
    "price": 1120.0,
    "avg_volume": 671760
  },
  "1980.T": {
    "ticker": "1980.T",
    "bullish_prob": 0.802,
    "bearish_prob": 0.198,
    "prediction": "bullish",
    "confidence": 0.604,
    "model_accuracy": 0.5527377521613832,
    "model_trained_at": "2026-06-30T14:47:45.612208",
    "feature_importance": {
      "vwap_ratio": 320.0,
      "vol_ratio_20": 308.0,
      "vol_ratio_5": 304.0,
      "ret_5": 281.0,
      "rsi_9": 254.0,
      "minute": 253.0,
      "time_in_session": 242.0,
      "ret_1": 235.0,
      "macd_signal": 231.0,
      "ret_10": 230.0,
      "high_low_ratio": 219.0,
      "atr_ratio": 216.0,
      "ret_3": 212.0,
      "macd": 197.0,
      "bb_width": 193.0,
      "macd_hist": 177.0,
      "rsi_14": 175.0,
      "ma_ratio_50": 173.0,
      "bb_position": 172.0,
      "ma_ratio_5": 167.0
    },
    "name": "ダイダン",
    "price": 2912.0,
    "avg_volume": 647800
  },
  "1944.T": {
    "ticker": "1944.T",
    "bullish_prob": 0.524,
    "bearish_prob": 0.476,
    "prediction": "bullish",
    "confidence": 0.0479,
    "model_accuracy": 0.5162393162393162,
    "model_trained_at": "2026-06-30T14:47:50.008025",
    "feature_importance": {
      "vol_ratio_20": 316.0,
      "bb_width": 303.0,
      "atr_ratio": 264.0,
      "ret_5": 254.0,
      "ma_ratio_10": 249.0,
      "macd_hist": 245.0,
      "vwap_ratio": 237.0,
      "ret_10": 236.0,
      "ret_1": 232.0,
      "minute": 225.0,
      "rsi_14": 222.0,
      "body_ratio": 221.0,
      "ret_3": 213.0,
      "macd_signal": 207.0,
      "vol_ratio_5": 203.0,
      "rsi_9": 202.0,
      "high_low_ratio": 200.0,
      "macd": 189.0,
      "ma_ratio_5": 187.0,
      "bb_position": 175.0
    },
    "name": "きんでん",
    "price": 8095.0,
    "avg_volume": 631300
  },
  "2670.T": {
    "ticker": "2670.T",
    "bullish_prob": 0.8793,
    "bearish_prob": 0.1207,
    "prediction": "bullish",
    "confidence": 0.7586,
    "model_accuracy": 0.5202346041055719,
    "model_trained_at": "2026-06-30T14:47:54.879363",
    "feature_importance": {
      "vol_ratio_5": 326.0,
      "vol_ratio_20": 314.0,
      "vwap_ratio": 307.0,
      "bb_width": 284.0,
      "atr_ratio": 284.0,
      "macd_hist": 268.0,
      "high_low_ratio": 264.0,
      "ret_3": 262.0,
      "time_in_session": 248.0,
      "minute": 244.0,
      "rsi_14": 242.0,
      "ret_10": 229.0,
      "rsi_9": 229.0,
      "ret_5": 228.0,
      "ma_ratio_5": 217.0,
      "ma_ratio_10": 217.0,
      "ret_1": 215.0,
      "body_ratio": 203.0,
      "macd": 186.0,
      "bb_position": 186.0
    },
    "name": "エービーシー・マート",
    "price": 2806.0,
    "avg_volume": 628340
  },
  "1861.T": {
    "ticker": "1861.T",
    "bullish_prob": 0.0354,
    "bearish_prob": 0.9646,
    "prediction": "bearish",
    "confidence": 0.9292,
    "model_accuracy": 0.7571884984025559,
    "model_trained_at": "2026-06-30T14:47:59.267898",
    "feature_importance": {
      "vol_ratio_20": 379.0,
      "vwap_ratio": 327.0,
      "macd_hist": 299.0,
      "minute": 297.0,
      "bb_width": 291.0,
      "atr_ratio": 280.0,
      "ma_ratio_10": 275.0,
      "ret_5": 274.0,
      "vol_ratio_5": 262.0,
      "rsi_14": 259.0,
      "macd_signal": 236.0,
      "bb_position": 236.0,
      "ma_ratio_50": 234.0,
      "ret_3": 233.0,
      "ret_10": 230.0,
      "ma_ratio_5": 224.0,
      "macd": 221.0,
      "ret_1": 219.0,
      "time_in_session": 212.0,
      "ma_ratio_20": 185.0
    },
    "name": "熊谷組",
    "price": 1402.0,
    "avg_volume": 620640
  },
  "2222.T": {
    "ticker": "2222.T",
    "bullish_prob": 0.3765,
    "bearish_prob": 0.6235,
    "prediction": "bearish",
    "confidence": 0.247,
    "model_accuracy": 0.625625,
    "model_trained_at": "2026-06-30T14:48:03.687304",
    "feature_importance": {
      "vol_ratio_20": 335.0,
      "vwap_ratio": 318.0,
      "vol_ratio_5": 271.0,
      "minute": 271.0,
      "ret_3": 258.0,
      "rsi_14": 256.0,
      "ret_1": 254.0,
      "time_in_session": 234.0,
      "atr_ratio": 228.0,
      "ma_ratio_5": 226.0,
      "ret_10": 225.0,
      "macd_hist": 219.0,
      "bb_width": 212.0,
      "high_low_ratio": 212.0,
      "bb_position": 196.0,
      "macd_signal": 187.0,
      "rsi_9": 185.0,
      "ma_ratio_25": 172.0,
      "ma_ratio_10": 169.0,
      "ret_5": 167.0
    },
    "name": "寿スピリッツ",
    "price": 2433.0,
    "avg_volume": 597100
  },
  "3101.T": {
    "ticker": "3101.T",
    "bullish_prob": 0.2094,
    "bearish_prob": 0.7906,
    "prediction": "bearish",
    "confidence": 0.5812,
    "model_accuracy": 0.6804953560371516,
    "model_trained_at": "2026-06-30T14:48:08.152789",
    "feature_importance": {
      "vol_ratio_5": 360.0,
      "atr_ratio": 311.0,
      "vol_ratio_20": 276.0,
      "bb_width": 271.0,
      "minute": 269.0,
      "ret_1": 263.0,
      "time_in_session": 255.0,
      "vwap_ratio": 236.0,
      "high_low_ratio": 236.0,
      "ret_10": 231.0,
      "ret_5": 229.0,
      "ret_3": 215.0,
      "macd_signal": 212.0,
      "macd_hist": 208.0,
      "rsi_9": 203.0,
      "macd": 203.0,
      "ma_ratio_25": 191.0,
      "ma_ratio_10": 186.0,
      "ma_ratio_50": 184.0,
      "bb_position": 184.0
    },
    "name": "東洋紡",
    "price": 1667.0,
    "avg_volume": 581580
  },
  "3116.T": {
    "ticker": "3116.T",
    "bullish_prob": 0.404,
    "bearish_prob": 0.596,
    "prediction": "bearish",
    "confidence": 0.1919,
    "model_accuracy": 0.5970238095238095,
    "model_trained_at": "2026-06-30T14:48:12.635646",
    "feature_importance": {
      "bb_width": 347.0,
      "vol_ratio_5": 337.0,
      "minute": 284.0,
      "rsi_14": 281.0,
      "vwap_ratio": 271.0,
      "vol_ratio_20": 270.0,
      "macd_hist": 267.0,
      "atr_ratio": 260.0,
      "ma_ratio_5": 246.0,
      "ma_ratio_50": 244.0,
      "ret_3": 237.0,
      "ma_ratio_10": 234.0,
      "high_low_ratio": 228.0,
      "bb_position": 217.0,
      "ret_5": 215.0,
      "ret_1": 211.0,
      "time_in_session": 206.0,
      "rsi_9": 186.0,
      "macd_signal": 186.0,
      "ma_ratio_20": 167.0
    },
    "name": "トヨタ紡織",
    "price": 2131.0,
    "avg_volume": 577380
  },
  "1489.T": {
    "ticker": "1489.T",
    "bullish_prob": 0.1589,
    "bearish_prob": 0.8411,
    "prediction": "bearish",
    "confidence": 0.6821,
    "model_accuracy": 0.6247191011235955,
    "model_trained_at": "2026-06-30T14:48:17.212741",
    "feature_importance": {
      "vol_ratio_20": 299.0,
      "vol_ratio_5": 296.0,
      "atr_ratio": 295.0,
      "vwap_ratio": 283.0,
      "high_low_ratio": 280.0,
      "ret_5": 265.0,
      "ret_1": 244.0,
      "macd_hist": 236.0,
      "ma_ratio_5": 234.0,
      "ret_3": 230.0,
      "minute": 230.0,
      "bb_width": 228.0,
      "rsi_14": 224.0,
      "ret_10": 215.0,
      "ma_ratio_50": 214.0,
      "ma_ratio_10": 210.0,
      "rsi_9": 210.0,
      "macd_signal": 209.0,
      "time_in_session": 205.0,
      "ma_ratio_25": 197.0
    },
    "name": "ＮＥＸＴ　ＦＵＮＤＳ　日経平均高配当株５０指数連動型上場投信",
    "price": 3185.0,
    "avg_volume": 573614
  },
  "1719.T": {
    "ticker": "1719.T",
    "bullish_prob": 0.0856,
    "bearish_prob": 0.9144,
    "prediction": "bearish",
    "confidence": 0.8287,
    "model_accuracy": 0.6211143695014663,
    "model_trained_at": "2026-06-30T14:48:21.712610",
    "feature_importance": {
      "vol_ratio_5": 393.0,
      "vwap_ratio": 340.0,
      "vol_ratio_20": 332.0,
      "atr_ratio": 278.0,
      "minute": 272.0,
      "ret_10": 266.0,
      "bb_width": 257.0,
      "macd_hist": 240.0,
      "bb_position": 240.0,
      "ma_ratio_5": 239.0,
      "rsi_14": 231.0,
      "ret_1": 230.0,
      "rsi_9": 227.0,
      "high_low_ratio": 217.0,
      "ret_3": 214.0,
      "macd_signal": 208.0,
      "time_in_session": 189.0,
      "ret_5": 183.0,
      "ma_ratio_10": 182.0,
      "ma_ratio_25": 177.0
    },
    "name": "安藤・間",
    "price": 1764.0,
    "avg_volume": 572260
  },
  "3132.T": {
    "ticker": "3132.T",
    "bullish_prob": 0.3196,
    "bearish_prob": 0.6804,
    "prediction": "bearish",
    "confidence": 0.3607,
    "model_accuracy": 0.5484419263456091,
    "model_trained_at": "2026-06-30T14:48:30.734210",
    "feature_importance": {
      "vol_ratio_5": 294.0,
      "vol_ratio_20": 291.0,
      "bb_width": 288.0,
      "minute": 272.0,
      "ma_ratio_5": 256.0,
      "atr_ratio": 245.0,
      "ret_1": 243.0,
      "vwap_ratio": 240.0,
      "high_low_ratio": 240.0,
      "rsi_14": 228.0,
      "macd_hist": 224.0,
      "ret_3": 221.0,
      "bb_position": 212.0,
      "ret_5": 208.0,
      "ret_10": 205.0,
      "time_in_session": 202.0,
      "rsi_9": 197.0,
      "ma_ratio_10": 181.0,
      "macd_signal": 177.0,
      "ma_ratio_50": 166.0
    },
    "name": "マクニカホールディングス",
    "price": 3215.0,
    "avg_volume": 571860
  },
  "1969.T": {
    "ticker": "1969.T",
    "bullish_prob": 0.181,
    "bearish_prob": 0.819,
    "prediction": "bearish",
    "confidence": 0.6381,
    "model_accuracy": 0.5264957264957265,
    "model_trained_at": "2026-06-30T14:48:26.275659",
    "feature_importance": {
      "rsi_14": 304.0,
      "vwap_ratio": 302.0,
      "vol_ratio_20": 282.0,
      "ret_3": 253.0,
      "ret_5": 252.0,
      "ma_ratio_50": 245.0,
      "high_low_ratio": 242.0,
      "body_ratio": 237.0,
      "bb_width": 236.0,
      "time_in_session": 233.0,
      "ret_1": 226.0,
      "minute": 224.0,
      "rsi_9": 222.0,
      "macd_hist": 215.0,
      "ma_ratio_5": 205.0,
      "ret_10": 204.0,
      "vol_ratio_5": 194.0,
      "macd": 193.0,
      "bb_position": 182.0,
      "macd_signal": 179.0
    },
    "name": "高砂熱学工業",
    "price": 5043.0,
    "avg_volume": 570960
  },
  "1365.T": {
    "ticker": "1365.T",
    "bullish_prob": 0.3318,
    "bearish_prob": 0.6682,
    "prediction": "bearish",
    "confidence": 0.3364,
    "model_accuracy": 0.5320113314447592,
    "model_trained_at": "2026-06-30T14:48:35.317067",
    "feature_importance": {
      "vol_ratio_5": 309.0,
      "ret_1": 285.0,
      "rsi_14": 273.0,
      "vwap_ratio": 269.0,
      "bb_width": 265.0,
      "minute": 263.0,
      "ret_3": 240.0,
      "macd_hist": 237.0,
      "high_low_ratio": 231.0,
      "vol_ratio_20": 228.0,
      "ma_ratio_10": 224.0,
      "atr_ratio": 222.0,
      "body_ratio": 221.0,
      "ret_5": 221.0,
      "time_in_session": 221.0,
      "ma_ratio_50": 218.0,
      "rsi_9": 218.0,
      "ma_ratio_5": 217.0,
      "bb_position": 205.0,
      "ret_10": 194.0
    },
    "name": "ｉＦｒｅｅＥＴＦ　日経平均レバレッジ・インデックス",
    "price": 4912.0,
    "avg_volume": 569165
  },
  "1333.T": {
    "ticker": "1333.T",
    "bullish_prob": 0.0591,
    "bearish_prob": 0.9409,
    "prediction": "bearish",
    "confidence": 0.8818,
    "model_accuracy": 0.6727848101265823,
    "model_trained_at": "2026-06-30T14:48:39.732188",
    "feature_importance": {
      "vol_ratio_20": 308.0,
      "atr_ratio": 292.0,
      "time_in_session": 280.0,
      "ret_10": 269.0,
      "minute": 269.0,
      "vol_ratio_5": 268.0,
      "vwap_ratio": 264.0,
      "bb_width": 252.0,
      "rsi_14": 251.0,
      "ret_1": 248.0,
      "ret_5": 248.0,
      "rsi_9": 248.0,
      "ma_ratio_50": 233.0,
      "ma_ratio_5": 232.0,
      "ma_ratio_10": 216.0,
      "macd_hist": 207.0,
      "ret_3": 200.0,
      "macd_signal": 186.0,
      "high_low_ratio": 180.0,
      "ma_ratio_25": 171.0
    },
    "name": "Ｕｍｉｏｓ",
    "price": 1298.0,
    "avg_volume": 558640
  },
  "2982.T": {
    "ticker": "2982.T",
    "bullish_prob": 0.0063,
    "bearish_prob": 0.9937,
    "prediction": "bearish",
    "confidence": 0.9875,
    "model_accuracy": 0.8942528735632184,
    "model_trained_at": "2026-06-30T14:48:48.047245",
    "feature_importance": {
      "vol_ratio_20": 313.0,
      "vol_ratio_5": 289.0,
      "bb_width": 234.0,
      "macd": 229.0,
      "minute": 229.0,
      "ma_ratio_10": 218.0,
      "vwap_ratio": 218.0,
      "atr_ratio": 218.0,
      "time_in_session": 205.0,
      "ma_ratio_5": 204.0,
      "rsi_14": 196.0,
      "macd_hist": 192.0,
      "ma_ratio_25": 177.0,
      "ret_10": 175.0,
      "macd_signal": 167.0,
      "bb_position": 157.0,
      "ma_ratio_20": 152.0,
      "ma_ratio_50": 152.0,
      "rsi_9": 139.0,
      "ret_1": 121.0
    },
    "name": "ＡＤワークスグループ",
    "price": 397.0,
    "avg_volume": 552240
  },
  "1852.T": {
    "ticker": "1852.T",
    "bullish_prob": 0.0109,
    "bearish_prob": 0.9891,
    "prediction": "bearish",
    "confidence": 0.9781,
    "model_accuracy": 0.8516949152542374,
    "model_trained_at": "2026-06-30T14:48:43.984724",
    "feature_importance": {
      "vol_ratio_20": 421.0,
      "time_in_session": 369.0,
      "vol_ratio_5": 361.0,
      "macd_hist": 306.0,
      "minute": 297.0,
      "macd_signal": 267.0,
      "atr_ratio": 258.0,
      "ma_ratio_5": 241.0,
      "bb_position": 239.0,
      "ma_ratio_10": 230.0,
      "vwap_ratio": 225.0,
      "ret_10": 210.0,
      "macd": 202.0,
      "bb_width": 188.0,
      "ma_ratio_20": 187.0,
      "rsi_14": 161.0,
      "ma_ratio_50": 156.0,
      "ret_5": 154.0,
      "ma_ratio_25": 152.0,
      "ret_3": 145.0
    },
    "name": "淺沼組",
    "price": 826.0,
    "avg_volume": 550500
  },
  "1699.T": {
    "ticker": "1699.T",
    "bullish_prob": 0.0077,
    "bearish_prob": 0.9923,
    "prediction": "bearish",
    "confidence": 0.9847,
    "model_accuracy": 0.7773584905660378,
    "model_trained_at": "2026-06-30T14:48:52.194959",
    "feature_importance": {
      "vol_ratio_20": 358.0,
      "ret_3": 264.0,
      "minute": 258.0,
      "ret_1": 248.0,
      "vol_ratio_5": 244.0,
      "vwap_ratio": 242.0,
      "time_in_session": 234.0,
      "atr_ratio": 231.0,
      "ma_ratio_5": 220.0,
      "rsi_14": 219.0,
      "ma_ratio_10": 194.0,
      "macd_hist": 182.0,
      "ret_5": 179.0,
      "bb_width": 170.0,
      "ret_10": 167.0,
      "bb_position": 159.0,
      "rsi_9": 157.0,
      "high_low_ratio": 131.0,
      "macd_signal": 123.0,
      "ma_ratio_25": 104.0
    },
    "name": "ＮＥＸＴ　ＦＵＮＤＳ　ＮＯＭＵＲＡ　原油インデックス連動型上場投信",
    "price": 547.0,
    "avg_volume": 541702
  },
  "1321.T": {
    "ticker": "1321.T",
    "bullish_prob": 0.4361,
    "bearish_prob": 0.5639,
    "prediction": "bearish",
    "confidence": 0.1279,
    "model_accuracy": 0.4885793871866295,
    "model_trained_at": "2026-06-30T14:48:56.650547",
    "feature_importance": {
      "vol_ratio_5": 280.0,
      "atr_ratio": 278.0,
      "vol_ratio_20": 273.0,
      "rsi_9": 269.0,
      "vwap_ratio": 249.0,
      "ret_3": 246.0,
      "high_low_ratio": 233.0,
      "ret_5": 232.0,
      "bb_width": 229.0,
      "ret_1": 226.0,
      "body_ratio": 223.0,
      "minute": 217.0,
      "rsi_14": 216.0,
      "time_in_session": 206.0,
      "ma_ratio_5": 201.0,
      "ret_10": 199.0,
      "ma_ratio_10": 188.0,
      "macd_hist": 184.0,
      "bb_position": 180.0,
      "ma_ratio_50": 165.0
    },
    "name": "ＮＥＸＴ　ＦＵＮＤＳ　日経２２５連動型上場投信",
    "price": 73464.0,
    "avg_volume": 522768
  },
  "1308.T": {
    "ticker": "1308.T",
    "bullish_prob": 0.1942,
    "bearish_prob": 0.8058,
    "prediction": "bearish",
    "confidence": 0.6117,
    "model_accuracy": 0.6885017421602788,
    "model_trained_at": "2026-06-30T14:49:00.994274",
    "feature_importance": {
      "vol_ratio_5": 302.0,
      "rsi_14": 261.0,
      "minute": 255.0,
      "ret_5": 252.0,
      "bb_width": 244.0,
      "vwap_ratio": 243.0,
      "ma_ratio_5": 239.0,
      "time_in_session": 239.0,
      "ret_1": 234.0,
      "rsi_9": 218.0,
      "macd_signal": 214.0,
      "atr_ratio": 202.0,
      "ret_3": 195.0,
      "macd_hist": 192.0,
      "ret_10": 187.0,
      "vol_ratio_20": 178.0,
      "high_low_ratio": 178.0,
      "ma_ratio_20": 170.0,
      "ma_ratio_10": 157.0,
      "macd": 131.0
    },
    "name": "上場インデックスファンドＴＯＰＩＸ",
    "price": 4184.0,
    "avg_volume": 520739
  },
  "2585.T": {
    "ticker": "2585.T",
    "bullish_prob": 0.0776,
    "bearish_prob": 0.9224,
    "prediction": "bearish",
    "confidence": 0.8448,
    "model_accuracy": 0.6469453376205788,
    "model_trained_at": "2026-06-30T14:49:05.390587",
    "feature_importance": {
      "vol_ratio_20": 328.0,
      "atr_ratio": 296.0,
      "minute": 271.0,
      "vol_ratio_5": 270.0,
      "bb_width": 256.0,
      "time_in_session": 256.0,
      "vwap_ratio": 250.0,
      "ret_5": 248.0,
      "ret_3": 246.0,
      "ret_1": 235.0,
      "ret_10": 234.0,
      "high_low_ratio": 213.0,
      "rsi_14": 208.0,
      "ma_ratio_5": 206.0,
      "rsi_9": 204.0,
      "ma_ratio_10": 195.0,
      "macd_hist": 195.0,
      "ma_ratio_50": 191.0,
      "macd_signal": 187.0,
      "bb_position": 186.0
    },
    "name": "ライフドリンク　カンパニー",
    "price": 1616.0,
    "avg_volume": 505180
  },
  "2212.T": {
    "ticker": "2212.T",
    "bullish_prob": 0.274,
    "bearish_prob": 0.726,
    "prediction": "bearish",
    "confidence": 0.452,
    "model_accuracy": 0.6789808917197451,
    "model_trained_at": "2026-06-30T14:49:09.821650",
    "feature_importance": {
      "vol_ratio_20": 330.0,
      "rsi_14": 326.0,
      "vol_ratio_5": 317.0,
      "atr_ratio": 266.0,
      "ret_1": 255.0,
      "vwap_ratio": 253.0,
      "ret_3": 236.0,
      "ret_5": 236.0,
      "macd_signal": 230.0,
      "ret_10": 229.0,
      "macd_hist": 225.0,
      "minute": 224.0,
      "bb_width": 216.0,
      "ma_ratio_10": 207.0,
      "time_in_session": 207.0,
      "high_low_ratio": 201.0,
      "macd": 191.0,
      "bb_position": 168.0,
      "rsi_9": 165.0,
      "ma_ratio_50": 163.0
    },
    "name": "山崎製パン",
    "price": 3190.0,
    "avg_volume": 504700
  }
}