{
  "1579.T": {
    "ticker": "1579.T",
    "bullish_prob": 0.498,
    "bearish_prob": 0.502,
    "prediction": "bearish",
    "confidence": 0.004,
    "model_accuracy": 0.48611111111111116,
    "model_trained_at": "2026-07-01T15:01:25.329617",
    "feature_importance": {
      "vol_ratio_20": 330.0,
      "rsi_9": 307.0,
      "vol_ratio_5": 279.0,
      "minute": 276.0,
      "bb_width": 272.0,
      "vwap_ratio": 261.0,
      "ret_5": 256.0,
      "body_ratio": 254.0,
      "high_low_ratio": 250.0,
      "rsi_14": 249.0,
      "ret_3": 235.0,
      "ret_1": 225.0,
      "ret_10": 222.0,
      "upper_shadow": 221.0,
      "atr_ratio": 196.0,
      "ma_ratio_5": 183.0,
      "macd": 180.0,
      "ma_ratio_50": 174.0,
      "bb_position": 171.0,
      "macd_hist": 167.0
    },
    "name": "日経平均ブル２倍上場投信",
    "price": 866.0,
    "avg_volume": 20764444
  },
  "1306.T": {
    "ticker": "1306.T",
    "bullish_prob": 0.1125,
    "bearish_prob": 0.8875,
    "prediction": "bearish",
    "confidence": 0.7751,
    "model_accuracy": 0.6044568245125348,
    "model_trained_at": "2026-07-01T15:01:29.727962",
    "feature_importance": {
      "vol_ratio_20": 334.0,
      "rsi_9": 277.0,
      "vol_ratio_5": 266.0,
      "ret_3": 263.0,
      "vwap_ratio": 261.0,
      "minute": 260.0,
      "macd_hist": 259.0,
      "bb_width": 241.0,
      "ret_10": 234.0,
      "high_low_ratio": 229.0,
      "macd_signal": 228.0,
      "ma_ratio_10": 221.0,
      "ret_1": 220.0,
      "rsi_14": 210.0,
      "atr_ratio": 209.0,
      "ret_5": 202.0,
      "macd": 193.0,
      "body_ratio": 179.0,
      "time_in_session": 179.0,
      "ma_ratio_5": 161.0
    },
    "name": "ＮＥＸＴ　ＦＵＮＤＳ　ＴＯＰＩＸ連動型上場投信",
    "price": 424.0,
    "avg_volume": 19743750
  },
  "1357.T": {
    "ticker": "1357.T",
    "bullish_prob": 0.3925,
    "bearish_prob": 0.6075,
    "prediction": "bearish",
    "confidence": 0.215,
    "model_accuracy": 0.4822222222222222,
    "model_trained_at": "2026-07-01T15:01:33.915613",
    "feature_importance": {
      "high_low_ratio": 319.0,
      "bb_width": 310.0,
      "vol_ratio_20": 296.0,
      "vol_ratio_5": 294.0,
      "ret_5": 282.0,
      "minute": 257.0,
      "vwap_ratio": 239.0,
      "ret_1": 237.0,
      "ret_3": 232.0,
      "macd_hist": 211.0,
      "atr_ratio": 207.0,
      "rsi_14": 203.0,
      "ma_ratio_5": 198.0,
      "rsi_9": 198.0,
      "time_in_session": 194.0,
      "macd_signal": 183.0,
      "ret_10": 167.0,
      "ma_ratio_10": 166.0,
      "ma_ratio_25": 163.0,
      "ma_ratio_50": 153.0
    },
    "name": "ＮＥＸＴ　ＦＵＮＤＳ　日経平均ダブルインバース・インデックス連動型上場投信",
    "price": 2537.0,
    "avg_volume": 17555546
  },
  "3110.T": {
    "ticker": "3110.T",
    "bullish_prob": 0.2527,
    "bearish_prob": 0.7473,
    "prediction": "bearish",
    "confidence": 0.4945,
    "model_accuracy": 0.5338888888888889,
    "model_trained_at": "2026-07-01T15:01:38.136125",
    "feature_importance": {
      "vol_ratio_5": 330.0,
      "atr_ratio": 323.0,
      "vwap_ratio": 316.0,
      "vol_ratio_20": 286.0,
      "rsi_9": 274.0,
      "time_in_session": 268.0,
      "ret_1": 262.0,
      "minute": 253.0,
      "high_low_ratio": 228.0,
      "macd": 227.0,
      "body_ratio": 226.0,
      "ret_5": 226.0,
      "rsi_14": 208.0,
      "bb_width": 201.0,
      "ret_3": 198.0,
      "macd_hist": 193.0,
      "ma_ratio_5": 187.0,
      "ma_ratio_50": 181.0,
      "ret_10": 168.0,
      "bb_position": 168.0
    },
    "name": "日東紡績",
    "price": 4167.0,
    "avg_volume": 7681260
  },
  "1475.T": {
    "ticker": "1475.T",
    "bullish_prob": 0.0821,
    "bearish_prob": 0.9179,
    "prediction": "bearish",
    "confidence": 0.8359,
    "model_accuracy": 0.6597560975609758,
    "model_trained_at": "2026-07-01T15:01:42.389036",
    "feature_importance": {
      "vol_ratio_5": 362.0,
      "vol_ratio_20": 349.0,
      "atr_ratio": 306.0,
      "vwap_ratio": 281.0,
      "ret_1": 262.0,
      "minute": 262.0,
      "bb_width": 251.0,
      "macd_hist": 237.0,
      "rsi_9": 235.0,
      "macd_signal": 230.0,
      "high_low_ratio": 226.0,
      "ma_ratio_10": 222.0,
      "rsi_14": 219.0,
      "ma_ratio_5": 218.0,
      "ret_10": 212.0,
      "ret_5": 210.0,
      "ret_3": 207.0,
      "time_in_session": 199.0,
      "bb_position": 189.0,
      "body_ratio": 185.0
    },
    "name": "ｉシェアーズ・コア　ＴＯＰＩＸ　ＥＴＦ",
    "price": 414.0,
    "avg_volume": 6705796
  },
  "2914.T": {
    "ticker": "2914.T",
    "bullish_prob": 0.7585,
    "bearish_prob": 0.2415,
    "prediction": "bullish",
    "confidence": 0.517,
    "model_accuracy": 0.5511111111111111,
    "model_trained_at": "2026-07-01T15:01:46.625917",
    "feature_importance": {
      "vol_ratio_5": 332.0,
      "atr_ratio": 305.0,
      "rsi_9": 301.0,
      "ret_5": 287.0,
      "bb_width": 279.0,
      "vol_ratio_20": 279.0,
      "high_low_ratio": 267.0,
      "ret_3": 263.0,
      "time_in_session": 254.0,
      "vwap_ratio": 249.0,
      "ret_1": 248.0,
      "bb_position": 238.0,
      "ret_10": 222.0,
      "minute": 219.0,
      "rsi_14": 213.0,
      "ma_ratio_10": 208.0,
      "macd_hist": 207.0,
      "ma_ratio_5": 198.0,
      "macd_signal": 197.0,
      "macd": 163.0
    },
    "name": "日本たばこ産業",
    "price": 5961.0,
    "avg_volume": 5648280
  },
  "2502.T": {
    "ticker": "2502.T",
    "bullish_prob": 0.5883,
    "bearish_prob": 0.4117,
    "prediction": "bullish",
    "confidence": 0.1767,
    "model_accuracy": 0.5866666666666667,
    "model_trained_at": "2026-07-01T15:01:50.875231",
    "feature_importance": {
      "vol_ratio_5": 365.0,
      "atr_ratio": 289.0,
      "vol_ratio_20": 270.0,
      "macd_hist": 264.0,
      "minute": 256.0,
      "rsi_9": 242.0,
      "ret_3": 241.0,
      "ret_5": 238.0,
      "high_low_ratio": 238.0,
      "vwap_ratio": 229.0,
      "ma_ratio_5": 222.0,
      "time_in_session": 215.0,
      "rsi_14": 211.0,
      "macd_signal": 203.0,
      "macd": 202.0,
      "bb_width": 202.0,
      "bb_position": 188.0,
      "ret_10": 175.0,
      "ma_ratio_25": 153.0,
      "ma_ratio_10": 148.0
    },
    "name": "アサヒグループホールディングス",
    "price": 1548.0,
    "avg_volume": 5611160
  },
  "3092.T": {
    "ticker": "3092.T",
    "bullish_prob": 0.1008,
    "bearish_prob": 0.8992,
    "prediction": "bearish",
    "confidence": 0.7984,
    "model_accuracy": 0.6112359550561797,
    "model_trained_at": "2026-07-01T15:01:55.207152",
    "feature_importance": {
      "vol_ratio_20": 334.0,
      "bb_width": 311.0,
      "vol_ratio_5": 310.0,
      "minute": 302.0,
      "ret_5": 297.0,
      "ret_3": 293.0,
      "time_in_session": 283.0,
      "atr_ratio": 277.0,
      "high_low_ratio": 273.0,
      "rsi_9": 268.0,
      "ma_ratio_5": 265.0,
      "vwap_ratio": 249.0,
      "rsi_14": 247.0,
      "ret_10": 239.0,
      "macd_hist": 233.0,
      "ma_ratio_50": 225.0,
      "bb_position": 221.0,
      "ret_1": 211.0,
      "macd": 167.0,
      "macd_signal": 166.0
    },
    "name": "ＺＯＺＯ",
    "price": 1134.0,
    "avg_volume": 5497000
  },
  "3382.T": {
    "ticker": "3382.T",
    "bullish_prob": 0.5885,
    "bearish_prob": 0.4115,
    "prediction": "bullish",
    "confidence": 0.177,
    "model_accuracy": 0.5355555555555556,
    "model_trained_at": "2026-07-01T15:01:59.462039",
    "feature_importance": {
      "atr_ratio": 292.0,
      "macd_hist": 283.0,
      "vol_ratio_5": 274.0,
      "bb_width": 269.0,
      "ret_1": 258.0,
      "vwap_ratio": 254.0,
      "minute": 240.0,
      "ret_3": 239.0,
      "rsi_14": 239.0,
      "vol_ratio_20": 239.0,
      "macd_signal": 230.0,
      "ret_5": 221.0,
      "ret_10": 213.0,
      "rsi_9": 213.0,
      "ma_ratio_5": 201.0,
      "ma_ratio_50": 190.0,
      "high_low_ratio": 189.0,
      "ma_ratio_10": 179.0,
      "time_in_session": 176.0,
      "bb_position": 171.0
    },
    "name": "セブン＆アイ・ホールディングス",
    "price": 1934.0,
    "avg_volume": 5328960
  },
  "1605.T": {
    "ticker": "1605.T",
    "bullish_prob": 0.3664,
    "bearish_prob": 0.6336,
    "prediction": "bearish",
    "confidence": 0.2671,
    "model_accuracy": 0.5683333333333334,
    "model_trained_at": "2026-07-01T15:02:03.635454",
    "feature_importance": {
      "vol_ratio_5": 363.0,
      "vol_ratio_20": 306.0,
      "ret_3": 282.0,
      "atr_ratio": 269.0,
      "rsi_9": 268.0,
      "vwap_ratio": 266.0,
      "minute": 258.0,
      "rsi_14": 233.0,
      "bb_width": 233.0,
      "ma_ratio_5": 221.0,
      "macd_hist": 219.0,
      "time_in_session": 212.0,
      "ret_1": 208.0,
      "ma_ratio_10": 192.0,
      "high_low_ratio": 183.0,
      "bb_position": 176.0,
      "ret_5": 174.0,
      "ret_10": 166.0,
      "macd_signal": 166.0,
      "body_ratio": 153.0
    },
    "name": "ＩＮＰＥＸ",
    "price": 3256.0,
    "avg_volume": 4956180
  },
  "1911.T": {
    "ticker": "1911.T",
    "bullish_prob": 0.3888,
    "bearish_prob": 0.6112,
    "prediction": "bearish",
    "confidence": 0.2224,
    "model_accuracy": 0.6279329608938548,
    "model_trained_at": "2026-07-01T15:02:08.066709",
    "feature_importance": {
      "bb_width": 349.0,
      "vol_ratio_20": 345.0,
      "ret_3": 299.0,
      "vwap_ratio": 295.0,
      "ma_ratio_5": 284.0,
      "vol_ratio_5": 281.0,
      "ma_ratio_10": 279.0,
      "atr_ratio": 270.0,
      "ret_5": 260.0,
      "ret_1": 259.0,
      "minute": 255.0,
      "macd_hist": 250.0,
      "rsi_14": 249.0,
      "high_low_ratio": 247.0,
      "rsi_9": 241.0,
      "bb_position": 236.0,
      "ret_10": 216.0,
      "ma_ratio_25": 209.0,
      "time_in_session": 202.0,
      "ma_ratio_50": 185.0
    },
    "name": "住友林業",
    "price": 1343.0,
    "avg_volume": 4600840
  },
  "2802.T": {
    "ticker": "2802.T",
    "bullish_prob": 0.1905,
    "bearish_prob": 0.8095,
    "prediction": "bearish",
    "confidence": 0.6191,
    "model_accuracy": 0.5122222222222221,
    "model_trained_at": "2026-07-01T15:02:12.269386",
    "feature_importance": {
      "vol_ratio_5": 309.0,
      "ret_3": 293.0,
      "vwap_ratio": 285.0,
      "vol_ratio_20": 254.0,
      "minute": 244.0,
      "rsi_9": 241.0,
      "high_low_ratio": 230.0,
      "bb_width": 228.0,
      "time_in_session": 217.0,
      "ret_1": 215.0,
      "rsi_14": 213.0,
      "ret_5": 209.0,
      "macd_hist": 205.0,
      "ma_ratio_5": 202.0,
      "body_ratio": 201.0,
      "ret_10": 186.0,
      "ma_ratio_20": 176.0,
      "ma_ratio_10": 169.0,
      "atr_ratio": 162.0,
      "macd_signal": 159.0
    },
    "name": "味の素",
    "price": 5855.0,
    "avg_volume": 4182420
  },
  "3197.T": {
    "ticker": "3197.T",
    "bullish_prob": 0.2285,
    "bearish_prob": 0.7715,
    "prediction": "bearish",
    "confidence": 0.5431,
    "model_accuracy": 0.5227777777777778,
    "model_trained_at": "2026-07-01T15:02:16.563183",
    "feature_importance": {
      "ret_3": 336.0,
      "ret_5": 326.0,
      "vol_ratio_5": 315.0,
      "vwap_ratio": 314.0,
      "vol_ratio_20": 306.0,
      "macd_hist": 304.0,
      "minute": 297.0,
      "rsi_9": 273.0,
      "bb_width": 269.0,
      "ma_ratio_5": 261.0,
      "high_low_ratio": 245.0,
      "macd_signal": 239.0,
      "atr_ratio": 228.0,
      "ret_1": 226.0,
      "ret_10": 223.0,
      "rsi_14": 220.0,
      "time_in_session": 220.0,
      "ma_ratio_10": 217.0,
      "bb_position": 198.0,
      "ma_ratio_20": 196.0
    },
    "name": "すかいらーくホールディングス",
    "price": 2801.0,
    "avg_volume": 4018780
  },
  "1615.T": {
    "ticker": "1615.T",
    "bullish_prob": 0.4139,
    "bearish_prob": 0.5861,
    "prediction": "bearish",
    "confidence": 0.1721,
    "model_accuracy": 0.5616901408450705,
    "model_trained_at": "2026-07-01T15:02:20.896239",
    "feature_importance": {
      "rsi_14": 303.0,
      "vol_ratio_5": 288.0,
      "ret_1": 276.0,
      "ret_3": 261.0,
      "vwap_ratio": 259.0,
      "atr_ratio": 259.0,
      "bb_width": 254.0,
      "rsi_9": 249.0,
      "vol_ratio_20": 247.0,
      "ma_ratio_5": 238.0,
      "ret_10": 236.0,
      "ma_ratio_10": 231.0,
      "ret_5": 227.0,
      "body_ratio": 226.0,
      "macd_hist": 225.0,
      "time_in_session": 217.0,
      "bb_position": 215.0,
      "macd_signal": 207.0,
      "high_low_ratio": 201.0,
      "minute": 199.0
    },
    "name": "ＮＥＸＴ　ＦＵＮＤＳ　東証銀行業株価指数連動型上場投信",
    "price": 703.0,
    "avg_volume": 3962458
  },
  "3402.T": {
    "ticker": "3402.T",
    "bullish_prob": 0.3943,
    "bearish_prob": 0.6057,
    "prediction": "bearish",
    "confidence": 0.2113,
    "model_accuracy": 0.6005571030640668,
    "model_trained_at": "2026-07-01T15:02:25.155454",
    "feature_importance": {
      "vol_ratio_20": 334.0,
      "vol_ratio_5": 323.0,
      "atr_ratio": 282.0,
      "ret_3": 256.0,
      "high_low_ratio": 254.0,
      "vwap_ratio": 253.0,
      "time_in_session": 241.0,
      "rsi_9": 235.0,
      "ret_5": 234.0,
      "rsi_14": 228.0,
      "ma_ratio_5": 221.0,
      "macd_hist": 220.0,
      "ma_ratio_10": 218.0,
      "macd_signal": 209.0,
      "bb_width": 207.0,
      "ret_10": 206.0,
      "minute": 206.0,
      "bb_position": 205.0,
      "ret_1": 195.0,
      "ma_ratio_20": 189.0
    },
    "name": "東レ",
    "price": 1138.0,
    "avg_volume": 3872400
  },
  "1568.T": {
    "ticker": "1568.T",
    "bullish_prob": 0.1204,
    "bearish_prob": 0.8796,
    "prediction": "bearish",
    "confidence": 0.7592,
    "model_accuracy": 0.5857142857142857,
    "model_trained_at": "2026-07-01T15:02:29.416360",
    "feature_importance": {
      "vol_ratio_20": 327.0,
      "bb_width": 303.0,
      "vwap_ratio": 288.0,
      "ret_10": 281.0,
      "ret_5": 260.0,
      "atr_ratio": 256.0,
      "vol_ratio_5": 253.0,
      "ret_3": 251.0,
      "rsi_9": 240.0,
      "ret_1": 238.0,
      "ma_ratio_5": 238.0,
      "ma_ratio_10": 236.0,
      "macd_hist": 233.0,
      "minute": 227.0,
      "time_in_session": 216.0,
      "high_low_ratio": 213.0,
      "macd_signal": 203.0,
      "body_ratio": 194.0,
      "rsi_14": 192.0,
      "macd": 150.0
    },
    "name": "ＴＯＰＩＸブル２倍上場投信",
    "price": 962.0,
    "avg_volume": 3853242
  },
  "1570.T": {
    "ticker": "1570.T",
    "bullish_prob": 0.3461,
    "bearish_prob": 0.6539,
    "prediction": "bearish",
    "confidence": 0.3078,
    "model_accuracy": 0.5005555555555555,
    "model_trained_at": "2026-07-01T15:02:33.704730",
    "feature_importance": {
      "vol_ratio_5": 311.0,
      "ret_5": 288.0,
      "vwap_ratio": 275.0,
      "rsi_9": 272.0,
      "ret_3": 256.0,
      "vol_ratio_20": 256.0,
      "ret_1": 228.0,
      "minute": 223.0,
      "macd_hist": 204.0,
      "macd": 200.0,
      "body_ratio": 199.0,
      "atr_ratio": 198.0,
      "ret_10": 197.0,
      "time_in_session": 194.0,
      "rsi_14": 190.0,
      "high_low_ratio": 186.0,
      "ma_ratio_5": 181.0,
      "upper_shadow": 170.0,
      "macd_signal": 160.0,
      "ma_ratio_10": 157.0
    },
    "name": "ＮＥＸＴ　ＦＵＮＤＳ　日経平均レバレッジ・インデックス連動型上場投信",
    "price": 80126.0,
    "avg_volume": 3676437
  },
  "3407.T": {
    "ticker": "3407.T",
    "bullish_prob": 0.4293,
    "bearish_prob": 0.5707,
    "prediction": "bearish",
    "confidence": 0.1415,
    "model_accuracy": 0.5405555555555555,
    "model_trained_at": "2026-07-01T15:02:42.178945",
    "feature_importance": {
      "vol_ratio_5": 330.0,
      "atr_ratio": 301.0,
      "ma_ratio_5": 298.0,
      "vwap_ratio": 287.0,
      "ret_5": 284.0,
      "vol_ratio_20": 277.0,
      "minute": 264.0,
      "ret_3": 259.0,
      "rsi_9": 255.0,
      "bb_width": 238.0,
      "high_low_ratio": 238.0,
      "macd_signal": 224.0,
      "rsi_14": 219.0,
      "bb_position": 215.0,
      "macd_hist": 214.0,
      "time_in_session": 200.0,
      "macd": 195.0,
      "ma_ratio_50": 190.0,
      "ret_1": 188.0,
      "ma_ratio_10": 176.0
    },
    "name": "旭化成",
    "price": 1793.0,
    "avg_volume": 3674700
  },
  "2413.T": {
    "ticker": "2413.T",
    "bullish_prob": 0.6294,
    "bearish_prob": 0.3706,
    "prediction": "bullish",
    "confidence": 0.2588,
    "model_accuracy": 0.5411111111111111,
    "model_trained_at": "2026-07-01T15:02:37.929792",
    "feature_importance": {
      "vol_ratio_20": 363.0,
      "vwap_ratio": 309.0,
      "vol_ratio_5": 302.0,
      "macd_hist": 271.0,
      "minute": 258.0,
      "high_low_ratio": 257.0,
      "bb_width": 254.0,
      "rsi_14": 251.0,
      "time_in_session": 233.0,
      "atr_ratio": 220.0,
      "ma_ratio_50": 205.0,
      "ma_ratio_5": 204.0,
      "ret_5": 201.0,
      "ret_3": 197.0,
      "ma_ratio_10": 197.0,
      "body_ratio": 188.0,
      "ret_10": 188.0,
      "macd": 182.0,
      "ret_1": 179.0,
      "macd_signal": 177.0
    },
    "name": "エムスリー",
    "price": 1788.0,
    "avg_volume": 3671360
  },
  "3289.T": {
    "ticker": "3289.T",
    "bullish_prob": 0.0494,
    "bearish_prob": 0.9506,
    "prediction": "bearish",
    "confidence": 0.9012,
    "model_accuracy": 0.6814606741573034,
    "model_trained_at": "2026-07-01T15:02:46.591092",
    "feature_importance": {
      "atr_ratio": 306.0,
      "rsi_9": 305.0,
      "high_low_ratio": 305.0,
      "vol_ratio_5": 301.0,
      "macd_hist": 288.0,
      "vwap_ratio": 282.0,
      "ret_10": 268.0,
      "vol_ratio_20": 268.0,
      "minute": 256.0,
      "bb_position": 245.0,
      "bb_width": 241.0,
      "ret_5": 237.0,
      "ret_3": 234.0,
      "ma_ratio_10": 231.0,
      "time_in_session": 227.0,
      "ma_ratio_5": 218.0,
      "macd_signal": 212.0,
      "rsi_14": 207.0,
      "ma_ratio_50": 195.0,
      "ret_1": 189.0
    },
    "name": "東急不動産ホールディングス",
    "price": 1285.0,
    "avg_volume": 3631980
  },
  "2801.T": {
    "ticker": "2801.T",
    "bullish_prob": 0.5293,
    "bearish_prob": 0.4707,
    "prediction": "bullish",
    "confidence": 0.0586,
    "model_accuracy": 0.5426183844011142,
    "model_trained_at": "2026-07-01T15:02:50.870626",
    "feature_importance": {
      "high_low_ratio": 343.0,
      "ret_3": 326.0,
      "vwap_ratio": 313.0,
      "vol_ratio_20": 297.0,
      "vol_ratio_5": 292.0,
      "ret_1": 287.0,
      "time_in_session": 285.0,
      "ret_5": 283.0,
      "rsi_14": 263.0,
      "atr_ratio": 258.0,
      "rsi_9": 246.0,
      "minute": 244.0,
      "macd_signal": 235.0,
      "ma_ratio_5": 231.0,
      "bb_position": 222.0,
      "macd_hist": 210.0,
      "ma_ratio_10": 206.0,
      "ret_10": 196.0,
      "bb_width": 193.0,
      "body_ratio": 165.0
    },
    "name": "キッコーマン",
    "price": 1639.0,
    "avg_volume": 3627520
  },
  "3086.T": {
    "ticker": "3086.T",
    "bullish_prob": 0.3343,
    "bearish_prob": 0.6657,
    "prediction": "bearish",
    "confidence": 0.3314,
    "model_accuracy": 0.5083333333333334,
    "model_trained_at": "2026-07-01T15:02:55.136472",
    "feature_importance": {
      "high_low_ratio": 381.0,
      "vol_ratio_20": 322.0,
      "rsi_9": 303.0,
      "vol_ratio_5": 300.0,
      "ret_5": 292.0,
      "bb_width": 285.0,
      "vwap_ratio": 284.0,
      "body_ratio": 272.0,
      "time_in_session": 260.0,
      "macd_signal": 239.0,
      "rsi_14": 235.0,
      "bb_position": 234.0,
      "atr_ratio": 231.0,
      "ret_1": 221.0,
      "macd_hist": 221.0,
      "ret_10": 204.0,
      "ret_3": 203.0,
      "minute": 203.0,
      "ma_ratio_5": 189.0,
      "ma_ratio_10": 183.0
    },
    "name": "Ｊ．フロント　リテイリング",
    "price": 3377.0,
    "avg_volume": 3479100
  },
  "2503.T": {
    "ticker": "2503.T",
    "bullish_prob": 0.7389,
    "bearish_prob": 0.2611,
    "prediction": "bullish",
    "confidence": 0.4779,
    "model_accuracy": 0.5096952908587258,
    "model_trained_at": "2026-07-01T15:02:59.445047",
    "feature_importance": {
      "vol_ratio_20": 304.0,
      "high_low_ratio": 298.0,
      "vwap_ratio": 295.0,
      "vol_ratio_5": 288.0,
      "rsi_14": 276.0,
      "bb_width": 272.0,
      "ret_1": 258.0,
      "ma_ratio_10": 250.0,
      "time_in_session": 239.0,
      "macd_signal": 228.0,
      "ret_3": 214.0,
      "ret_5": 213.0,
      "macd_hist": 212.0,
      "ma_ratio_5": 211.0,
      "atr_ratio": 208.0,
      "ret_10": 190.0,
      "minute": 190.0,
      "rsi_9": 172.0,
      "ma_ratio_50": 168.0,
      "bb_position": 155.0
    },
    "name": "キリンホールディングス",
    "price": 2795.0,
    "avg_volume": 3172880
  },
  "2644.T": {
    "ticker": "2644.T",
    "bullish_prob": 0.3083,
    "bearish_prob": 0.6917,
    "prediction": "bearish",
    "confidence": 0.3834,
    "model_accuracy": 0.4997214484679665,
    "model_trained_at": "2026-07-01T15:03:04.058918",
    "feature_importance": {
      "vol_ratio_20": 317.0,
      "vol_ratio_5": 314.0,
      "high_low_ratio": 304.0,
      "bb_width": 285.0,
      "ret_5": 273.0,
      "ret_3": 272.0,
      "rsi_14": 267.0,
      "macd_hist": 266.0,
      "ma_ratio_5": 236.0,
      "vwap_ratio": 234.0,
      "atr_ratio": 223.0,
      "rsi_9": 220.0,
      "minute": 217.0,
      "time_in_session": 213.0,
      "body_ratio": 209.0,
      "ret_1": 202.0,
      "macd": 200.0,
      "ma_ratio_10": 196.0,
      "macd_signal": 194.0,
      "ret_10": 170.0
    },
    "name": "グローバルＸ　半導体関連－日本株式　ＥＴＦ",
    "price": 4942.0,
    "avg_volume": 2988334
  },
  "3231.T": {
    "ticker": "3231.T",
    "bullish_prob": 0.1937,
    "bearish_prob": 0.8063,
    "prediction": "bearish",
    "confidence": 0.6125,
    "model_accuracy": 0.5305555555555556,
    "model_trained_at": "2026-07-01T15:03:08.402959",
    "feature_importance": {
      "vol_ratio_5": 354.0,
      "rsi_14": 326.0,
      "vol_ratio_20": 311.0,
      "vwap_ratio": 281.0,
      "rsi_9": 279.0,
      "body_ratio": 266.0,
      "ret_3": 261.0,
      "atr_ratio": 244.0,
      "time_in_session": 237.0,
      "ret_1": 233.0,
      "bb_width": 226.0,
      "minute": 226.0,
      "ret_5": 223.0,
      "macd_hist": 220.0,
      "ret_10": 215.0,
      "macd_signal": 207.0,
      "high_low_ratio": 207.0,
      "ma_ratio_5": 202.0,
      "ma_ratio_50": 188.0,
      "ma_ratio_10": 181.0
    },
    "name": "野村不動産ホールディングス",
    "price": 928.0,
    "avg_volume": 2962280
  },
  "3003.T": {
    "ticker": "3003.T",
    "bullish_prob": 0.2143,
    "bearish_prob": 0.7857,
    "prediction": "bearish",
    "confidence": 0.5713,
    "model_accuracy": 0.6541899441340782,
    "model_trained_at": "2026-07-01T15:03:12.589209",
    "feature_importance": {
      "vwap_ratio": 356.0,
      "vol_ratio_20": 338.0,
      "ret_5": 324.0,
      "rsi_14": 313.0,
      "vol_ratio_5": 280.0,
      "minute": 261.0,
      "bb_position": 254.0,
      "ma_ratio_5": 247.0,
      "bb_width": 245.0,
      "macd_hist": 244.0,
      "atr_ratio": 243.0,
      "macd_signal": 239.0,
      "rsi_9": 224.0,
      "time_in_session": 221.0,
      "ret_3": 207.0,
      "ret_10": 207.0,
      "ma_ratio_10": 201.0,
      "high_low_ratio": 187.0,
      "ma_ratio_50": 181.0,
      "macd": 180.0
    },
    "name": "ヒューリック",
    "price": 1684.0,
    "avg_volume": 2919660
  },
  "1802.T": {
    "ticker": "1802.T",
    "bullish_prob": 0.2816,
    "bearish_prob": 0.7184,
    "prediction": "bearish",
    "confidence": 0.4369,
    "model_accuracy": 0.5411111111111111,
    "model_trained_at": "2026-07-01T15:03:16.982306",
    "feature_importance": {
      "vol_ratio_5": 289.0,
      "vol_ratio_20": 281.0,
      "vwap_ratio": 259.0,
      "bb_width": 257.0,
      "ret_3": 252.0,
      "rsi_14": 250.0,
      "rsi_9": 249.0,
      "macd_hist": 248.0,
      "ret_5": 241.0,
      "minute": 234.0,
      "high_low_ratio": 230.0,
      "atr_ratio": 225.0,
      "time_in_session": 218.0,
      "ma_ratio_5": 212.0,
      "macd": 210.0,
      "ma_ratio_10": 209.0,
      "ret_1": 203.0,
      "ma_ratio_25": 181.0,
      "ret_10": 167.0,
      "macd_signal": 165.0
    },
    "name": "大林組",
    "price": 3220.0,
    "avg_volume": 2888180
  },
  "1928.T": {
    "ticker": "1928.T",
    "bullish_prob": 0.0164,
    "bearish_prob": 0.9836,
    "prediction": "bearish",
    "confidence": 0.9672,
    "model_accuracy": 0.6438202247191012,
    "model_trained_at": "2026-07-01T15:03:21.250423",
    "feature_importance": {
      "vol_ratio_5": 393.0,
      "vol_ratio_20": 345.0,
      "vwap_ratio": 324.0,
      "bb_width": 321.0,
      "ma_ratio_5": 302.0,
      "bb_position": 285.0,
      "rsi_14": 284.0,
      "atr_ratio": 275.0,
      "macd_hist": 267.0,
      "minute": 265.0,
      "ma_ratio_10": 242.0,
      "ret_1": 241.0,
      "rsi_9": 227.0,
      "time_in_session": 224.0,
      "high_low_ratio": 221.0,
      "ma_ratio_25": 220.0,
      "ret_10": 213.0,
      "ret_5": 196.0,
      "ret_3": 193.0,
      "macd_signal": 191.0
    },
    "name": "積水ハウス",
    "price": 3347.0,
    "avg_volume": 2850600
  },
  "1925.T": {
    "ticker": "1925.T",
    "bullish_prob": 0.427,
    "bearish_prob": 0.573,
    "prediction": "bearish",
    "confidence": 0.146,
    "model_accuracy": 0.592200557103064,
    "model_trained_at": "2026-07-01T15:03:25.581469",
    "feature_importance": {
      "atr_ratio": 357.0,
      "vol_ratio_20": 324.0,
      "vol_ratio_5": 305.0,
      "vwap_ratio": 293.0,
      "ret_5": 292.0,
      "ma_ratio_5": 286.0,
      "rsi_9": 278.0,
      "bb_width": 278.0,
      "ret_10": 270.0,
      "rsi_14": 259.0,
      "time_in_session": 251.0,
      "macd_hist": 249.0,
      "ret_1": 248.0,
      "ma_ratio_25": 224.0,
      "high_low_ratio": 224.0,
      "ma_ratio_10": 212.0,
      "ret_3": 211.0,
      "minute": 208.0,
      "ma_ratio_50": 201.0,
      "bb_position": 195.0
    },
    "name": "大和ハウス工業",
    "price": 4406.0,
    "avg_volume": 2689700
  },
  "1803.T": {
    "ticker": "1803.T",
    "bullish_prob": 0.4488,
    "bearish_prob": 0.5512,
    "prediction": "bearish",
    "confidence": 0.1024,
    "model_accuracy": 0.5005555555555555,
    "model_trained_at": "2026-07-01T15:03:29.866057",
    "feature_importance": {
      "vol_ratio_5": 331.0,
      "bb_width": 282.0,
      "vwap_ratio": 258.0,
      "atr_ratio": 246.0,
      "ma_ratio_10": 240.0,
      "ret_5": 238.0,
      "high_low_ratio": 236.0,
      "bb_position": 227.0,
      "ret_1": 225.0,
      "rsi_9": 224.0,
      "ret_10": 213.0,
      "minute": 203.0,
      "macd_signal": 198.0,
      "ret_3": 194.0,
      "rsi_14": 192.0,
      "body_ratio": 191.0,
      "vol_ratio_20": 185.0,
      "ma_ratio_50": 177.0,
      "ma_ratio_20": 170.0,
      "time_in_session": 166.0
    },
    "name": "清水建設",
    "price": 2550.0,
    "avg_volume": 2597840
  },
  "3103.T": {
    "ticker": "3103.T",
    "bullish_prob": 0.2036,
    "bearish_prob": 0.7964,
    "prediction": "bearish",
    "confidence": 0.5929,
    "model_accuracy": 0.5905555555555556,
    "model_trained_at": "2026-07-01T15:03:34.228978",
    "feature_importance": {
      "vol_ratio_20": 324.0,
      "high_low_ratio": 322.0,
      "vwap_ratio": 300.0,
      "ma_ratio_10": 253.0,
      "vol_ratio_5": 251.0,
      "rsi_14": 250.0,
      "atr_ratio": 246.0,
      "ret_5": 230.0,
      "minute": 230.0,
      "time_in_session": 229.0,
      "ret_1": 221.0,
      "rsi_9": 216.0,
      "bb_width": 215.0,
      "ret_10": 214.0,
      "macd_hist": 211.0,
      "ma_ratio_5": 177.0,
      "macd_signal": 176.0,
      "ret_3": 162.0,
      "bb_position": 155.0,
      "ma_ratio_50": 147.0
    },
    "name": "ユニチカ",
    "price": 1036.0,
    "avg_volume": 2484060
  },
  "3405.T": {
    "ticker": "3405.T",
    "bullish_prob": 0.0818,
    "bearish_prob": 0.9182,
    "prediction": "bearish",
    "confidence": 0.8365,
    "model_accuracy": 0.6011235955056179,
    "model_trained_at": "2026-07-01T15:03:38.530046",
    "feature_importance": {
      "vol_ratio_5": 415.0,
      "vol_ratio_20": 316.0,
      "high_low_ratio": 296.0,
      "minute": 287.0,
      "vwap_ratio": 283.0,
      "atr_ratio": 281.0,
      "bb_width": 274.0,
      "macd_hist": 270.0,
      "time_in_session": 258.0,
      "ret_10": 256.0,
      "ret_1": 254.0,
      "ret_5": 240.0,
      "macd_signal": 233.0,
      "ret_3": 224.0,
      "macd": 217.0,
      "rsi_14": 209.0,
      "rsi_9": 199.0,
      "ma_ratio_10": 187.0,
      "ma_ratio_25": 183.0,
      "ma_ratio_50": 183.0
    },
    "name": "クラレ",
    "price": 1662.0,
    "avg_volume": 2406960
  },
  "3387.T": {
    "ticker": "3387.T",
    "bullish_prob": 0.0141,
    "bearish_prob": 0.9859,
    "prediction": "bearish",
    "confidence": 0.9719,
    "model_accuracy": 0.8508474576271187,
    "model_trained_at": "2026-07-01T15:03:42.655578",
    "feature_importance": {
      "vol_ratio_5": 424.0,
      "vol_ratio_20": 354.0,
      "atr_ratio": 339.0,
      "minute": 326.0,
      "macd_signal": 323.0,
      "ma_ratio_5": 319.0,
      "bb_width": 286.0,
      "bb_position": 278.0,
      "ma_ratio_10": 275.0,
      "macd_hist": 261.0,
      "time_in_session": 257.0,
      "macd": 240.0,
      "ma_ratio_50": 205.0,
      "ma_ratio_25": 199.0,
      "ret_10": 198.0,
      "vwap_ratio": 194.0,
      "ret_3": 179.0,
      "ret_5": 167.0,
      "ret_1": 148.0,
      "high_low_ratio": 135.0
    },
    "name": "クリエイト・レストランツ・ホールディングス",
    "price": 727.0,
    "avg_volume": 2089760
  },
  "3099.T": {
    "ticker": "3099.T",
    "bullish_prob": 0.3883,
    "bearish_prob": 0.6117,
    "prediction": "bearish",
    "confidence": 0.2235,
    "model_accuracy": 0.5394444444444444,
    "model_trained_at": "2026-07-01T15:03:47.037879",
    "feature_importance": {
      "vol_ratio_5": 328.0,
      "rsi_14": 304.0,
      "ma_ratio_5": 302.0,
      "ret_10": 300.0,
      "ret_3": 297.0,
      "minute": 286.0,
      "vol_ratio_20": 267.0,
      "atr_ratio": 266.0,
      "time_in_session": 266.0,
      "ret_1": 261.0,
      "vwap_ratio": 254.0,
      "high_low_ratio": 253.0,
      "bb_width": 243.0,
      "ret_5": 241.0,
      "rsi_9": 233.0,
      "macd_hist": 224.0,
      "macd_signal": 214.0,
      "ma_ratio_50": 191.0,
      "macd": 186.0,
      "ma_ratio_25": 183.0
    },
    "name": "三越伊勢丹ホールディングス",
    "price": 4106.0,
    "avg_volume": 2083060
  },
  "2492.T": {
    "ticker": "2492.T",
    "bullish_prob": 0.1083,
    "bearish_prob": 0.8917,
    "prediction": "bearish",
    "confidence": 0.7834,
    "model_accuracy": 0.8532751091703057,
    "model_trained_at": "2026-07-01T15:03:51.014746",
    "feature_importance": {
      "vol_ratio_5": 383.0,
      "bb_width": 354.0,
      "vol_ratio_20": 332.0,
      "atr_ratio": 305.0,
      "minute": 276.0,
      "time_in_session": 248.0,
      "vwap_ratio": 247.0,
      "macd_hist": 236.0,
      "ma_ratio_10": 235.0,
      "macd": 234.0,
      "macd_signal": 216.0,
      "ret_1": 212.0,
      "ma_ratio_25": 207.0,
      "ma_ratio_5": 204.0,
      "bb_position": 198.0,
      "rsi_14": 192.0,
      "ret_10": 168.0,
      "ret_5": 140.0,
      "ma_ratio_50": 122.0,
      "ret_3": 120.0
    },
    "name": "インフォマート",
    "price": 373.0,
    "avg_volume": 1949180
  },
  "3064.T": {
    "ticker": "3064.T",
    "bullish_prob": 0.1886,
    "bearish_prob": 0.8114,
    "prediction": "bearish",
    "confidence": 0.6227,
    "model_accuracy": 0.5458100558659218,
    "model_trained_at": "2026-07-01T15:03:55.403911",
    "feature_importance": {
      "ret_5": 318.0,
      "time_in_session": 315.0,
      "vwap_ratio": 311.0,
      "vol_ratio_20": 287.0,
      "rsi_9": 284.0,
      "macd_hist": 283.0,
      "ret_3": 281.0,
      "bb_width": 279.0,
      "minute": 278.0,
      "rsi_14": 275.0,
      "vol_ratio_5": 269.0,
      "ret_1": 256.0,
      "atr_ratio": 255.0,
      "ma_ratio_5": 252.0,
      "high_low_ratio": 241.0,
      "ret_10": 235.0,
      "bb_position": 218.0,
      "ma_ratio_20": 188.0,
      "ma_ratio_50": 187.0,
      "body_ratio": 185.0
    },
    "name": "ＭｏｎｏｔａＲＯ",
    "price": 1794.0,
    "avg_volume": 1923480
  },
  "2127.T": {
    "ticker": "2127.T",
    "bullish_prob": 0.047,
    "bearish_prob": 0.953,
    "prediction": "bearish",
    "confidence": 0.906,
    "model_accuracy": 0.53954802259887,
    "model_trained_at": "2026-07-01T15:03:59.901799",
    "feature_importance": {
      "vol_ratio_5": 339.0,
      "vol_ratio_20": 327.0,
      "ret_1": 309.0,
      "vwap_ratio": 292.0,
      "atr_ratio": 281.0,
      "ret_5": 273.0,
      "rsi_9": 267.0,
      "time_in_session": 267.0,
      "bb_width": 260.0,
      "rsi_14": 259.0,
      "ma_ratio_5": 252.0,
      "ret_10": 246.0,
      "minute": 236.0,
      "body_ratio": 235.0,
      "high_low_ratio": 232.0,
      "macd_signal": 218.0,
      "macd_hist": 195.0,
      "ret_3": 192.0,
      "ma_ratio_25": 192.0,
      "ma_ratio_50": 191.0
    },
    "name": "日本Ｍ＆Ａセンターホールディングス",
    "price": 630.0,
    "avg_volume": 1847060
  },
  "2264.T": {
    "ticker": "2264.T",
    "bullish_prob": 0.1642,
    "bearish_prob": 0.8358,
    "prediction": "bearish",
    "confidence": 0.6716,
    "model_accuracy": 0.5366863905325444,
    "model_trained_at": "2026-07-01T15:04:04.330460",
    "feature_importance": {
      "vwap_ratio": 302.0,
      "vol_ratio_5": 289.0,
      "vol_ratio_20": 278.0,
      "atr_ratio": 272.0,
      "ret_5": 246.0,
      "minute": 238.0,
      "ret_10": 235.0,
      "rsi_9": 232.0,
      "time_in_session": 228.0,
      "high_low_ratio": 224.0,
      "macd_hist": 222.0,
      "rsi_14": 215.0,
      "ma_ratio_5": 195.0,
      "bb_width": 194.0,
      "bb_position": 190.0,
      "ret_3": 185.0,
      "macd_signal": 178.0,
      "ret_1": 175.0,
      "ma_ratio_20": 165.0,
      "ma_ratio_25": 159.0
    },
    "name": "森永乳業",
    "price": 1252.0,
    "avg_volume": 1772600
  },
  "1812.T": {
    "ticker": "1812.T",
    "bullish_prob": 0.7906,
    "bearish_prob": 0.2094,
    "prediction": "bullish",
    "confidence": 0.5813,
    "model_accuracy": 0.515235457063712,
    "model_trained_at": "2026-07-01T15:04:08.673222",
    "feature_importance": {
      "vol_ratio_20": 375.0,
      "vol_ratio_5": 369.0,
      "vwap_ratio": 317.0,
      "high_low_ratio": 306.0,
      "bb_width": 293.0,
      "rsi_14": 272.0,
      "minute": 255.0,
      "ret_1": 249.0,
      "body_ratio": 245.0,
      "macd_signal": 232.0,
      "ret_3": 221.0,
      "rsi_9": 221.0,
      "ma_ratio_50": 219.0,
      "ma_ratio_10": 217.0,
      "ret_5": 215.0,
      "atr_ratio": 215.0,
      "macd_hist": 202.0,
      "ret_10": 196.0,
      "macd": 194.0,
      "time_in_session": 189.0
    },
    "name": "鹿島建設",
    "price": 5834.0,
    "avg_volume": 1718800
  },
  "2962.T": {
    "ticker": "2962.T",
    "bullish_prob": 0.2084,
    "bearish_prob": 0.7916,
    "prediction": "bearish",
    "confidence": 0.5831,
    "model_accuracy": 0.539297124600639,
    "model_trained_at": "2026-07-01T15:04:12.877928",
    "feature_importance": {
      "vwap_ratio": 330.0,
      "vol_ratio_20": 259.0,
      "vol_ratio_5": 248.0,
      "rsi_9": 247.0,
      "body_ratio": 241.0,
      "rsi_14": 236.0,
      "minute": 230.0,
      "bb_width": 226.0,
      "high_low_ratio": 224.0,
      "ret_3": 220.0,
      "time_in_session": 214.0,
      "macd_signal": 208.0,
      "ma_ratio_25": 204.0,
      "atr_ratio": 191.0,
      "macd_hist": 181.0,
      "ret_1": 179.0,
      "ret_5": 172.0,
      "bb_position": 171.0,
      "ma_ratio_5": 159.0,
      "ret_10": 149.0
    },
    "name": "テクニスコ",
    "price": 1849.0,
    "avg_volume": 1676100
  },
  "2702.T": {
    "ticker": "2702.T",
    "bullish_prob": 0.0532,
    "bearish_prob": 0.9468,
    "prediction": "bearish",
    "confidence": 0.8936,
    "model_accuracy": 0.7927272727272727,
    "model_trained_at": "2026-07-01T15:04:17.030783",
    "feature_importance": {
      "vol_ratio_20": 423.0,
      "atr_ratio": 349.0,
      "vol_ratio_5": 343.0,
      "vwap_ratio": 328.0,
      "macd_hist": 304.0,
      "time_in_session": 303.0,
      "minute": 293.0,
      "bb_width": 286.0,
      "ma_ratio_5": 252.0,
      "ma_ratio_10": 247.0,
      "macd_signal": 227.0,
      "ma_ratio_50": 211.0,
      "rsi_14": 207.0,
      "ret_3": 202.0,
      "ret_10": 199.0,
      "bb_position": 199.0,
      "rsi_9": 178.0,
      "ret_5": 174.0,
      "high_low_ratio": 166.0,
      "ma_ratio_25": 154.0
    },
    "name": "日本マクドナルドホールディングス",
    "price": 7456.0,
    "avg_volume": 1598940
  },
  "3088.T": {
    "ticker": "3088.T",
    "bullish_prob": 0.5346,
    "bearish_prob": 0.4654,
    "prediction": "bullish",
    "confidence": 0.0692,
    "model_accuracy": 0.5406162464985995,
    "model_trained_at": "2026-07-01T15:04:21.505604",
    "feature_importance": {
      "rsi_9": 301.0,
      "vol_ratio_20": 294.0,
      "vwap_ratio": 275.0,
      "ma_ratio_5": 268.0,
      "atr_ratio": 258.0,
      "vol_ratio_5": 254.0,
      "ret_3": 253.0,
      "rsi_14": 249.0,
      "bb_width": 239.0,
      "time_in_session": 236.0,
      "macd_signal": 231.0,
      "minute": 230.0,
      "ma_ratio_25": 229.0,
      "high_low_ratio": 228.0,
      "ret_5": 214.0,
      "ret_1": 203.0,
      "ret_10": 197.0,
      "ma_ratio_10": 197.0,
      "body_ratio": 191.0,
      "ma_ratio_50": 187.0
    },
    "name": "マツキヨココカラ＆カンパニー",
    "price": 2382.0,
    "avg_volume": 1571920
  },
  "1963.T": {
    "ticker": "1963.T",
    "bullish_prob": 0.2662,
    "bearish_prob": 0.7338,
    "prediction": "bearish",
    "confidence": 0.4676,
    "model_accuracy": 0.5202216066481995,
    "model_trained_at": "2026-07-01T15:04:25.908875",
    "feature_importance": {
      "vol_ratio_20": 343.0,
      "vol_ratio_5": 336.0,
      "vwap_ratio": 317.0,
      "atr_ratio": 291.0,
      "time_in_session": 284.0,
      "rsi_14": 273.0,
      "rsi_9": 254.0,
      "ret_5": 246.0,
      "bb_width": 237.0,
      "minute": 236.0,
      "ma_ratio_5": 231.0,
      "macd_hist": 231.0,
      "ret_3": 225.0,
      "body_ratio": 222.0,
      "ret_1": 212.0,
      "ma_ratio_50": 212.0,
      "ret_10": 206.0,
      "bb_position": 205.0,
      "ma_ratio_10": 195.0,
      "high_low_ratio": 191.0
    },
    "name": "日揮ホールディングス",
    "price": 2526.0,
    "avg_volume": 1503580
  },
  "2334.T": {
    "ticker": "2334.T",
    "bullish_prob": 0.127,
    "bearish_prob": 0.873,
    "prediction": "bearish",
    "confidence": 0.7461,
    "model_accuracy": 0.703448275862069,
    "model_trained_at": "2026-07-01T15:04:30.024872",
    "feature_importance": {
      "vol_ratio_5": 325.0,
      "ret_10": 277.0,
      "ret_3": 275.0,
      "atr_ratio": 264.0,
      "time_in_session": 264.0,
      "ret_5": 261.0,
      "bb_width": 261.0,
      "vol_ratio_20": 230.0,
      "macd_signal": 226.0,
      "minute": 222.0,
      "rsi_9": 208.0,
      "macd": 203.0,
      "rsi_14": 189.0,
      "ma_ratio_5": 188.0,
      "vwap_ratio": 188.0,
      "ma_ratio_10": 181.0,
      "macd_hist": 181.0,
      "ma_ratio_20": 179.0,
      "ma_ratio_50": 174.0,
      "ret_1": 173.0
    },
    "name": "イオレ",
    "price": 597.0,
    "avg_volume": 1480420
  },
  "3391.T": {
    "ticker": "3391.T",
    "bullish_prob": 0.5732,
    "bearish_prob": 0.4268,
    "prediction": "bullish",
    "confidence": 0.1464,
    "model_accuracy": 0.5294117647058825,
    "model_trained_at": "2026-07-01T15:04:34.303209",
    "feature_importance": {
      "vol_ratio_5": 342.0,
      "vwap_ratio": 328.0,
      "rsi_14": 290.0,
      "vol_ratio_20": 285.0,
      "atr_ratio": 274.0,
      "rsi_9": 272.0,
      "ret_1": 271.0,
      "ret_5": 265.0,
      "minute": 257.0,
      "high_low_ratio": 253.0,
      "ret_10": 238.0,
      "bb_width": 232.0,
      "ma_ratio_50": 230.0,
      "ma_ratio_5": 223.0,
      "time_in_session": 209.0,
      "macd": 202.0,
      "macd_hist": 193.0,
      "ret_3": 191.0,
      "macd_signal": 188.0,
      "bb_position": 167.0
    },
    "name": "ツルハホールディングス",
    "price": 2032.0,
    "avg_volume": 1477580
  },
  "3038.T": {
    "ticker": "3038.T",
    "bullish_prob": 0.4107,
    "bearish_prob": 0.5893,
    "prediction": "bearish",
    "confidence": 0.1787,
    "model_accuracy": 0.5162921348314606,
    "model_trained_at": "2026-07-01T15:04:38.611260",
    "feature_importance": {
      "vol_ratio_5": 362.0,
      "atr_ratio": 358.0,
      "vol_ratio_20": 295.0,
      "vwap_ratio": 283.0,
      "rsi_14": 282.0,
      "ma_ratio_5": 277.0,
      "minute": 276.0,
      "high_low_ratio": 255.0,
      "ret_5": 248.0,
      "macd_hist": 248.0,
      "rsi_9": 240.0,
      "time_in_session": 240.0,
      "bb_width": 235.0,
      "macd_signal": 234.0,
      "ret_3": 227.0,
      "ret_10": 224.0,
      "ma_ratio_10": 214.0,
      "ret_1": 209.0,
      "bb_position": 209.0,
      "ma_ratio_50": 181.0
    },
    "name": "神戸物産",
    "price": 2610.0,
    "avg_volume": 1389040
  },
  "1893.T": {
    "ticker": "1893.T",
    "bullish_prob": 0.4973,
    "bearish_prob": 0.5027,
    "prediction": "bearish",
    "confidence": 0.0054,
    "model_accuracy": 0.535933147632312,
    "model_trained_at": "2026-07-01T15:04:42.879325",
    "feature_importance": {
      "vwap_ratio": 368.0,
      "vol_ratio_20": 321.0,
      "bb_width": 298.0,
      "vol_ratio_5": 275.0,
      "ma_ratio_5": 248.0,
      "ret_10": 238.0,
      "ret_5": 232.0,
      "minute": 232.0,
      "time_in_session": 231.0,
      "atr_ratio": 226.0,
      "macd_hist": 225.0,
      "rsi_14": 215.0,
      "ma_ratio_10": 213.0,
      "rsi_9": 211.0,
      "high_low_ratio": 209.0,
      "macd_signal": 200.0,
      "ret_1": 198.0,
      "bb_position": 195.0,
      "body_ratio": 183.0,
      "ret_3": 162.0
    },
    "name": "五洋建設",
    "price": 1696.0,
    "avg_volume": 1382300
  },
  "1878.T": {
    "ticker": "1878.T",
    "bullish_prob": 0.0759,
    "bearish_prob": 0.9241,
    "prediction": "bearish",
    "confidence": 0.8481,
    "model_accuracy": 0.6834782608695653,
    "model_trained_at": "2026-07-01T15:04:47.096193",
    "feature_importance": {
      "vwap_ratio": 340.0,
      "vol_ratio_5": 314.0,
      "vol_ratio_20": 310.0,
      "time_in_session": 275.0,
      "atr_ratio": 273.0,
      "ret_10": 266.0,
      "rsi_14": 261.0,
      "ret_3": 251.0,
      "bb_width": 250.0,
      "ret_5": 235.0,
      "macd": 230.0,
      "minute": 227.0,
      "rsi_9": 220.0,
      "macd_hist": 217.0,
      "ma_ratio_5": 211.0,
      "high_low_ratio": 210.0,
      "bb_position": 208.0,
      "ma_ratio_10": 180.0,
      "ret_1": 179.0,
      "macd_signal": 171.0
    },
    "name": "大東建託",
    "price": 3055.0,
    "avg_volume": 1378000
  },
  "2501.T": {
    "ticker": "2501.T",
    "bullish_prob": 0.2036,
    "bearish_prob": 0.7964,
    "prediction": "bearish",
    "confidence": 0.5929,
    "model_accuracy": 0.5058495821727018,
    "model_trained_at": "2026-07-01T15:04:51.385896",
    "feature_importance": {
      "vol_ratio_5": 326.0,
      "ret_5": 323.0,
      "vol_ratio_20": 296.0,
      "vwap_ratio": 291.0,
      "bb_width": 269.0,
      "atr_ratio": 258.0,
      "ret_1": 257.0,
      "minute": 251.0,
      "rsi_14": 250.0,
      "ma_ratio_5": 242.0,
      "rsi_9": 235.0,
      "high_low_ratio": 224.0,
      "ret_3": 221.0,
      "macd_signal": 216.0,
      "time_in_session": 210.0,
      "ret_10": 208.0,
      "macd_hist": 204.0,
      "bb_position": 204.0,
      "body_ratio": 203.0,
      "ma_ratio_50": 202.0
    },
    "name": "サッポロホールディングス",
    "price": 2004.0,
    "avg_volume": 1326300
  },
  "1662.T": {
    "ticker": "1662.T",
    "bullish_prob": 0.0956,
    "bearish_prob": 0.9044,
    "prediction": "bearish",
    "confidence": 0.8088,
    "model_accuracy": 0.6581039755351682,
    "model_trained_at": "2026-07-01T15:04:55.498252",
    "feature_importance": {
      "vol_ratio_20": 340.0,
      "vwap_ratio": 314.0,
      "vol_ratio_5": 304.0,
      "bb_width": 303.0,
      "minute": 282.0,
      "atr_ratio": 276.0,
      "ret_5": 258.0,
      "ma_ratio_10": 242.0,
      "ma_ratio_5": 225.0,
      "high_low_ratio": 219.0,
      "ret_10": 216.0,
      "rsi_14": 196.0,
      "time_in_session": 195.0,
      "ret_1": 193.0,
      "macd_signal": 193.0,
      "rsi_9": 180.0,
      "macd": 176.0,
      "ma_ratio_50": 174.0,
      "bb_position": 170.0,
      "ret_3": 169.0
    },
    "name": "石油資源開発",
    "price": 1593.0,
    "avg_volume": 1283660
  },
  "2579.T": {
    "ticker": "2579.T",
    "bullish_prob": 0.1665,
    "bearish_prob": 0.8335,
    "prediction": "bearish",
    "confidence": 0.667,
    "model_accuracy": 0.5488636363636363,
    "model_trained_at": "2026-07-01T15:04:59.829508",
    "feature_importance": {
      "vwap_ratio": 312.0,
      "vol_ratio_20": 310.0,
      "bb_width": 305.0,
      "ret_1": 300.0,
      "minute": 300.0,
      "rsi_9": 299.0,
      "atr_ratio": 284.0,
      "high_low_ratio": 274.0,
      "ret_3": 268.0,
      "ma_ratio_5": 268.0,
      "macd_signal": 245.0,
      "vol_ratio_5": 240.0,
      "ret_5": 228.0,
      "ret_10": 220.0,
      "rsi_14": 214.0,
      "time_in_session": 203.0,
      "body_ratio": 200.0,
      "macd_hist": 200.0,
      "ma_ratio_10": 187.0,
      "bb_position": 167.0
    },
    "name": "コカ・コーラ　ボトラーズジャパンホールディングス",
    "price": 4294.0,
    "avg_volume": 1240600
  },
  "3105.T": {
    "ticker": "3105.T",
    "bullish_prob": 0.7768,
    "bearish_prob": 0.2232,
    "prediction": "bullish",
    "confidence": 0.5535,
    "model_accuracy": 0.4833333333333333,
    "model_trained_at": "2026-07-01T15:05:04.054755",
    "feature_importance": {
      "vol_ratio_5": 331.0,
      "vol_ratio_20": 274.0,
      "atr_ratio": 272.0,
      "ret_5": 271.0,
      "vwap_ratio": 264.0,
      "high_low_ratio": 263.0,
      "rsi_14": 251.0,
      "minute": 251.0,
      "ret_3": 239.0,
      "rsi_9": 237.0,
      "ret_1": 235.0,
      "ma_ratio_10": 234.0,
      "ma_ratio_5": 231.0,
      "body_ratio": 230.0,
      "ma_ratio_25": 230.0,
      "bb_width": 222.0,
      "macd_hist": 204.0,
      "macd_signal": 195.0,
      "time_in_session": 180.0,
      "bb_position": 167.0
    },
    "name": "日清紡ホールディングス",
    "price": 2450.0,
    "avg_volume": 1200000
  },
  "1655.T": {
    "ticker": "1655.T",
    "bullish_prob": 0.0572,
    "bearish_prob": 0.9428,
    "prediction": "bearish",
    "confidence": 0.8856,
    "model_accuracy": 0.7907590759075908,
    "model_trained_at": "2026-07-01T15:05:08.316194",
    "feature_importance": {
      "vol_ratio_5": 362.0,
      "vwap_ratio": 329.0,
      "vol_ratio_20": 326.0,
      "bb_width": 300.0,
      "ret_3": 294.0,
      "minute": 271.0,
      "time_in_session": 267.0,
      "atr_ratio": 242.0,
      "ret_5": 241.0,
      "ret_1": 235.0,
      "ma_ratio_5": 234.0,
      "rsi_14": 233.0,
      "ma_ratio_50": 222.0,
      "ma_ratio_10": 213.0,
      "macd": 201.0,
      "ma_ratio_25": 193.0,
      "rsi_9": 191.0,
      "macd_hist": 188.0,
      "macd_signal": 185.0,
      "high_low_ratio": 181.0
    },
    "name": "ｉシェアーズ　Ｓ＆Ｐ　５００　米国株　ＥＴＦ",
    "price": 867.0,
    "avg_volume": 1194388
  },
  "2871.T": {
    "ticker": "2871.T",
    "bullish_prob": 0.3563,
    "bearish_prob": 0.6437,
    "prediction": "bearish",
    "confidence": 0.2874,
    "model_accuracy": 0.5491525423728814,
    "model_trained_at": "2026-07-01T15:05:16.416502",
    "feature_importance": {
      "rsi_9": 308.0,
      "vol_ratio_5": 299.0,
      "bb_position": 285.0,
      "rsi_14": 278.0,
      "ret_5": 276.0,
      "high_low_ratio": 253.0,
      "vwap_ratio": 248.0,
      "macd_hist": 244.0,
      "vol_ratio_20": 240.0,
      "ret_3": 239.0,
      "ret_10": 236.0,
      "ma_ratio_10": 234.0,
      "minute": 233.0,
      "ret_1": 229.0,
      "time_in_session": 222.0,
      "atr_ratio": 216.0,
      "ma_ratio_5": 209.0,
      "bb_width": 208.0,
      "ma_ratio_25": 181.0,
      "macd": 166.0
    },
    "name": "ニチレイ",
    "price": 2159.0,
    "avg_volume": 1140020
  },
  "2317.T": {
    "ticker": "2317.T",
    "bullish_prob": 0.0067,
    "bearish_prob": 0.9933,
    "prediction": "bearish",
    "confidence": 0.9866,
    "model_accuracy": 0.9302083333333334,
    "model_trained_at": "2026-07-01T15:05:12.146482",
    "feature_importance": {
      "vol_ratio_5": 390.0,
      "vol_ratio_20": 384.0,
      "macd_hist": 314.0,
      "minute": 308.0,
      "macd_signal": 297.0,
      "time_in_session": 286.0,
      "bb_width": 248.0,
      "vwap_ratio": 226.0,
      "ma_ratio_5": 224.0,
      "bb_position": 220.0,
      "atr_ratio": 210.0,
      "ma_ratio_10": 198.0,
      "ma_ratio_20": 181.0,
      "ma_ratio_50": 151.0,
      "macd": 144.0,
      "ret_10": 143.0,
      "ma_ratio_25": 136.0,
      "rsi_9": 107.0,
      "rsi_14": 96.0,
      "ret_1": 86.0
    },
    "name": "システナ",
    "price": 393.0,
    "avg_volume": 1137700
  },
  "1332.T": {
    "ticker": "1332.T",
    "bullish_prob": 0.0966,
    "bearish_prob": 0.9034,
    "prediction": "bearish",
    "confidence": 0.8069,
    "model_accuracy": 0.6288184438040345,
    "model_trained_at": "2026-07-01T15:05:20.807548",
    "feature_importance": {
      "vol_ratio_5": 341.0,
      "vol_ratio_20": 325.0,
      "rsi_9": 308.0,
      "time_in_session": 294.0,
      "ret_1": 291.0,
      "atr_ratio": 279.0,
      "minute": 275.0,
      "ret_3": 266.0,
      "macd_hist": 259.0,
      "bb_width": 256.0,
      "vwap_ratio": 237.0,
      "ret_5": 232.0,
      "rsi_14": 229.0,
      "high_low_ratio": 218.0,
      "ma_ratio_5": 210.0,
      "bb_position": 201.0,
      "macd_signal": 200.0,
      "ma_ratio_50": 184.0,
      "ret_10": 182.0,
      "ma_ratio_10": 177.0
    },
    "name": "ニッスイ",
    "price": 1278.0,
    "avg_volume": 1134360
  },
  "2897.T": {
    "ticker": "2897.T",
    "bullish_prob": 0.5326,
    "bearish_prob": 0.4674,
    "prediction": "bullish",
    "confidence": 0.0651,
    "model_accuracy": 0.5477272727272727,
    "model_trained_at": "2026-07-01T15:05:25.051555",
    "feature_importance": {
      "vol_ratio_5": 329.0,
      "vol_ratio_20": 285.0,
      "macd_hist": 279.0,
      "atr_ratio": 279.0,
      "ret_1": 278.0,
      "bb_width": 270.0,
      "ma_ratio_5": 267.0,
      "ret_3": 249.0,
      "vwap_ratio": 243.0,
      "time_in_session": 233.0,
      "rsi_14": 225.0,
      "minute": 214.0,
      "ma_ratio_10": 211.0,
      "high_low_ratio": 209.0,
      "ret_5": 206.0,
      "ret_10": 200.0,
      "rsi_9": 199.0,
      "ma_ratio_50": 191.0,
      "ma_ratio_20": 178.0,
      "bb_position": 176.0
    },
    "name": "日清食品ホールディングス",
    "price": 2773.0,
    "avg_volume": 1107140
  },
  "2331.T": {
    "ticker": "2331.T",
    "bullish_prob": 0.1159,
    "bearish_prob": 0.8841,
    "prediction": "bearish",
    "confidence": 0.7683,
    "model_accuracy": 0.7218934911242604,
    "model_trained_at": "2026-07-01T15:05:29.260844",
    "feature_importance": {
      "vol_ratio_20": 401.0,
      "bb_width": 345.0,
      "vwap_ratio": 318.0,
      "vol_ratio_5": 316.0,
      "time_in_session": 290.0,
      "atr_ratio": 264.0,
      "minute": 260.0,
      "ret_5": 253.0,
      "macd_hist": 244.0,
      "ret_3": 237.0,
      "ma_ratio_5": 231.0,
      "rsi_14": 221.0,
      "ma_ratio_10": 216.0,
      "macd_signal": 200.0,
      "ma_ratio_50": 188.0,
      "ret_1": 174.0,
      "ma_ratio_25": 174.0,
      "bb_position": 172.0,
      "ret_10": 171.0,
      "rsi_9": 160.0
    },
    "name": "ＡＬＳＯＫ",
    "price": 1065.0,
    "avg_volume": 1099160
  },
  "1329.T": {
    "ticker": "1329.T",
    "bullish_prob": 0.2796,
    "bearish_prob": 0.7204,
    "prediction": "bearish",
    "confidence": 0.4409,
    "model_accuracy": 0.526111111111111,
    "model_trained_at": "2026-07-01T15:05:33.511994",
    "feature_importance": {
      "vol_ratio_20": 322.0,
      "rsi_9": 304.0,
      "high_low_ratio": 291.0,
      "vol_ratio_5": 285.0,
      "bb_width": 254.0,
      "vwap_ratio": 245.0,
      "macd_signal": 235.0,
      "ret_1": 233.0,
      "ret_5": 229.0,
      "atr_ratio": 223.0,
      "body_ratio": 222.0,
      "time_in_session": 205.0,
      "rsi_14": 201.0,
      "minute": 201.0,
      "ret_3": 188.0,
      "macd_hist": 187.0,
      "ma_ratio_5": 184.0,
      "ma_ratio_10": 177.0,
      "ret_10": 163.0,
      "bb_position": 154.0
    },
    "name": "ｉシェアーズ・コア　日経２２５　ＥＴＦ",
    "price": 7336.0,
    "avg_volume": 1066486
  },
  "2432.T": {
    "ticker": "2432.T",
    "bullish_prob": 0.282,
    "bearish_prob": 0.718,
    "prediction": "bearish",
    "confidence": 0.436,
    "model_accuracy": 0.5391304347826087,
    "model_trained_at": "2026-07-01T15:05:37.800112",
    "feature_importance": {
      "rsi_14": 301.0,
      "vol_ratio_5": 297.0,
      "vol_ratio_20": 280.0,
      "ret_3": 277.0,
      "atr_ratio": 276.0,
      "ret_5": 269.0,
      "high_low_ratio": 258.0,
      "macd_hist": 256.0,
      "ret_1": 255.0,
      "rsi_9": 254.0,
      "time_in_session": 250.0,
      "bb_width": 245.0,
      "vwap_ratio": 244.0,
      "ma_ratio_5": 234.0,
      "bb_position": 199.0,
      "ma_ratio_50": 198.0,
      "ma_ratio_25": 189.0,
      "ret_10": 188.0,
      "minute": 180.0,
      "ma_ratio_10": 171.0
    },
    "name": "ディー・エヌ・エー",
    "price": 2437.0,
    "avg_volume": 1041000
  },
  "1808.T": {
    "ticker": "1808.T",
    "bullish_prob": 0.2517,
    "bearish_prob": 0.7483,
    "prediction": "bearish",
    "confidence": 0.4965,
    "model_accuracy": 0.5427762039660056,
    "model_trained_at": "2026-07-01T15:05:42.028410",
    "feature_importance": {
      "vwap_ratio": 364.0,
      "time_in_session": 308.0,
      "rsi_9": 275.0,
      "vol_ratio_5": 272.0,
      "minute": 255.0,
      "vol_ratio_20": 250.0,
      "ret_1": 246.0,
      "rsi_14": 245.0,
      "atr_ratio": 245.0,
      "macd_hist": 237.0,
      "ret_5": 234.0,
      "ma_ratio_5": 225.0,
      "bb_width": 221.0,
      "ma_ratio_10": 219.0,
      "bb_position": 213.0,
      "high_low_ratio": 212.0,
      "ma_ratio_50": 187.0,
      "macd": 180.0,
      "ma_ratio_25": 178.0,
      "macd_signal": 177.0
    },
    "name": "長谷工コーポレーション",
    "price": 2813.0,
    "avg_volume": 1006040
  },
  "2768.T": {
    "ticker": "2768.T",
    "bullish_prob": 0.2904,
    "bearish_prob": 0.7096,
    "prediction": "bearish",
    "confidence": 0.4192,
    "model_accuracy": 0.5195530726256983,
    "model_trained_at": "2026-07-01T15:05:46.284099",
    "feature_importance": {
      "vol_ratio_5": 302.0,
      "vwap_ratio": 290.0,
      "ret_3": 270.0,
      "vol_ratio_20": 264.0,
      "ret_10": 262.0,
      "rsi_14": 255.0,
      "atr_ratio": 248.0,
      "minute": 243.0,
      "ma_ratio_5": 240.0,
      "ret_1": 239.0,
      "macd_hist": 239.0,
      "high_low_ratio": 217.0,
      "rsi_9": 207.0,
      "ret_5": 199.0,
      "time_in_session": 198.0,
      "bb_width": 185.0,
      "macd_signal": 181.0,
      "bb_position": 166.0,
      "ma_ratio_10": 163.0,
      "ma_ratio_50": 157.0
    },
    "name": "双日",
    "price": 5218.0,
    "avg_volume": 1002540
  },
  "1860.T": {
    "ticker": "1860.T",
    "bullish_prob": 0.8469,
    "bearish_prob": 0.1531,
    "prediction": "bullish",
    "confidence": 0.6938,
    "model_accuracy": 0.6035190615835777,
    "model_trained_at": "2026-07-01T15:05:50.625464",
    "feature_importance": {
      "vwap_ratio": 363.0,
      "vol_ratio_20": 293.0,
      "vol_ratio_5": 277.0,
      "rsi_14": 274.0,
      "ret_5": 272.0,
      "time_in_session": 267.0,
      "ret_10": 260.0,
      "ma_ratio_5": 256.0,
      "minute": 245.0,
      "bb_width": 240.0,
      "rsi_9": 236.0,
      "ret_3": 234.0,
      "high_low_ratio": 232.0,
      "macd_hist": 228.0,
      "macd_signal": 222.0,
      "ma_ratio_10": 220.0,
      "atr_ratio": 220.0,
      "ret_1": 217.0,
      "ma_ratio_25": 206.0,
      "ma_ratio_50": 188.0
    },
    "name": "戸田建設",
    "price": 1620.0,
    "avg_volume": 999580
  },
  "2587.T": {
    "ticker": "2587.T",
    "bullish_prob": 0.1374,
    "bearish_prob": 0.8626,
    "prediction": "bearish",
    "confidence": 0.7251,
    "model_accuracy": 0.5813411078717201,
    "model_trained_at": "2026-07-01T15:05:55.059859",
    "feature_importance": {
      "vol_ratio_5": 318.0,
      "vol_ratio_20": 271.0,
      "atr_ratio": 259.0,
      "ret_3": 245.0,
      "bb_width": 243.0,
      "ret_1": 241.0,
      "vwap_ratio": 232.0,
      "rsi_14": 228.0,
      "time_in_session": 221.0,
      "ret_5": 210.0,
      "macd_signal": 210.0,
      "ma_ratio_50": 205.0,
      "macd": 201.0,
      "ma_ratio_10": 199.0,
      "minute": 196.0,
      "ma_ratio_5": 194.0,
      "high_low_ratio": 189.0,
      "ma_ratio_25": 173.0,
      "ret_10": 172.0,
      "rsi_9": 171.0
    },
    "name": "サントリービバレッジ＆フード",
    "price": 4460.0,
    "avg_volume": 975880
  },
  "1343.T": {
    "ticker": "1343.T",
    "bullish_prob": 0.6153,
    "bearish_prob": 0.3847,
    "prediction": "bullish",
    "confidence": 0.2305,
    "model_accuracy": 0.7623376623376623,
    "model_trained_at": "2026-07-01T15:05:59.196537",
    "feature_importance": {
      "vol_ratio_5": 352.0,
      "vwap_ratio": 330.0,
      "atr_ratio": 320.0,
      "minute": 307.0,
      "ma_ratio_5": 293.0,
      "macd_hist": 283.0,
      "rsi_9": 250.0,
      "ret_1": 249.0,
      "rsi_14": 245.0,
      "vol_ratio_20": 240.0,
      "time_in_session": 240.0,
      "ret_10": 234.0,
      "ret_3": 232.0,
      "macd_signal": 231.0,
      "ret_5": 211.0,
      "bb_width": 199.0,
      "bb_position": 184.0,
      "ma_ratio_10": 180.0,
      "ma_ratio_25": 164.0,
      "macd": 157.0
    },
    "name": "ＮＥＸＴ　ＦＵＮＤＳ　東証ＲＥＩＴ　指数連動型上場投信",
    "price": 1952.0,
    "avg_volume": 972096
  },
  "2243.T": {
    "ticker": "2243.T",
    "bullish_prob": 0.4613,
    "bearish_prob": 0.5387,
    "prediction": "bearish",
    "confidence": 0.0775,
    "model_accuracy": 0.5561111111111112,
    "model_trained_at": "2026-07-01T15:06:03.455280",
    "feature_importance": {
      "rsi_9": 305.0,
      "high_low_ratio": 301.0,
      "atr_ratio": 276.0,
      "vol_ratio_5": 270.0,
      "bb_width": 267.0,
      "vwap_ratio": 266.0,
      "ret_3": 257.0,
      "rsi_14": 257.0,
      "ret_5": 250.0,
      "vol_ratio_20": 247.0,
      "ret_1": 235.0,
      "bb_position": 227.0,
      "macd_hist": 221.0,
      "body_ratio": 220.0,
      "ret_10": 219.0,
      "ma_ratio_5": 216.0,
      "macd_signal": 201.0,
      "minute": 189.0,
      "ma_ratio_50": 165.0,
      "time_in_session": 165.0
    },
    "name": "グローバルＸ　半導体　ＥＴＦ",
    "price": 5301.0,
    "avg_volume": 966859
  },
  "2170.T": {
    "ticker": "2170.T",
    "bullish_prob": 0.0082,
    "bearish_prob": 0.9918,
    "prediction": "bearish",
    "confidence": 0.9835,
    "model_accuracy": 0.8708571428571428,
    "model_trained_at": "2026-07-01T15:06:07.305163",
    "feature_importance": {
      "vol_ratio_20": 333.0,
      "minute": 312.0,
      "time_in_session": 286.0,
      "vol_ratio_5": 276.0,
      "bb_width": 272.0,
      "macd_hist": 245.0,
      "vwap_ratio": 220.0,
      "ma_ratio_5": 218.0,
      "rsi_14": 215.0,
      "macd_signal": 211.0,
      "ret_5": 210.0,
      "atr_ratio": 207.0,
      "ma_ratio_50": 194.0,
      "ma_ratio_20": 167.0,
      "ma_ratio_25": 160.0,
      "ret_3": 159.0,
      "macd": 157.0,
      "ma_ratio_10": 148.0,
      "bb_position": 141.0,
      "ret_10": 136.0
    },
    "name": "リンクアンドモチベーション",
    "price": 536.0,
    "avg_volume": 921140
  },
  "2269.T": {
    "ticker": "2269.T",
    "bullish_prob": 0.3812,
    "bearish_prob": 0.6188,
    "prediction": "bearish",
    "confidence": 0.2376,
    "model_accuracy": 0.6034383954154728,
    "model_trained_at": "2026-07-01T15:06:11.480119",
    "feature_importance": {
      "ret_3": 316.0,
      "minute": 316.0,
      "vol_ratio_5": 290.0,
      "vol_ratio_20": 278.0,
      "ret_1": 273.0,
      "vwap_ratio": 272.0,
      "ret_5": 271.0,
      "rsi_9": 255.0,
      "bb_width": 245.0,
      "ret_10": 243.0,
      "rsi_14": 243.0,
      "high_low_ratio": 217.0,
      "time_in_session": 205.0,
      "macd_hist": 204.0,
      "atr_ratio": 201.0,
      "bb_position": 200.0,
      "ma_ratio_5": 194.0,
      "ma_ratio_25": 171.0,
      "ma_ratio_10": 169.0,
      "ma_ratio_50": 165.0
    },
    "name": "明治ホールディングス",
    "price": 3788.0,
    "avg_volume": 895900
  },
  "2160.T": {
    "ticker": "2160.T",
    "bullish_prob": 0.1351,
    "bearish_prob": 0.8649,
    "prediction": "bearish",
    "confidence": 0.7298,
    "model_accuracy": 0.5696428571428572,
    "model_trained_at": "2026-07-01T15:06:15.881120",
    "feature_importance": {
      "vol_ratio_20": 309.0,
      "vwap_ratio": 307.0,
      "bb_width": 298.0,
      "vol_ratio_5": 278.0,
      "ret_10": 273.0,
      "rsi_14": 260.0,
      "rsi_9": 253.0,
      "ret_3": 251.0,
      "ret_5": 249.0,
      "macd_signal": 249.0,
      "macd_hist": 249.0,
      "ma_ratio_5": 239.0,
      "atr_ratio": 238.0,
      "minute": 238.0,
      "ret_1": 225.0,
      "ma_ratio_10": 218.0,
      "high_low_ratio": 209.0,
      "time_in_session": 204.0,
      "bb_position": 202.0,
      "ma_ratio_25": 195.0
    },
    "name": "ジーエヌアイグループ",
    "price": 2704.0,
    "avg_volume": 864840
  },
  "1580.T": {
    "ticker": "1580.T",
    "bullish_prob": 0.0966,
    "bearish_prob": 0.9034,
    "prediction": "bearish",
    "confidence": 0.8068,
    "model_accuracy": 0.7555555555555555,
    "model_trained_at": "2026-07-01T15:06:19.906004",
    "feature_importance": {
      "rsi_9": 313.0,
      "vwap_ratio": 276.0,
      "ret_1": 274.0,
      "ma_ratio_5": 273.0,
      "vol_ratio_20": 261.0,
      "ret_3": 237.0,
      "ret_5": 231.0,
      "vol_ratio_5": 225.0,
      "macd_signal": 206.0,
      "atr_ratio": 204.0,
      "ret_10": 197.0,
      "rsi_14": 194.0,
      "minute": 194.0,
      "bb_width": 193.0,
      "time_in_session": 180.0,
      "ma_ratio_25": 176.0,
      "bb_position": 169.0,
      "macd_hist": 166.0,
      "ma_ratio_50": 161.0,
      "ma_ratio_10": 159.0
    },
    "name": "日経平均ベア上場投信",
    "price": 748.0,
    "avg_volume": 849902
  },
  "2931.T": {
    "ticker": "2931.T",
    "bullish_prob": 0.0294,
    "bearish_prob": 0.9706,
    "prediction": "bearish",
    "confidence": 0.9413,
    "model_accuracy": 0.8858585858585858,
    "model_trained_at": "2026-07-01T15:06:23.726282",
    "feature_importance": {
      "time_in_session": 313.0,
      "ma_ratio_10": 305.0,
      "vol_ratio_20": 300.0,
      "minute": 291.0,
      "vol_ratio_5": 290.0,
      "atr_ratio": 264.0,
      "macd_hist": 243.0,
      "bb_width": 234.0,
      "vwap_ratio": 233.0,
      "ma_ratio_5": 204.0,
      "ma_ratio_50": 197.0,
      "ret_5": 193.0,
      "bb_position": 192.0,
      "macd_signal": 188.0,
      "rsi_14": 168.0,
      "rsi_9": 148.0,
      "ret_10": 144.0,
      "ma_ratio_25": 144.0,
      "ma_ratio_20": 125.0,
      "macd": 107.0
    },
    "name": "ユーグレナ",
    "price": 326.0,
    "avg_volume": 834540
  },
  "2371.T": {
    "ticker": "2371.T",
    "bullish_prob": 0.1277,
    "bearish_prob": 0.8723,
    "prediction": "bearish",
    "confidence": 0.7447,
    "model_accuracy": 0.713375796178344,
    "model_trained_at": "2026-07-01T15:06:28.019386",
    "feature_importance": {
      "minute": 336.0,
      "time_in_session": 328.0,
      "vol_ratio_5": 320.0,
      "vol_ratio_20": 313.0,
      "bb_position": 279.0,
      "ret_3": 277.0,
      "ma_ratio_5": 277.0,
      "bb_width": 271.0,
      "vwap_ratio": 263.0,
      "ret_1": 241.0,
      "atr_ratio": 238.0,
      "ret_5": 232.0,
      "rsi_14": 231.0,
      "ma_ratio_10": 227.0,
      "ma_ratio_50": 227.0,
      "rsi_9": 216.0,
      "macd_hist": 211.0,
      "macd_signal": 207.0,
      "high_low_ratio": 207.0,
      "ma_ratio_25": 201.0
    },
    "name": "カカクコム",
    "price": 3353.0,
    "avg_volume": 813120
  },
  "2337.T": {
    "ticker": "2337.T",
    "bullish_prob": 0.0326,
    "bearish_prob": 0.9674,
    "prediction": "bearish",
    "confidence": 0.9348,
    "model_accuracy": 0.9315315315315316,
    "model_trained_at": "2026-07-01T15:06:36.187592",
    "feature_importance": {
      "vol_ratio_5": 378.0,
      "vol_ratio_20": 321.0,
      "macd_hist": 310.0,
      "atr_ratio": 287.0,
      "time_in_session": 277.0,
      "bb_width": 252.0,
      "minute": 234.0,
      "macd_signal": 213.0,
      "vwap_ratio": 204.0,
      "macd": 204.0,
      "ma_ratio_10": 193.0,
      "ma_ratio_5": 188.0,
      "bb_position": 172.0,
      "ma_ratio_25": 169.0,
      "ma_ratio_20": 155.0,
      "ma_ratio_50": 134.0,
      "ret_10": 113.0,
      "ret_5": 110.0,
      "rsi_9": 108.0,
      "rsi_14": 99.0
    },
    "name": "いちご",
    "price": 435.0,
    "avg_volume": 810020
  },
  "1414.T": {
    "ticker": "1414.T",
    "bullish_prob": 0.2898,
    "bearish_prob": 0.7102,
    "prediction": "bearish",
    "confidence": 0.4205,
    "model_accuracy": 0.77015873015873,
    "model_trained_at": "2026-07-01T15:06:32.219988",
    "feature_importance": {
      "vol_ratio_5": 439.0,
      "vol_ratio_20": 321.0,
      "time_in_session": 318.0,
      "bb_width": 311.0,
      "atr_ratio": 302.0,
      "minute": 296.0,
      "ma_ratio_5": 282.0,
      "vwap_ratio": 263.0,
      "ma_ratio_10": 251.0,
      "rsi_14": 237.0,
      "ret_3": 232.0,
      "ma_ratio_50": 225.0,
      "bb_position": 219.0,
      "ret_10": 211.0,
      "macd_signal": 211.0,
      "ma_ratio_20": 207.0,
      "ret_5": 205.0,
      "macd_hist": 205.0,
      "macd": 198.0,
      "ret_1": 178.0
    },
    "name": "ショーボンドホールディングス",
    "price": 1239.0,
    "avg_volume": 809580
  },
  "2002.T": {
    "ticker": "2002.T",
    "bullish_prob": 0.6504,
    "bearish_prob": 0.3496,
    "prediction": "bullish",
    "confidence": 0.3008,
    "model_accuracy": 0.6134897360703813,
    "model_trained_at": "2026-07-01T15:06:40.409091",
    "feature_importance": {
      "vol_ratio_5": 383.0,
      "atr_ratio": 321.0,
      "rsi_9": 301.0,
      "vwap_ratio": 285.0,
      "ma_ratio_5": 284.0,
      "rsi_14": 281.0,
      "minute": 271.0,
      "vol_ratio_20": 270.0,
      "high_low_ratio": 256.0,
      "ret_10": 254.0,
      "ret_5": 238.0,
      "ret_3": 230.0,
      "ma_ratio_10": 219.0,
      "time_in_session": 219.0,
      "bb_width": 204.0,
      "macd_signal": 198.0,
      "macd_hist": 197.0,
      "ret_1": 178.0,
      "bb_position": 164.0,
      "ma_ratio_25": 161.0
    },
    "name": "日清製粉グループ本社",
    "price": 1980.0,
    "avg_volume": 799160
  },
  "2267.T": {
    "ticker": "2267.T",
    "bullish_prob": 0.4003,
    "bearish_prob": 0.5997,
    "prediction": "bearish",
    "confidence": 0.1994,
    "model_accuracy": 0.5804597701149425,
    "model_trained_at": "2026-07-01T15:06:44.682914",
    "feature_importance": {
      "vol_ratio_20": 360.0,
      "ret_1": 332.0,
      "vol_ratio_5": 310.0,
      "vwap_ratio": 293.0,
      "ret_3": 291.0,
      "rsi_14": 269.0,
      "atr_ratio": 262.0,
      "rsi_9": 253.0,
      "minute": 237.0,
      "time_in_session": 236.0,
      "ret_10": 234.0,
      "ret_5": 230.0,
      "high_low_ratio": 229.0,
      "macd_signal": 222.0,
      "bb_width": 219.0,
      "macd": 203.0,
      "ma_ratio_5": 201.0,
      "bb_position": 201.0,
      "ma_ratio_10": 198.0,
      "ma_ratio_25": 181.0
    },
    "name": "ヤクルト本社",
    "price": 2739.0,
    "avg_volume": 752340
  },
  "2726.T": {
    "ticker": "2726.T",
    "bullish_prob": 0.1471,
    "bearish_prob": 0.8529,
    "prediction": "bearish",
    "confidence": 0.7059,
    "model_accuracy": 0.68625,
    "model_trained_at": "2026-07-01T15:06:48.848292",
    "feature_importance": {
      "vol_ratio_5": 359.0,
      "time_in_session": 298.0,
      "vol_ratio_20": 296.0,
      "vwap_ratio": 292.0,
      "ma_ratio_5": 285.0,
      "atr_ratio": 278.0,
      "ret_5": 268.0,
      "high_low_ratio": 259.0,
      "minute": 254.0,
      "ret_1": 249.0,
      "rsi_14": 245.0,
      "bb_position": 224.0,
      "bb_width": 219.0,
      "rsi_9": 215.0,
      "ret_10": 214.0,
      "macd_hist": 205.0,
      "ret_3": 204.0,
      "ma_ratio_50": 177.0,
      "ma_ratio_25": 174.0,
      "macd_signal": 170.0
    },
    "name": "パルグループホールディングス",
    "price": 1464.0,
    "avg_volume": 747840
  },
  "1942.T": {
    "ticker": "1942.T",
    "bullish_prob": 0.472,
    "bearish_prob": 0.528,
    "prediction": "bearish",
    "confidence": 0.0561,
    "model_accuracy": 0.5439775910364146,
    "model_trained_at": "2026-07-01T15:06:53.213285",
    "feature_importance": {
      "vol_ratio_5": 296.0,
      "atr_ratio": 293.0,
      "high_low_ratio": 291.0,
      "time_in_session": 278.0,
      "minute": 275.0,
      "bb_width": 272.0,
      "vol_ratio_20": 269.0,
      "vwap_ratio": 266.0,
      "ma_ratio_5": 258.0,
      "body_ratio": 237.0,
      "ret_1": 225.0,
      "ret_5": 223.0,
      "ret_3": 220.0,
      "rsi_9": 215.0,
      "rsi_14": 212.0,
      "ma_ratio_10": 209.0,
      "ret_10": 207.0,
      "macd_signal": 206.0,
      "ma_ratio_50": 204.0,
      "macd_hist": 204.0
    },
    "name": "関電工",
    "price": 6739.0,
    "avg_volume": 710480
  },
  "1801.T": {
    "ticker": "1801.T",
    "bullish_prob": 0.2901,
    "bearish_prob": 0.7099,
    "prediction": "bearish",
    "confidence": 0.4199,
    "model_accuracy": 0.5909348441926345,
    "model_trained_at": "2026-07-01T15:06:57.554708",
    "feature_importance": {
      "bb_width": 303.0,
      "vol_ratio_20": 303.0,
      "vol_ratio_5": 273.0,
      "time_in_session": 273.0,
      "vwap_ratio": 272.0,
      "rsi_9": 271.0,
      "high_low_ratio": 258.0,
      "atr_ratio": 257.0,
      "macd_hist": 255.0,
      "ret_10": 252.0,
      "ret_3": 251.0,
      "ma_ratio_10": 247.0,
      "ret_5": 240.0,
      "ma_ratio_5": 240.0,
      "rsi_14": 226.0,
      "macd_signal": 217.0,
      "ret_1": 215.0,
      "bb_position": 214.0,
      "body_ratio": 204.0,
      "minute": 201.0
    },
    "name": "大成建設",
    "price": 14158.0,
    "avg_volume": 706860
  },
  "2433.T": {
    "ticker": "2433.T",
    "bullish_prob": 0.4114,
    "bearish_prob": 0.5886,
    "prediction": "bearish",
    "confidence": 0.1771,
    "model_accuracy": 0.7041269841269842,
    "model_trained_at": "2026-07-01T15:07:01.861313",
    "feature_importance": {
      "vwap_ratio": 332.0,
      "vol_ratio_20": 329.0,
      "vol_ratio_5": 300.0,
      "atr_ratio": 276.0,
      "macd_hist": 272.0,
      "ret_10": 248.0,
      "minute": 244.0,
      "ma_ratio_5": 241.0,
      "ret_3": 238.0,
      "bb_width": 229.0,
      "rsi_14": 226.0,
      "ret_1": 223.0,
      "macd_signal": 217.0,
      "time_in_session": 215.0,
      "rsi_9": 210.0,
      "ret_5": 207.0,
      "high_low_ratio": 197.0,
      "bb_position": 182.0,
      "macd": 176.0,
      "ma_ratio_10": 170.0
    },
    "name": "博報堂ＤＹホールディングス",
    "price": 1127.0,
    "avg_volume": 696760
  },
  "1861.T": {
    "ticker": "1861.T",
    "bullish_prob": 0.0655,
    "bearish_prob": 0.9345,
    "prediction": "bearish",
    "confidence": 0.8689,
    "model_accuracy": 0.7498412698412699,
    "model_trained_at": "2026-07-01T15:07:06.154515",
    "feature_importance": {
      "vol_ratio_5": 377.0,
      "vol_ratio_20": 370.0,
      "time_in_session": 324.0,
      "ma_ratio_10": 300.0,
      "atr_ratio": 292.0,
      "ret_5": 291.0,
      "macd_hist": 279.0,
      "bb_position": 264.0,
      "rsi_14": 260.0,
      "minute": 259.0,
      "ma_ratio_5": 253.0,
      "bb_width": 245.0,
      "vwap_ratio": 244.0,
      "ret_10": 243.0,
      "ret_3": 228.0,
      "ret_1": 225.0,
      "macd_signal": 181.0,
      "ma_ratio_50": 174.0,
      "rsi_9": 163.0,
      "macd": 153.0
    },
    "name": "熊谷組",
    "price": 1409.0,
    "avg_volume": 683560
  },
  "3401.T": {
    "ticker": "3401.T",
    "bullish_prob": 0.0687,
    "bearish_prob": 0.9313,
    "prediction": "bearish",
    "confidence": 0.8627,
    "model_accuracy": 0.6053731343283582,
    "model_trained_at": "2026-07-01T15:07:10.474946",
    "feature_importance": {
      "vol_ratio_5": 305.0,
      "ret_3": 291.0,
      "atr_ratio": 284.0,
      "bb_width": 273.0,
      "vwap_ratio": 272.0,
      "macd_hist": 267.0,
      "vol_ratio_20": 264.0,
      "rsi_14": 263.0,
      "ma_ratio_5": 259.0,
      "ret_1": 242.0,
      "ret_10": 236.0,
      "time_in_session": 235.0,
      "minute": 234.0,
      "ret_5": 228.0,
      "rsi_9": 228.0,
      "high_low_ratio": 204.0,
      "ma_ratio_50": 182.0,
      "ma_ratio_10": 178.0,
      "bb_position": 163.0,
      "macd_signal": 154.0
    },
    "name": "帝人",
    "price": 1631.0,
    "avg_volume": 660940
  },
  "3116.T": {
    "ticker": "3116.T",
    "bullish_prob": 0.157,
    "bearish_prob": 0.843,
    "prediction": "bearish",
    "confidence": 0.6861,
    "model_accuracy": 0.6169096209912536,
    "model_trained_at": "2026-07-01T15:07:14.711060",
    "feature_importance": {
      "vwap_ratio": 360.0,
      "vol_ratio_5": 347.0,
      "vol_ratio_20": 324.0,
      "bb_width": 322.0,
      "ma_ratio_10": 301.0,
      "ret_3": 295.0,
      "macd_hist": 295.0,
      "minute": 281.0,
      "ma_ratio_5": 256.0,
      "ret_5": 249.0,
      "ret_1": 245.0,
      "atr_ratio": 244.0,
      "rsi_14": 241.0,
      "high_low_ratio": 240.0,
      "rsi_9": 236.0,
      "time_in_session": 223.0,
      "ma_ratio_50": 211.0,
      "macd_signal": 202.0,
      "body_ratio": 195.0,
      "ma_ratio_25": 194.0
    },
    "name": "トヨタ紡織",
    "price": 2142.0,
    "avg_volume": 657460
  },
  "2585.T": {
    "ticker": "2585.T",
    "bullish_prob": 0.4825,
    "bearish_prob": 0.5175,
    "prediction": "bearish",
    "confidence": 0.035,
    "model_accuracy": 0.6209523809523809,
    "model_trained_at": "2026-07-01T15:07:18.962365",
    "feature_importance": {
      "vol_ratio_20": 350.0,
      "minute": 343.0,
      "vol_ratio_5": 338.0,
      "vwap_ratio": 310.0,
      "macd_hist": 291.0,
      "atr_ratio": 281.0,
      "time_in_session": 281.0,
      "rsi_9": 274.0,
      "ret_10": 270.0,
      "high_low_ratio": 269.0,
      "ret_5": 259.0,
      "ret_1": 258.0,
      "ma_ratio_5": 246.0,
      "bb_width": 237.0,
      "bb_position": 233.0,
      "rsi_14": 226.0,
      "ma_ratio_50": 207.0,
      "ma_ratio_10": 198.0,
      "ret_3": 187.0,
      "macd_signal": 172.0
    },
    "name": "ライフドリンク　カンパニー",
    "price": 1601.0,
    "avg_volume": 648620
  },
  "1951.T": {
    "ticker": "1951.T",
    "bullish_prob": 0.741,
    "bearish_prob": 0.259,
    "prediction": "bullish",
    "confidence": 0.4821,
    "model_accuracy": 0.5674285714285714,
    "model_trained_at": "2026-07-01T15:07:23.400356",
    "feature_importance": {
      "vol_ratio_5": 333.0,
      "ret_1": 329.0,
      "vol_ratio_20": 329.0,
      "vwap_ratio": 307.0,
      "ret_3": 301.0,
      "bb_position": 296.0,
      "atr_ratio": 272.0,
      "high_low_ratio": 270.0,
      "rsi_9": 257.0,
      "ma_ratio_5": 256.0,
      "ret_10": 253.0,
      "bb_width": 253.0,
      "ret_5": 245.0,
      "rsi_14": 242.0,
      "minute": 236.0,
      "time_in_session": 236.0,
      "ma_ratio_50": 230.0,
      "macd_signal": 225.0,
      "ma_ratio_10": 197.0,
      "macd_hist": 193.0
    },
    "name": "エクシオグループ",
    "price": 2747.0,
    "avg_volume": 638880
  },
  "3101.T": {
    "ticker": "3101.T",
    "bullish_prob": 0.05,
    "bearish_prob": 0.95,
    "prediction": "bearish",
    "confidence": 0.8999,
    "model_accuracy": 0.7141065830721003,
    "model_trained_at": "2026-07-01T15:07:27.686360",
    "feature_importance": {
      "atr_ratio": 360.0,
      "vol_ratio_5": 334.0,
      "vwap_ratio": 283.0,
      "ret_1": 267.0,
      "minute": 267.0,
      "macd_hist": 261.0,
      "rsi_14": 247.0,
      "high_low_ratio": 240.0,
      "ma_ratio_5": 238.0,
      "time_in_session": 237.0,
      "rsi_9": 231.0,
      "ret_3": 228.0,
      "vol_ratio_20": 213.0,
      "ma_ratio_50": 207.0,
      "bb_width": 205.0,
      "ret_5": 201.0,
      "bb_position": 186.0,
      "ma_ratio_25": 183.0,
      "ret_10": 167.0,
      "ma_ratio_10": 155.0
    },
    "name": "東洋紡",
    "price": 1645.0,
    "avg_volume": 606460
  },
  "1852.T": {
    "ticker": "1852.T",
    "bullish_prob": 0.005,
    "bearish_prob": 0.995,
    "prediction": "bearish",
    "confidence": 0.9901,
    "model_accuracy": 0.8396551724137931,
    "model_trained_at": "2026-07-01T15:07:31.701663",
    "feature_importance": {
      "time_in_session": 377.0,
      "vol_ratio_5": 354.0,
      "vol_ratio_20": 335.0,
      "minute": 291.0,
      "atr_ratio": 282.0,
      "bb_width": 266.0,
      "macd_hist": 237.0,
      "ma_ratio_5": 234.0,
      "ret_10": 232.0,
      "vwap_ratio": 229.0,
      "macd": 225.0,
      "ma_ratio_10": 218.0,
      "macd_signal": 200.0,
      "bb_position": 189.0,
      "rsi_14": 188.0,
      "ma_ratio_20": 184.0,
      "ma_ratio_25": 178.0,
      "ret_5": 162.0,
      "ret_3": 154.0,
      "ma_ratio_50": 152.0
    },
    "name": "淺沼組",
    "price": 835.0,
    "avg_volume": 604340
  },
  "2670.T": {
    "ticker": "2670.T",
    "bullish_prob": 0.5047,
    "bearish_prob": 0.4953,
    "prediction": "bullish",
    "confidence": 0.0095,
    "model_accuracy": 0.5389048991354467,
    "model_trained_at": "2026-07-01T15:07:36.027356",
    "feature_importance": {
      "vwap_ratio": 325.0,
      "vol_ratio_20": 304.0,
      "atr_ratio": 303.0,
      "ret_3": 267.0,
      "high_low_ratio": 267.0,
      "rsi_9": 265.0,
      "bb_width": 259.0,
      "ret_10": 256.0,
      "macd_hist": 256.0,
      "vol_ratio_5": 249.0,
      "ret_1": 241.0,
      "ret_5": 240.0,
      "rsi_14": 238.0,
      "minute": 237.0,
      "ma_ratio_5": 224.0,
      "ma_ratio_10": 202.0,
      "bb_position": 189.0,
      "body_ratio": 180.0,
      "ma_ratio_25": 180.0,
      "time_in_session": 173.0
    },
    "name": "エービーシー・マート",
    "price": 2802.0,
    "avg_volume": 604000
  },
  "1969.T": {
    "ticker": "1969.T",
    "bullish_prob": 0.4576,
    "bearish_prob": 0.5424,
    "prediction": "bearish",
    "confidence": 0.0847,
    "model_accuracy": 0.5658119658119658,
    "model_trained_at": "2026-07-01T15:07:40.260243",
    "feature_importance": {
      "vol_ratio_20": 341.0,
      "vwap_ratio": 336.0,
      "rsi_14": 311.0,
      "ret_1": 306.0,
      "ret_3": 284.0,
      "body_ratio": 259.0,
      "minute": 249.0,
      "rsi_9": 244.0,
      "atr_ratio": 234.0,
      "vol_ratio_5": 231.0,
      "ret_5": 217.0,
      "ma_ratio_50": 216.0,
      "time_in_session": 210.0,
      "macd": 200.0,
      "bb_width": 200.0,
      "high_low_ratio": 194.0,
      "ret_10": 190.0,
      "macd_hist": 182.0,
      "ma_ratio_5": 178.0,
      "bb_position": 165.0
    },
    "name": "高砂熱学工業",
    "price": 5077.0,
    "avg_volume": 576680
  },
  "1719.T": {
    "ticker": "1719.T",
    "bullish_prob": 0.2424,
    "bearish_prob": 0.7576,
    "prediction": "bearish",
    "confidence": 0.5153,
    "model_accuracy": 0.639067055393586,
    "model_trained_at": "2026-07-01T15:07:44.443645",
    "feature_importance": {
      "vol_ratio_5": 403.0,
      "vol_ratio_20": 341.0,
      "atr_ratio": 291.0,
      "vwap_ratio": 276.0,
      "bb_width": 251.0,
      "ret_5": 242.0,
      "bb_position": 235.0,
      "ma_ratio_5": 234.0,
      "macd_hist": 229.0,
      "minute": 229.0,
      "ret_3": 225.0,
      "macd_signal": 218.0,
      "ret_10": 217.0,
      "time_in_session": 211.0,
      "rsi_14": 209.0,
      "ma_ratio_10": 200.0,
      "rsi_9": 200.0,
      "high_low_ratio": 190.0,
      "ma_ratio_25": 182.0,
      "ret_1": 181.0
    },
    "name": "安藤・間",
    "price": 1769.0,
    "avg_volume": 566260
  },
  "2222.T": {
    "ticker": "2222.T",
    "bullish_prob": 0.6285,
    "bearish_prob": 0.3715,
    "prediction": "bullish",
    "confidence": 0.2571,
    "model_accuracy": 0.618808777429467,
    "model_trained_at": "2026-07-01T15:07:48.672092",
    "feature_importance": {
      "vol_ratio_20": 320.0,
      "vwap_ratio": 311.0,
      "vol_ratio_5": 296.0,
      "ret_10": 270.0,
      "atr_ratio": 257.0,
      "time_in_session": 235.0,
      "ret_1": 233.0,
      "ret_3": 229.0,
      "bb_width": 222.0,
      "macd_hist": 221.0,
      "rsi_14": 220.0,
      "ret_5": 210.0,
      "ma_ratio_10": 189.0,
      "rsi_9": 187.0,
      "body_ratio": 175.0,
      "macd_signal": 173.0,
      "bb_position": 171.0,
      "high_low_ratio": 171.0,
      "ma_ratio_5": 166.0,
      "minute": 159.0
    },
    "name": "寿スピリッツ",
    "price": 2459.0,
    "avg_volume": 565300
  },
  "1333.T": {
    "ticker": "1333.T",
    "bullish_prob": 0.0522,
    "bearish_prob": 0.9478,
    "prediction": "bearish",
    "confidence": 0.8957,
    "model_accuracy": 0.6532915360501568,
    "model_trained_at": "2026-07-01T15:07:52.854773",
    "feature_importance": {
      "vol_ratio_20": 347.0,
      "vol_ratio_5": 309.0,
      "vwap_ratio": 281.0,
      "rsi_14": 275.0,
      "ret_5": 264.0,
      "minute": 251.0,
      "ret_3": 250.0,
      "ma_ratio_10": 249.0,
      "atr_ratio": 247.0,
      "time_in_session": 235.0,
      "ret_1": 234.0,
      "bb_width": 231.0,
      "macd_signal": 218.0,
      "ma_ratio_5": 212.0,
      "ret_10": 203.0,
      "macd_hist": 199.0,
      "rsi_9": 195.0,
      "high_low_ratio": 184.0,
      "ma_ratio_25": 168.0,
      "bb_position": 168.0
    },
    "name": "Ｕｍｉｏｓ",
    "price": 1298.0,
    "avg_volume": 562320
  },
  "1944.T": {
    "ticker": "1944.T",
    "bullish_prob": 0.729,
    "bearish_prob": 0.271,
    "prediction": "bullish",
    "confidence": 0.458,
    "model_accuracy": 0.5188571428571429,
    "model_trained_at": "2026-07-01T15:07:57.089926",
    "feature_importance": {
      "vol_ratio_20": 339.0,
      "vwap_ratio": 297.0,
      "atr_ratio": 285.0,
      "body_ratio": 269.0,
      "vol_ratio_5": 266.0,
      "bb_width": 261.0,
      "ret_1": 259.0,
      "ma_ratio_5": 237.0,
      "rsi_9": 237.0,
      "ret_3": 227.0,
      "time_in_session": 226.0,
      "ret_10": 224.0,
      "ret_5": 223.0,
      "macd_signal": 222.0,
      "macd_hist": 222.0,
      "ma_ratio_10": 211.0,
      "rsi_14": 211.0,
      "minute": 195.0,
      "bb_position": 194.0,
      "high_low_ratio": 187.0
    },
    "name": "きんでん",
    "price": 8020.0,
    "avg_volume": 559500
  },
  "3132.T": {
    "ticker": "3132.T",
    "bullish_prob": 0.1445,
    "bearish_prob": 0.8555,
    "prediction": "bearish",
    "confidence": 0.711,
    "model_accuracy": 0.5994318181818181,
    "model_trained_at": "2026-07-01T15:08:01.509145",
    "feature_importance": {
      "vol_ratio_20": 328.0,
      "vwap_ratio": 309.0,
      "minute": 307.0,
      "ma_ratio_5": 296.0,
      "ret_1": 285.0,
      "bb_width": 278.0,
      "vol_ratio_5": 261.0,
      "high_low_ratio": 259.0,
      "bb_position": 251.0,
      "ret_3": 229.0,
      "atr_ratio": 227.0,
      "rsi_14": 222.0,
      "ma_ratio_10": 219.0,
      "ret_5": 215.0,
      "time_in_session": 211.0,
      "macd_hist": 207.0,
      "rsi_9": 202.0,
      "ret_10": 199.0,
      "macd_signal": 180.0,
      "ma_ratio_25": 158.0
    },
    "name": "マクニカホールディングス",
    "price": 3213.0,
    "avg_volume": 555100
  },
  "1489.T": {
    "ticker": "1489.T",
    "bullish_prob": 0.0466,
    "bearish_prob": 0.9534,
    "prediction": "bearish",
    "confidence": 0.9067,
    "model_accuracy": 0.6479108635097492,
    "model_trained_at": "2026-07-01T15:08:05.740110",
    "feature_importance": {
      "vol_ratio_5": 313.0,
      "atr_ratio": 312.0,
      "vol_ratio_20": 299.0,
      "ret_5": 298.0,
      "vwap_ratio": 297.0,
      "minute": 273.0,
      "time_in_session": 271.0,
      "rsi_14": 268.0,
      "ret_10": 254.0,
      "ret_3": 242.0,
      "high_low_ratio": 242.0,
      "bb_width": 238.0,
      "macd_signal": 232.0,
      "macd": 229.0,
      "ret_1": 207.0,
      "macd_hist": 205.0,
      "bb_position": 202.0,
      "ma_ratio_10": 191.0,
      "ma_ratio_5": 188.0,
      "rsi_9": 181.0
    },
    "name": "ＮＥＸＴ　ＦＵＮＤＳ　日経平均高配当株５０指数連動型上場投信",
    "price": 3183.0,
    "avg_volume": 553523
  },
  "1980.T": {
    "ticker": "1980.T",
    "bullish_prob": 0.2336,
    "bearish_prob": 0.7664,
    "prediction": "bearish",
    "confidence": 0.5327,
    "model_accuracy": 0.5444126074498568,
    "model_trained_at": "2026-07-01T15:08:10.042186",
    "feature_importance": {
      "vol_ratio_5": 345.0,
      "atr_ratio": 305.0,
      "ret_1": 244.0,
      "ret_5": 243.0,
      "vwap_ratio": 238.0,
      "minute": 234.0,
      "time_in_session": 230.0,
      "ret_3": 226.0,
      "vol_ratio_20": 225.0,
      "rsi_9": 222.0,
      "high_low_ratio": 218.0,
      "macd_signal": 215.0,
      "ret_10": 213.0,
      "macd_hist": 197.0,
      "ma_ratio_5": 193.0,
      "bb_width": 172.0,
      "bb_position": 172.0,
      "rsi_14": 171.0,
      "macd": 159.0,
      "ma_ratio_10": 153.0
    },
    "name": "ダイダン",
    "price": 2896.0,
    "avg_volume": 551420
  },
  "2282.T": {
    "ticker": "2282.T",
    "bullish_prob": 0.2986,
    "bearish_prob": 0.7014,
    "prediction": "bearish",
    "confidence": 0.4027,
    "model_accuracy": 0.5666666666666667,
    "model_trained_at": "2026-07-01T15:08:14.199718",
    "feature_importance": {
      "vol_ratio_20": 380.0,
      "vwap_ratio": 301.0,
      "vol_ratio_5": 292.0,
      "atr_ratio": 280.0,
      "rsi_14": 263.0,
      "ret_3": 260.0,
      "macd_hist": 250.0,
      "time_in_session": 243.0,
      "minute": 224.0,
      "ma_ratio_5": 217.0,
      "ret_10": 215.0,
      "ret_1": 214.0,
      "ma_ratio_25": 205.0,
      "bb_width": 195.0,
      "ma_ratio_10": 188.0,
      "macd_signal": 180.0,
      "rsi_9": 176.0,
      "high_low_ratio": 176.0,
      "ret_5": 169.0,
      "ma_ratio_20": 168.0
    },
    "name": "日本ハム",
    "price": 6011.0,
    "avg_volume": 537160
  },
  "1365.T": {
    "ticker": "1365.T",
    "bullish_prob": 0.1335,
    "bearish_prob": 0.8665,
    "prediction": "bearish",
    "confidence": 0.7331,
    "model_accuracy": 0.5325842696629214,
    "model_trained_at": "2026-07-01T15:08:18.526545",
    "feature_importance": {
      "vol_ratio_20": 369.0,
      "vwap_ratio": 334.0,
      "ret_1": 332.0,
      "vol_ratio_5": 318.0,
      "macd_hist": 284.0,
      "atr_ratio": 275.0,
      "rsi_9": 269.0,
      "ret_5": 268.0,
      "time_in_session": 268.0,
      "high_low_ratio": 264.0,
      "bb_width": 263.0,
      "rsi_14": 254.0,
      "minute": 242.0,
      "ret_3": 231.0,
      "body_ratio": 229.0,
      "ma_ratio_5": 228.0,
      "ma_ratio_10": 188.0,
      "bb_position": 177.0,
      "ret_10": 165.0,
      "macd": 162.0
    },
    "name": "ｉＦｒｅｅＥＴＦ　日経平均レバレッジ・インデックス",
    "price": 4940.0,
    "avg_volume": 532786
  },
  "3291.T": {
    "ticker": "3291.T",
    "bullish_prob": 0.0735,
    "bearish_prob": 0.9265,
    "prediction": "bearish",
    "confidence": 0.853,
    "model_accuracy": 0.6134556574923548,
    "model_trained_at": "2026-07-01T15:08:22.921135",
    "feature_importance": {
      "vwap_ratio": 390.0,
      "vol_ratio_20": 328.0,
      "minute": 305.0,
      "vol_ratio_5": 304.0,
      "rsi_14": 289.0,
      "ret_3": 261.0,
      "atr_ratio": 256.0,
      "ma_ratio_10": 234.0,
      "ret_1": 233.0,
      "ma_ratio_5": 230.0,
      "high_low_ratio": 230.0,
      "macd_signal": 229.0,
      "time_in_session": 227.0,
      "ret_10": 202.0,
      "bb_width": 193.0,
      "ret_5": 190.0,
      "rsi_9": 187.0,
      "macd": 187.0,
      "macd_hist": 187.0,
      "ma_ratio_50": 185.0
    },
    "name": "飯田グループホールディングス",
    "price": 2174.0,
    "avg_volume": 525800
  },
  "1961.T": {
    "ticker": "1961.T",
    "bullish_prob": 0.0592,
    "bearish_prob": 0.9408,
    "prediction": "bearish",
    "confidence": 0.8816,
    "model_accuracy": 0.7395833333333334,
    "model_trained_at": "2026-07-01T15:08:31.224530",
    "feature_importance": {
      "vol_ratio_20": 405.0,
      "vwap_ratio": 342.0,
      "vol_ratio_5": 331.0,
      "atr_ratio": 300.0,
      "minute": 298.0,
      "ma_ratio_5": 265.0,
      "bb_width": 263.0,
      "time_in_session": 263.0,
      "macd_signal": 261.0,
      "rsi_9": 250.0,
      "ret_3": 240.0,
      "ret_5": 240.0,
      "ma_ratio_10": 238.0,
      "macd_hist": 236.0,
      "ret_1": 220.0,
      "ma_ratio_50": 214.0,
      "rsi_14": 212.0,
      "bb_position": 179.0,
      "high_low_ratio": 178.0,
      "macd": 173.0
    },
    "name": "三機工業",
    "price": 3027.0,
    "avg_volume": 524560
  },
  "2982.T": {
    "ticker": "2982.T",
    "bullish_prob": 0.0639,
    "bearish_prob": 0.9361,
    "prediction": "bearish",
    "confidence": 0.8721,
    "model_accuracy": 0.9044943820224718,
    "model_trained_at": "2026-07-01T15:08:27.071122",
    "feature_importance": {
      "vol_ratio_5": 308.0,
      "atr_ratio": 285.0,
      "vol_ratio_20": 279.0,
      "vwap_ratio": 268.0,
      "time_in_session": 259.0,
      "bb_width": 252.0,
      "macd_hist": 248.0,
      "rsi_14": 230.0,
      "macd": 227.0,
      "ma_ratio_5": 221.0,
      "minute": 215.0,
      "ma_ratio_10": 201.0,
      "ma_ratio_25": 192.0,
      "bb_position": 189.0,
      "macd_signal": 167.0,
      "ret_3": 152.0,
      "ret_1": 136.0,
      "ret_10": 134.0,
      "ma_ratio_50": 121.0,
      "ret_5": 119.0
    },
    "name": "ＡＤワークスグループ",
    "price": 398.0,
    "avg_volume": 523340
  }
}